Workbook
Name cfgBodega: '01_CONFIG'!$C$11
Name cfgDiasSinRotacion: '01_CONFIG'!$C$14
Name cfgEdicion: '01_CONFIG'!$C$17
Name cfgEmpresa: '01_CONFIG'!$C$9
Name cfgFechaBuild: '01_CONFIG'!$C$18
Name cfgFechaMin: '01_CONFIG'!$C$15
Name cfgMargenAlerta: '01_CONFIG'!$C$13
Name cfgMoneda: '01_CONFIG'!$C$12
Name cfgNIT: '01_CONFIG'!$C$10
Name cfgProveedor: '01_CONFIG'!$C$19
Name cfgSelladoHasta: '01_CONFIG'!$C$20
Name cfgVersion: '01_CONFIG'!$C$16
Name ctFecha: '13_CONTEO'!$K$5
Name ctResponsable: '13_CONTEO'!$M$5
Name irBitacora: INDEX('10_MOVIMIENTOS'!$C:$C,MIN(kpiFilaLibreMov,5007))
Name irConsultar: '17_KARDEX'!$H$8
Name irFilaLibreProd: INDEX('05_PRODUCTOS'!$B:$B,MIN(kpiFilaLibreProd,507))
Name irFilaLibreProv: INDEX('04_PROVEEDORES'!$B:$B,MIN(kpiFilaLibreProv,107))
Name irPrimerAdvertencia: INDEX(tblMovimientos[Fecha],MATCH("⚠*",tblMovimientos[Estado],0))
Name irPrimerError: INDEX(tblMovimientos[Fecha],MATCH("✖*",tblMovimientos[Estado],0))
Name irPrimerosPasos: '99_AYUDA'!$B$9
Name irRegistrar: irBitacora
Name irSiguientePaso: CHOOSE(kpiPaso,irPrimerError,irPrimerosPasos,irFilaLibreProd,irRegistrar,irPrimerAdvertencia,'13_CONTEO'!$I$8,'18_PEDIDO'!$D$10,'18_PEDIDO'!$D$10,'15_STOCK'!$A$1,'15_STOCK'!$A$1)
Name kpiActivos: '91_KPIS'!$C$9
Name kpiAdvertencias: '91_KPIS'!$C$34
Name kpiAgotados: '91_KPIS'!$C$11
Name kpiBajos: '91_KPIS'!$C$13
Name kpiCapacidad: '91_KPIS'!$C$24
Name kpiCatalogo: '91_KPIS'!$C$8
Name kpiCategorias: '91_KPIS'!$C$22
Name kpiConSaldoInicial: '91_KPIS'!$C$35
Name kpiConteoContados: '91_KPIS'!$C$37
Name kpiConteoDif: '91_KPIS'!$C$38
Name kpiConteoValor: '91_KPIS'!$C$39
Name kpiCriticos: '91_KPIS'!$C$12
Name kpiEgrMes: '91_KPIS'!$C$31
Name kpiEnAlerta: '91_KPIS'!$C$17
Name kpiErrores: '91_KPIS'!$C$33
Name kpiFilaLibreMov: '91_KPIS'!$C$26
Name kpiFilaLibreProd: '91_KPIS'!$C$27
Name kpiFilaLibreProv: '91_KPIS'!$C$28
Name kpiInactivos: '91_KPIS'!$C$16
Name kpiInconsistentes: '91_KPIS'!$C$10
Name kpiIngMes: '91_KPIS'!$C$30
Name kpiMovMes: '91_KPIS'!$C$29
Name kpiOperativos: '91_KPIS'!$C$36
Name kpiOptimos: '91_KPIS'!$C$14
Name kpiPaso: '91_KPIS'!$C$51
Name kpiPasoNivel: '91_KPIS'!$C$52
Name kpiPedidoLineas: '91_KPIS'!$C$41
Name kpiPedidoProv: '91_KPIS'!$C$43
Name kpiPedidoTotal: '91_KPIS'!$C$42
Name kpiProveedores: '91_KPIS'!$C$21
Name kpiRegistros: '91_KPIS'!$C$23
Name kpiSinRotacion: '91_KPIS'!$C$19
Name kpiSobrestock: '91_KPIS'!$C$15
Name kpiUltFecha: '91_KPIS'!$C$32
Name kpiUltimoID: '91_KPIS'!$C$25
Name kpiValor: '91_KPIS'!$C$18
Name kpiValorSinRot: '91_KPIS'!$C$20

Sheet 00_PORTADA
D2: M-INV · Sistema de Inventarios | J2: =TODAY() -> 46290
D3: =txtEmpresa -> NOMBRE DE SU EMPRESA · Bodega principal | J3: M-INV V1.2.0
B6: PRÓXIMO PASO | C6: =txtPaso -> ① Primeros pasos: el administrador debe personalizar el nombre de la empresa y las categorías.
B10: ▍ INDICADORES CLAVE | J10: =txtIntegridad -> ✔ Bitácora íntegra · sin errores
B15: ▍ ANÁLISIS DEL INVENTARIO
B19: ▍ ÚLTIMOS MOVIMIENTOS
B20: Fecha | C20: Tipo | D20: Producto | I20: Cantidad | J20: Unidad | K20: Responsable | M20: Documento
B21: =IF(kpiUltimoID-0<1,"",INDEX(tblMovimientos[Fecha],kpiUltimoID-0)) | C21: =IF(kpiUltimoID-0<1,"",INDEX(tblMovimientos[Tipo],kpiUltimoID-0)&"") | D21: =IF(kpiUltimoID-0<1,"",INDEX(tblMovimientos[Producto],kpiUltimoID-0)&"") | I21: =IF(kpiUltimoID-0<1,"",INDEX(tblMovimientos[CantidadNeta],kpiUltimoID-0)) | J21: =IF(kpiUltimoID-0<1,"",INDEX(tblMovimientos[Unidad],kpiUltimoID-0)&"") | K21: =IF(kpiUltimoID-0<1,"",INDEX(tblMovimientos[Responsable],kpiUltimoID-0)&"") | M21: =IF(kpiUltimoID-0<1,"",INDEX(tblMovimientos[Documento],kpiUltimoID-0)&"")
B22: =IF(kpiUltimoID-1<1,"",INDEX(tblMovimientos[Fecha],kpiUltimoID-1)) | C22: =IF(kpiUltimoID-1<1,"",INDEX(tblMovimientos[Tipo],kpiUltimoID-1)&"") | D22: =IF(kpiUltimoID-1<1,"",INDEX(tblMovimientos[Producto],kpiUltimoID-1)&"") | I22: =IF(kpiUltimoID-1<1,"",INDEX(tblMovimientos[CantidadNeta],kpiUltimoID-1)) | J22: =IF(kpiUltimoID-1<1,"",INDEX(tblMovimientos[Unidad],kpiUltimoID-1)&"") | K22: =IF(kpiUltimoID-1<1,"",INDEX(tblMovimientos[Responsable],kpiUltimoID-1)&"") | M22: =IF(kpiUltimoID-1<1,"",INDEX(tblMovimientos[Documento],kpiUltimoID-1)&"")
B23: =IF(kpiUltimoID-2<1,"",INDEX(tblMovimientos[Fecha],kpiUltimoID-2)) | C23: =IF(kpiUltimoID-2<1,"",INDEX(tblMovimientos[Tipo],kpiUltimoID-2)&"") | D23: =IF(kpiUltimoID-2<1,"",INDEX(tblMovimientos[Producto],kpiUltimoID-2)&"") | I23: =IF(kpiUltimoID-2<1,"",INDEX(tblMovimientos[CantidadNeta],kpiUltimoID-2)) | J23: =IF(kpiUltimoID-2<1,"",INDEX(tblMovimientos[Unidad],kpiUltimoID-2)&"") | K23: =IF(kpiUltimoID-2<1,"",INDEX(tblMovimientos[Responsable],kpiUltimoID-2)&"") | M23: =IF(kpiUltimoID-2<1,"",INDEX(tblMovimientos[Documento],kpiUltimoID-2)&"")
B24: =IF(kpiUltimoID-3<1,"",INDEX(tblMovimientos[Fecha],kpiUltimoID-3)) | C24: =IF(kpiUltimoID-3<1,"",INDEX(tblMovimientos[Tipo],kpiUltimoID-3)&"") | D24: =IF(kpiUltimoID-3<1,"",INDEX(tblMovimientos[Producto],kpiUltimoID-3)&"") | I24: =IF(kpiUltimoID-3<1,"",INDEX(tblMovimientos[CantidadNeta],kpiUltimoID-3)) | J24: =IF(kpiUltimoID-3<1,"",INDEX(tblMovimientos[Unidad],kpiUltimoID-3)&"") | K24: =IF(kpiUltimoID-3<1,"",INDEX(tblMovimientos[Responsable],kpiUltimoID-3)&"") | M24: =IF(kpiUltimoID-3<1,"",INDEX(tblMovimientos[Documento],kpiUltimoID-3)&"")
B25: =IF(kpiUltimoID-4<1,"",INDEX(tblMovimientos[Fecha],kpiUltimoID-4)) | C25: =IF(kpiUltimoID-4<1,"",INDEX(tblMovimientos[Tipo],kpiUltimoID-4)&"") | D25: =IF(kpiUltimoID-4<1,"",INDEX(tblMovimientos[Producto],kpiUltimoID-4)&"") | I25: =IF(kpiUltimoID-4<1,"",INDEX(tblMovimientos[CantidadNeta],kpiUltimoID-4)) | J25: =IF(kpiUltimoID-4<1,"",INDEX(tblMovimientos[Unidad],kpiUltimoID-4)&"") | K25: =IF(kpiUltimoID-4<1,"",INDEX(tblMovimientos[Responsable],kpiUltimoID-4)&"") | M25: =IF(kpiUltimoID-4<1,"",INDEX(tblMovimientos[Documento],kpiUltimoID-4)&"")
B26: =IF(kpiUltimoID-5<1,"",INDEX(tblMovimientos[Fecha],kpiUltimoID-5)) | C26: =IF(kpiUltimoID-5<1,"",INDEX(tblMovimientos[Tipo],kpiUltimoID-5)&"") | D26: =IF(kpiUltimoID-5<1,"",INDEX(tblMovimientos[Producto],kpiUltimoID-5)&"") | I26: =IF(kpiUltimoID-5<1,"",INDEX(tblMovimientos[CantidadNeta],kpiUltimoID-5)) | J26: =IF(kpiUltimoID-5<1,"",INDEX(tblMovimientos[Unidad],kpiUltimoID-5)&"") | K26: =IF(kpiUltimoID-5<1,"",INDEX(tblMovimientos[Responsable],kpiUltimoID-5)&"") | M26: =IF(kpiUltimoID-5<1,"",INDEX(tblMovimientos[Documento],kpiUltimoID-5)&"")
B27: =IF(kpiUltimoID-6<1,"",INDEX(tblMovimientos[Fecha],kpiUltimoID-6)) | C27: =IF(kpiUltimoID-6<1,"",INDEX(tblMovimientos[Tipo],kpiUltimoID-6)&"") | D27: =IF(kpiUltimoID-6<1,"",INDEX(tblMovimientos[Producto],kpiUltimoID-6)&"") | I27: =IF(kpiUltimoID-6<1,"",INDEX(tblMovimientos[CantidadNeta],kpiUltimoID-6)) | J27: =IF(kpiUltimoID-6<1,"",INDEX(tblMovimientos[Unidad],kpiUltimoID-6)&"") | K27: =IF(kpiUltimoID-6<1,"",INDEX(tblMovimientos[Responsable],kpiUltimoID-6)&"") | M27: =IF(kpiUltimoID-6<1,"",INDEX(tblMovimientos[Documento],kpiUltimoID-6)&"")
B28: =IF(kpiUltimoID-7<1,"",INDEX(tblMovimientos[Fecha],kpiUltimoID-7)) | C28: =IF(kpiUltimoID-7<1,"",INDEX(tblMovimientos[Tipo],kpiUltimoID-7)&"") | D28: =IF(kpiUltimoID-7<1,"",INDEX(tblMovimientos[Producto],kpiUltimoID-7)&"") | I28: =IF(kpiUltimoID-7<1,"",INDEX(tblMovimientos[CantidadNeta],kpiUltimoID-7)) | J28: =IF(kpiUltimoID-7<1,"",INDEX(tblMovimientos[Unidad],kpiUltimoID-7)&"") | K28: =IF(kpiUltimoID-7<1,"",INDEX(tblMovimientos[Responsable],kpiUltimoID-7)&"") | M28: =IF(kpiUltimoID-7<1,"",INDEX(tblMovimientos[Documento],kpiUltimoID-7)&"")
B30: M-INV V1.2.0 · CQRS: escritura en 10_MOVIMIENTOS → lectura en 15_STOCK y 16_ALERTAS · Z&P Software Fast Solutions | J30: =txtBitacora -> Bitácora: 0 de 5.000 registros · 0% de capacidad

Sheet 01_CONFIG
B2: Configuración del sistema
B3: Capa de configuración (oculta) · Solo administrador · Cambios aquí afectan todo el libro
B7: PARÁMETROS DEL TENANT
B8: Parámetro | C8: Valor | D8: Descripción
B9: Empresa (cliente) | C9: NOMBRE DE SU EMPRESA | D9: Nombre que aparece en la portada y en los documentos.
B10: NIT / Identificación | D10: Identificación tributaria del cliente.
B11: Sede / Bodega | C11: Bodega principal | D11: Ubicación física que controla este libro (un libro por bodega en V1).
B12: Moneda | C12: COP | D12: Informativo. Los formatos de valor usan el símbolo $.
B13: Margen de alerta preventiva | C13: 0.2 | D13: Un producto pasa a BAJO cuando su stock es ≤ Mínimo × (1 + margen).
B14: Días para considerar sin rotación | C14: 60 | D14: Productos con stock y sin movimientos en este plazo se marcan como inventario inmovilizado.
B15: Fecha mínima permitida | C15: 43831 | D15: Fechas anteriores son rechazadas por la validación de la bitácora y del formulario.
B16: Versión del sistema | C16: 1.2.0 | D16: Versión del motor M-INV.
B17: Edición | C17: Estándar | D17: Estándar = .xlsx sin macros · Plus = .xlsm con formulario guiado y automatizaciones.
B18: Fecha de generación | C18: 46290 | D18: Fecha en que se generó este libro.
B19: Implementado por | C19: Z&P Software Fast Solutions | D19: Proveedor del software.
B20: Bitácora sellada hasta el ID | C20: 0 | D20: Lo actualiza la edición Plus al sellar registros (no editar a mano).
B22: TIPOS DE MOVIMIENTO (definen el FactorStock de la bitácora)
B23: Tipo | C23: FactorStock | D23: Descripción
B24: SALDO INICIAL | C24: 1 | D24: Carga del inventario existente al implementar el sistema (una vez por producto).
B25: ENTRADA | C25: 1 | D25: Compra, recepción de mercancía o devolución de un cliente.
B26: SALIDA | C26: -1 | D26: Venta, despacho a cliente o consumo interno.
B27: AJUSTE (+) | C27: 1 | D27: Sobrante encontrado en conteo físico. Exige observación.
B28: AJUSTE (-) | C28: -1 | D28: Merma, daño, pérdida o faltante en conteo físico. Exige observación.
B30: SEMÁFORO DE STOCK (reglas de 15_STOCK, 16_ALERTAS y 18_PEDIDO)
B31: Estado | C31: Prioridad | D31: Regla | E31: Acción
B32: INCONSISTENTE | C32: 1 | D32: Stock negativo: se registraron salidas mayores a lo disponible. | E32: Auditar la bitácora y registrar un AJUSTE
B33: AGOTADO | C33: 2 | D33: Stock en cero. | E33: Reabastecer de inmediato
B34: CRÍTICO | C34: 3 | D34: Stock en o por debajo del mínimo. | E34: Emitir orden de compra
B35: BAJO | C35: 4 | D35: Stock cercano al mínimo (dentro del margen de alerta). | E35: Programar reposición
B36: ÓPTIMO | C36: 5 | D36: Stock entre el margen de alerta y el máximo. | E36: Sin acción
B37: SOBRESTOCK | C37: 6 | D37: Stock por encima del máximo. | E37: Frenar compras / rotar inventario
B38: INACTIVO | C38: 7 | D38: Producto descontinuado (Activo = NO). | E38: Sin acción
B40: RESPONSABLES (listas de la bitácora, el formulario y la toma física)
B41: Nombre | C41: Cargo
B42: ADMINISTRADOR | C42: Administrador del sistema
B43: BODEGA | C43: Operador de bodega
B44: COMPRAS | C44: Responsable de compras

Sheet 03_CATEGORIAS
B2: Categorías
B3: Capa de configuración (oculta) · Primer nivel de la lista en cascada
B7: Código | C7: Categoría | D7: Descripción
B8: MP | C8: MATERIA PRIMA | D8: Insumos que se transforman en producto
B9: PT | C9: PRODUCTO TERMINADO | D9: Artículos listos para la venta
B10: INS | C10: INSUMOS | D10: Materiales de consumo de la operación
B11: REP | C11: REPUESTOS | D11: Partes y repuestos de mantenimiento
B12: EMP | C12: EMPAQUES | D12: Material de empaque y embalaje
B13: GEN | C13: GENERAL | D13: Artículos sin categoría específica

Sheet 04_PROVEEDORES
B2: Proveedores
B3: Datos maestros · Quién le vende cada producto y en cuántos días entrega
B6: ✎ | C6: ✎ | D6: ✎ | E6: ✎ | F6: ✎ | G6: ✎ | H6: ƒx | I6: ƒx | J6: ƒx
B7: Proveedor | C7: NIT | D7: Contacto | E7: Teléfono | F7: Correo | G7: DiasEntrega | H7: Productos | I7: EnAlerta | J7: Validación
H8: =IF(tblProveedores[[#This Row],[Proveedor]]="","",COUNTIF(tblProductos[Proveedor],tblProveedores[[#This Row],[Proveedor]])) | I8: =IF(tblProveedores[[#This Row],[Proveedor]]="","",SUMPRODUCT(COUNTIFS(tblStock[Proveedor],tblProveedores[[#This Row],[Proveedor]],tblStock[Estado],{"INCONSISTENTE","AGOTADO","CRÍTICO","BAJO"}))) | J8: =IF(AND(tblProveedores[[#This Row],[Proveedor]]="",tblProveedores[[#This Row],[NIT]]="",tblProveedores[[#This Row],[Contacto]]="",tblProveedores[[#This Row],[Correo]]=""),"",IF(tblProveedores[[#This Row],[Proveedor]]="","⚠ Falta el nombre",IF(COUNTIF(tblProveedores[Proveedor],tblProveedores[[#This Row],[Proveedor]])>1,"✖ Proveedor duplicado",IF(AND(tblProveedores[[#This Row],[Correo]]<>"",ISERROR(FIND("@",tblProveedores[[#This Row],[Correo]]))),"⚠ Correo no válido","✔ OK"))))
H9: =IF(tblProveedores[[#This Row],[Proveedor]]="","",COUNTIF(tblProductos[Proveedor],tblProveedores[[#This Row],[Proveedor]])) | I9: =IF(tblProveedores[[#This Row],[Proveedor]]="","",SUMPRODUCT(COUNTIFS(tblStock[Proveedor],tblProveedores[[#This Row],[Proveedor]],tblStock[Estado],{"INCONSISTENTE","AGOTADO","CRÍTICO","BAJO"}))) | J9: =IF(AND(tblProveedores[[#This Row],[Proveedor]]="",tblProveedores[[#This Row],[NIT]]="",tblProveedores[[#This Row],[Contacto]]="",tblProveedores[[#This Row],[Correo]]=""),"",IF(tblProveedores[[#This Row],[Proveedor]]="","⚠ Falta el nombre",IF(COUNTIF(tblProveedores[Proveedor],tblProveedores[[#This Row],[Proveedor]])>1,"✖ Proveedor duplicado",IF(AND(tblProveedores[[#This Row],[Correo]]<>"",ISERROR(FIND("@",tblProveedores[[#This Row],[Correo]]))),"⚠ Correo no válido","✔ OK"))))
H10: =IF(tblProveedores[[#This Row],[Proveedor]]="","",COUNTIF(tblProductos[Proveedor],tblProveedores[[#This Row],[Proveedor]])) | I10: =IF(tblProveedores[[#This Row],[Proveedor]]="","",SUMPRODUCT(COUNTIFS(tblStock[Proveedor],tblProveedores[[#This Row],[Proveedor]],tblStock[Estado],{"INCONSISTENTE","AGOTADO","CRÍTICO","BAJO"}))) | J10: =IF(AND(tblProveedores[[#This Row],[Proveedor]]="",tblProveedores[[#This Row],[NIT]]="",tblProveedores[[#This Row],[Contacto]]="",tblProveedores[[#This Row],[Correo]]=""),"",IF(tblProveedores[[#This Row],[Proveedor]]="","⚠ Falta el nombre",IF(COUNTIF(tblProveedores[Proveedor],tblProveedores[[#This Row],[Proveedor]])>1,"✖ Proveedor duplicado",IF(AND(tblProveedores[[#This Row],[Correo]]<>"",ISERROR(FIND("@",tblProveedores[[#This Row],[Correo]]))),"⚠ Correo no válido","✔ OK"))))
H11: =IF(tblProveedores[[#This Row],[Proveedor]]="","",COUNTIF(tblProductos[Proveedor],tblProveedores[[#This Row],[Proveedor]])) | I11: =IF(tblProveedores[[#This Row],[Proveedor]]="","",SUMPRODUCT(COUNTIFS(tblStock[Proveedor],tblProveedores[[#This Row],[Proveedor]],tblStock[Estado],{"INCONSISTENTE","AGOTADO","CRÍTICO","BAJO"}))) | J11: =IF(AND(tblProveedores[[#This Row],[Proveedor]]="",tblProveedores[[#This Row],[NIT]]="",tblProveedores[[#This Row],[Contacto]]="",tblProveedores[[#This Row],[Correo]]=""),"",IF(tblProveedores[[#This Row],[Proveedor]]="","⚠ Falta el nombre",IF(COUNTIF(tblProveedores[Proveedor],tblProveedores[[#This Row],[Proveedor]])>1,"✖ Proveedor duplicado",IF(AND(tblProveedores[[#This Row],[Correo]]<>"",ISERROR(FIND("@",tblProveedores[[#This Row],[Correo]]))),"⚠ Correo no válido","✔ OK"))))
H12: =IF(tblProveedores[[#This Row],[Proveedor]]="","",COUNTIF(tblProductos[Proveedor],tblProveedores[[#This Row],[Proveedor]])) | I12: =IF(tblProveedores[[#This Row],[Proveedor]]="","",SUMPRODUCT(COUNTIFS(tblStock[Proveedor],tblProveedores[[#This Row],[Proveedor]],tblStock[Estado],{"INCONSISTENTE","AGOTADO","CRÍTICO","BAJO"}))) | J12: =IF(AND(tblProveedores[[#This Row],[Proveedor]]="",tblProveedores[[#This Row],[NIT]]="",tblProveedores[[#This Row],[Contacto]]="",tblProveedores[[#This Row],[Correo]]=""),"",IF(tblProveedores[[#This Row],[Proveedor]]="","⚠ Falta el nombre",IF(COUNTIF(tblProveedores[Proveedor],tblProveedores[[#This Row],[Proveedor]])>1,"✖ Proveedor duplicado",IF(AND(tblProveedores[[#This Row],[Correo]]<>"",ISERROR(FIND("@",tblProveedores[[#This Row],[Correo]]))),"⚠ Correo no válido","✔ OK"))))
H13: =IF(tblProveedores[[#This Row],[Proveedor]]="","",COUNTIF(tblProductos[Proveedor],tblProveedores[[#This Row],[Proveedor]])) | I13: =IF(tblProveedores[[#This Row],[Proveedor]]="","",SUMPRODUCT(COUNTIFS(tblStock[Proveedor],tblProveedores[[#This Row],[Proveedor]],tblStock[Estado],{"INCONSISTENTE","AGOTADO","CRÍTICO","BAJO"}))) | J13: =IF(AND(tblProveedores[[#This Row],[Proveedor]]="",tblProveedores[[#This Row],[NIT]]="",tblProveedores[[#This Row],[Contacto]]="",tblProveedores[[#This Row],[Correo]]=""),"",IF(tblProveedores[[#This Row],[Proveedor]]="","⚠ Falta el nombre",IF(COUNTIF(tblProveedores[Proveedor],tblProveedores[[#This Row],[Proveedor]])>1,"✖ Proveedor duplicado",IF(AND(tblProveedores[[#This Row],[Correo]]<>"",ISERROR(FIND("@",tblProveedores[[#This Row],[Correo]]))),"⚠ Correo no válido","✔ OK"))))
H14: =IF(tblProveedores[[#This Row],[Proveedor]]="","",COUNTIF(tblProductos[Proveedor],tblProveedores[[#This Row],[Proveedor]])) | I14: =IF(tblProveedores[[#This Row],[Proveedor]]="","",SUMPRODUCT(COUNTIFS(tblStock[Proveedor],tblProveedores[[#This Row],[Proveedor]],tblStock[Estado],{"INCONSISTENTE","AGOTADO","CRÍTICO","BAJO"}))) | J14: =IF(AND(tblProveedores[[#This Row],[Proveedor]]="",tblProveedores[[#This Row],[NIT]]="",tblProveedores[[#This Row],[Contacto]]="",tblProveedores[[#This Row],[Correo]]=""),"",IF(tblProveedores[[#This Row],[Proveedor]]="","⚠ Falta el nombre",IF(COUNTIF(tblProveedores[Proveedor],tblProveedores[[#This Row],[Proveedor]])>1,"✖ Proveedor duplicado",IF(AND(tblProveedores[[#This Row],[Correo]]<>"",ISERROR(FIND("@",tblProveedores[[#This Row],[Correo]]))),"⚠ Correo no válido","✔ OK"))))
H15: =IF(tblProveedores[[#This Row],[Proveedor]]="","",COUNTIF(tblProductos[Proveedor],tblProveedores[[#This Row],[Proveedor]])) | I15: =IF(tblProveedores[[#This Row],[Proveedor]]="","",SUMPRODUCT(COUNTIFS(tblStock[Proveedor],tblProveedores[[#This Row],[Proveedor]],tblStock[Estado],{"INCONSISTENTE","AGOTADO","CRÍTICO","BAJO"}))) | J15: =IF(AND(tblProveedores[[#This Row],[Proveedor]]="",tblProveedores[[#This Row],[NIT]]="",tblProveedores[[#This Row],[Contacto]]="",tblProveedores[[#This Row],[Correo]]=""),"",IF(tblProveedores[[#This Row],[Proveedor]]="","⚠ Falta el nombre",IF(COUNTIF(tblProveedores[Proveedor],tblProveedores[[#This Row],[Proveedor]])>1,"✖ Proveedor duplicado",IF(AND(tblProveedores[[#This Row],[Correo]]<>"",ISERROR(FIND("@",tblProveedores[[#This Row],[Correo]]))),"⚠ Correo no válido","✔ OK"))))
H16: =IF(tblProveedores[[#This Row],[Proveedor]]="","",COUNTIF(tblProductos[Proveedor],tblProveedores[[#This Row],[Proveedor]])) | I16: =IF(tblProveedores[[#This Row],[Proveedor]]="","",SUMPRODUCT(COUNTIFS(tblStock[Proveedor],tblProveedores[[#This Row],[Proveedor]],tblStock[Estado],{"INCONSISTENTE","AGOTADO","CRÍTICO","BAJO"}))) | J16: =IF(AND(tblProveedores[[#This Row],[Proveedor]]="",tblProveedores[[#This Row],[NIT]]="",tblProveedores[[#This Row],[Contacto]]="",tblProveedores[[#This Row],[Correo]]=""),"",IF(tblProveedores[[#This Row],[Proveedor]]="","⚠ Falta el nombre",IF(COUNTIF(tblProveedores[Proveedor],tblProveedores[[#This Row],[Proveedor]])>1,"✖ Proveedor duplicado",IF(AND(tblProveedores[[#This Row],[Correo]]<>"",ISERROR(FIND("@",tblProveedores[[#This Row],[Correo]]))),"⚠ Correo no válido","✔ OK"))))
H17: =IF(tblProveedores[[#This Row],[Proveedor]]="","",COUNTIF(tblProductos[Proveedor],tblProveedores[[#This Row],[Proveedor]])) | I17: =IF(tblProveedores[[#This Row],[Proveedor]]="","",SUMPRODUCT(COUNTIFS(tblStock[Proveedor],tblProveedores[[#This Row],[Proveedor]],tblStock[Estado],{"INCONSISTENTE","AGOTADO","CRÍTICO","BAJO"}))) | J17: =IF(AND(tblProveedores[[#This Row],[Proveedor]]="",tblProveedores[[#This Row],[NIT]]="",tblProveedores[[#This Row],[Contacto]]="",tblProveedores[[#This Row],[Correo]]=""),"",IF(tblProveedores[[#This Row],[Proveedor]]="","⚠ Falta el nombre",IF(COUNTIF(tblProveedores[Proveedor],tblProveedores[[#This Row],[Proveedor]])>1,"✖ Proveedor duplicado",IF(AND(tblProveedores[[#This Row],[Correo]]<>"",ISERROR(FIND("@",tblProveedores[[#This Row],[Correo]]))),"⚠ Correo no válido","✔ OK"))))
H18: =IF(tblProveedores[[#This Row],[Proveedor]]="","",COUNTIF(tblProductos[Proveedor],tblProveedores[[#This Row],[Proveedor]])) | I18: =IF(tblProveedores[[#This Row],[Proveedor]]="","",SUMPRODUCT(COUNTIFS(tblStock[Proveedor],tblProveedores[[#This Row],[Proveedor]],tblStock[Estado],{"INCONSISTENTE","AGOTADO","CRÍTICO","BAJO"}))) | J18: =IF(AND(tblProveedores[[#This Row],[Proveedor]]="",tblProveedores[[#This Row],[NIT]]="",tblProveedores[[#This Row],[Contacto]]="",tblProveedores[[#This Row],[Correo]]=""),"",IF(tblProveedores[[#This Row],[Proveedor]]="","⚠ Falta el nombre",IF(COUNTIF(tblProveedores[Proveedor],tblProveedores[[#This Row],[Proveedor]])>1,"✖ Proveedor duplicado",IF(AND(tblProveedores[[#This Row],[Correo]]<>"",ISERROR(FIND("@",tblProveedores[[#This Row],[Correo]]))),"⚠ Correo no válido","✔ OK"))))
H19: =IF(tblProveedores[[#This Row],[Proveedor]]="","",COUNTIF(tblProductos[Proveedor],tblProveedores[[#This Row],[Proveedor]])) | I19: =IF(tblProveedores[[#This Row],[Proveedor]]="","",SUMPRODUCT(COUNTIFS(tblStock[Proveedor],tblProveedores[[#This Row],[Proveedor]],tblStock[Estado],{"INCONSISTENTE","AGOTADO","CRÍTICO","BAJO"}))) | J19: =IF(AND(tblProveedores[[#This Row],[Proveedor]]="",tblProveedores[[#This Row],[NIT]]="",tblProveedores[[#This Row],[Contacto]]="",tblProveedores[[#This Row],[Correo]]=""),"",IF(tblProveedores[[#This Row],[Proveedor]]="","⚠ Falta el nombre",IF(COUNTIF(tblProveedores[Proveedor],tblProveedores[[#This Row],[Proveedor]])>1,"✖ Proveedor duplicado",IF(AND(tblProveedores[[#This Row],[Correo]]<>"",ISERROR(FIND("@",tblProveedores[[#This Row],[Correo]]))),"⚠ Correo no válido","✔ OK"))))
... H107: =IF(tblProveedores[[#This Row],[Proveedor]]="","",COUNTIF(tblProductos[Proveedor],tblProveedores[[#This Row],[Proveedor]])) | I107: =IF(tblProveedores[[#This Row],[Proveedor]]="","",SUMPRODUCT(COUNTIFS(tblStock[Proveedor],tblProveedores[[#This Row],[Proveedor]],tblStock[Estado],{"INCONSISTENTE","AGOTADO","CRÍTICO","BAJO"}))) | J107: =IF(AND(tblProveedores[[#This Row],[Proveedor]]="",tblProveedores[[#This Row],[NIT]]="",tblProveedores[[#This Row],[Contacto]]="",tblProveedores[[#This Row],[Correo]]=""),"",IF(tblProveedores[[#This Row],[Proveedor]]="","⚠ Falta el nombre",IF(COUNTIF(tblProveedores[Proveedor],tblProveedores[[#This Row],[Proveedor]])>1,"✖ Proveedor duplicado",IF(AND(tblProveedores[[#This Row],[Correo]]<>"",ISERROR(FIND("@",tblProveedores[[#This Row],[Correo]]))),"⚠ Correo no válido","✔ OK"))))

Sheet 05_PRODUCTOS
B2: Catálogo de productos
B3: Datos maestros · Cada producto se registra una sola vez · Nunca borre filas (use Activo = NO)
B6: ✎ | C6: ✎ | D6: ✎ | E6: ✎ | F6: ✎ | G6: ✎ | H6: ✎ | I6: ✎ | J6: ✎ | K6: ✎ | L6: ƒx | M6: ƒx | N6: ƒx
B7: SKU | C7: Producto | D7: Categoría | E7: Unidad | F7: StockMin | G7: StockMax | H7: CostoUnitario | I7: Proveedor | J7: Ubicación | K7: Activo | L7: Etiqueta | M7: Movimientos | N7: Validación
L8: =IF(OR(tblProductos[[#This Row],[SKU]]="",tblProductos[[#This Row],[Producto]]=""),"",tblProductos[[#This Row],[SKU]]&" · "&tblProductos[[#This Row],[Producto]]) | M8: =IF(tblProductos[[#This Row],[SKU]]="","",COUNTIF(tblMovimientos[SKU],tblProductos[[#This Row],[SKU]])) | N8: =IF(AND(tblProductos[[#This Row],[SKU]]="",tblProductos[[#This Row],[Producto]]=""),"",IF(OR(tblProductos[[#This Row],[SKU]]="",tblProductos[[#This Row],[Producto]]="",tblProductos[[#This Row],[Categoría]]="",tblProductos[[#This Row],[Unidad]]=""),"⚠ Faltan datos",IF(COUNTIF(tblProductos[SKU],tblProductos[[#This Row],[SKU]])>1,"✖ SKU duplicado",IF(ISNUMBER(FIND(" ",tblProductos[[#This Row],[SKU]])),"✖ SKU con espacios",IF(ISNA(MATCH(tblProductos[[#This Row],[Categoría]],lstCategorias,0)),"✖ Categoría no existe",IF(ISNA(MATCH(tblProductos[[#This Row],[Unidad]],lstUniCod,0)),"✖ Unidad no existe",IF(AND(tblProductos[[#This Row],[Proveedor]]<>"",ISNA(MATCH(tblProductos[[#This Row],[Proveedor]],tblProveedores[Proveedor],0))),"✖ Proveedor no existe",IF(AND(N(tblProductos[[#This Row],[StockMax]])>0,N(tblProductos[[#This Row],[StockMin]])>N(tblProductos[[#This Row],[StockMax]])),"⚠ Mínimo mayor que máximo",IF(tblProductos[[#This Row],[Activo]]="NO","● Inactivo","✔ OK")))))))))
L9: =IF(OR(tblProductos[[#This Row],[SKU]]="",tblProductos[[#This Row],[Producto]]=""),"",tblProductos[[#This Row],[SKU]]&" · "&tblProductos[[#This Row],[Producto]]) | M9: =IF(tblProductos[[#This Row],[SKU]]="","",COUNTIF(tblMovimientos[SKU],tblProductos[[#This Row],[SKU]])) | N9: =IF(AND(tblProductos[[#This Row],[SKU]]="",tblProductos[[#This Row],[Producto]]=""),"",IF(OR(tblProductos[[#This Row],[SKU]]="",tblProductos[[#This Row],[Producto]]="",tblProductos[[#This Row],[Categoría]]="",tblProductos[[#This Row],[Unidad]]=""),"⚠ Faltan datos",IF(COUNTIF(tblProductos[SKU],tblProductos[[#This Row],[SKU]])>1,"✖ SKU duplicado",IF(ISNUMBER(FIND(" ",tblProductos[[#This Row],[SKU]])),"✖ SKU con espacios",IF(ISNA(MATCH(tblProductos[[#This Row],[Categoría]],lstCategorias,0)),"✖ Categoría no existe",IF(ISNA(MATCH(tblProductos[[#This Row],[Unidad]],lstUniCod,0)),"✖ Unidad no existe",IF(AND(tblProductos[[#This Row],[Proveedor]]<>"",ISNA(MATCH(tblProductos[[#This Row],[Proveedor]],tblProveedores[Proveedor],0))),"✖ Proveedor no existe",IF(AND(N(tblProductos[[#This Row],[StockMax]])>0,N(tblProductos[[#This Row],[StockMin]])>N(tblProductos[[#This Row],[StockMax]])),"⚠ Mínimo mayor que máximo",IF(tblProductos[[#This Row],[Activo]]="NO","● Inactivo","✔ OK")))))))))
L10: =IF(OR(tblProductos[[#This Row],[SKU]]="",tblProductos[[#This Row],[Producto]]=""),"",tblProductos[[#This Row],[SKU]]&" · "&tblProductos[[#This Row],[Producto]]) | M10: =IF(tblProductos[[#This Row],[SKU]]="","",COUNTIF(tblMovimientos[SKU],tblProductos[[#This Row],[SKU]])) | N10: =IF(AND(tblProductos[[#This Row],[SKU]]="",tblProductos[[#This Row],[Producto]]=""),"",IF(OR(tblProductos[[#This Row],[SKU]]="",tblProductos[[#This Row],[Producto]]="",tblProductos[[#This Row],[Categoría]]="",tblProductos[[#This Row],[Unidad]]=""),"⚠ Faltan datos",IF(COUNTIF(tblProductos[SKU],tblProductos[[#This Row],[SKU]])>1,"✖ SKU duplicado",IF(ISNUMBER(FIND(" ",tblProductos[[#This Row],[SKU]])),"✖ SKU con espacios",IF(ISNA(MATCH(tblProductos[[#This Row],[Categoría]],lstCategorias,0)),"✖ Categoría no existe",IF(ISNA(MATCH(tblProductos[[#This Row],[Unidad]],lstUniCod,0)),"✖ Unidad no existe",IF(AND(tblProductos[[#This Row],[Proveedor]]<>"",ISNA(MATCH(tblProductos[[#This Row],[Proveedor]],tblProveedores[Proveedor],0))),"✖ Proveedor no existe",IF(AND(N(tblProductos[[#This Row],[StockMax]])>0,N(tblProductos[[#This Row],[StockMin]])>N(tblProductos[[#This Row],[StockMax]])),"⚠ Mínimo mayor que máximo",IF(tblProductos[[#This Row],[Activo]]="NO","● Inactivo","✔ OK")))))))))
L11: =IF(OR(tblProductos[[#This Row],[SKU]]="",tblProductos[[#This Row],[Producto]]=""),"",tblProductos[[#This Row],[SKU]]&" · "&tblProductos[[#This Row],[Producto]]) | M11: =IF(tblProductos[[#This Row],[SKU]]="","",COUNTIF(tblMovimientos[SKU],tblProductos[[#This Row],[SKU]])) | N11: =IF(AND(tblProductos[[#This Row],[SKU]]="",tblProductos[[#This Row],[Producto]]=""),"",IF(OR(tblProductos[[#This Row],[SKU]]="",tblProductos[[#This Row],[Producto]]="",tblProductos[[#This Row],[Categoría]]="",tblProductos[[#This Row],[Unidad]]=""),"⚠ Faltan datos",IF(COUNTIF(tblProductos[SKU],tblProductos[[#This Row],[SKU]])>1,"✖ SKU duplicado",IF(ISNUMBER(FIND(" ",tblProductos[[#This Row],[SKU]])),"✖ SKU con espacios",IF(ISNA(MATCH(tblProductos[[#This Row],[Categoría]],lstCategorias,0)),"✖ Categoría no existe",IF(ISNA(MATCH(tblProductos[[#This Row],[Unidad]],lstUniCod,0)),"✖ Unidad no existe",IF(AND(tblProductos[[#This Row],[Proveedor]]<>"",ISNA(MATCH(tblProductos[[#This Row],[Proveedor]],tblProveedores[Proveedor],0))),"✖ Proveedor no existe",IF(AND(N(tblProductos[[#This Row],[StockMax]])>0,N(tblProductos[[#This Row],[StockMin]])>N(tblProductos[[#This Row],[StockMax]])),"⚠ Mínimo mayor que máximo",IF(tblProductos[[#This Row],[Activo]]="NO","● Inactivo","✔ OK")))))))))
L12: =IF(OR(tblProductos[[#This Row],[SKU]]="",tblProductos[[#This Row],[Producto]]=""),"",tblProductos[[#This Row],[SKU]]&" · "&tblProductos[[#This Row],[Producto]]) | M12: =IF(tblProductos[[#This Row],[SKU]]="","",COUNTIF(tblMovimientos[SKU],tblProductos[[#This Row],[SKU]])) | N12: =IF(AND(tblProductos[[#This Row],[SKU]]="",tblProductos[[#This Row],[Producto]]=""),"",IF(OR(tblProductos[[#This Row],[SKU]]="",tblProductos[[#This Row],[Producto]]="",tblProductos[[#This Row],[Categoría]]="",tblProductos[[#This Row],[Unidad]]=""),"⚠ Faltan datos",IF(COUNTIF(tblProductos[SKU],tblProductos[[#This Row],[SKU]])>1,"✖ SKU duplicado",IF(ISNUMBER(FIND(" ",tblProductos[[#This Row],[SKU]])),"✖ SKU con espacios",IF(ISNA(MATCH(tblProductos[[#This Row],[Categoría]],lstCategorias,0)),"✖ Categoría no existe",IF(ISNA(MATCH(tblProductos[[#This Row],[Unidad]],lstUniCod,0)),"✖ Unidad no existe",IF(AND(tblProductos[[#This Row],[Proveedor]]<>"",ISNA(MATCH(tblProductos[[#This Row],[Proveedor]],tblProveedores[Proveedor],0))),"✖ Proveedor no existe",IF(AND(N(tblProductos[[#This Row],[StockMax]])>0,N(tblProductos[[#This Row],[StockMin]])>N(tblProductos[[#This Row],[StockMax]])),"⚠ Mínimo mayor que máximo",IF(tblProductos[[#This Row],[Activo]]="NO","● Inactivo","✔ OK")))))))))
L13: =IF(OR(tblProductos[[#This Row],[SKU]]="",tblProductos[[#This Row],[Producto]]=""),"",tblProductos[[#This Row],[SKU]]&" · "&tblProductos[[#This Row],[Producto]]) | M13: =IF(tblProductos[[#This Row],[SKU]]="","",COUNTIF(tblMovimientos[SKU],tblProductos[[#This Row],[SKU]])) | N13: =IF(AND(tblProductos[[#This Row],[SKU]]="",tblProductos[[#This Row],[Producto]]=""),"",IF(OR(tblProductos[[#This Row],[SKU]]="",tblProductos[[#This Row],[Producto]]="",tblProductos[[#This Row],[Categoría]]="",tblProductos[[#This Row],[Unidad]]=""),"⚠ Faltan datos",IF(COUNTIF(tblProductos[SKU],tblProductos[[#This Row],[SKU]])>1,"✖ SKU duplicado",IF(ISNUMBER(FIND(" ",tblProductos[[#This Row],[SKU]])),"✖ SKU con espacios",IF(ISNA(MATCH(tblProductos[[#This Row],[Categoría]],lstCategorias,0)),"✖ Categoría no existe",IF(ISNA(MATCH(tblProductos[[#This Row],[Unidad]],lstUniCod,0)),"✖ Unidad no existe",IF(AND(tblProductos[[#This Row],[Proveedor]]<>"",ISNA(MATCH(tblProductos[[#This Row],[Proveedor]],tblProveedores[Proveedor],0))),"✖ Proveedor no existe",IF(AND(N(tblProductos[[#This Row],[StockMax]])>0,N(tblProductos[[#This Row],[StockMin]])>N(tblProductos[[#This Row],[StockMax]])),"⚠ Mínimo mayor que máximo",IF(tblProductos[[#This Row],[Activo]]="NO","● Inactivo","✔ OK")))))))))
L14: =IF(OR(tblProductos[[#This Row],[SKU]]="",tblProductos[[#This Row],[Producto]]=""),"",tblProductos[[#This Row],[SKU]]&" · "&tblProductos[[#This Row],[Producto]]) | M14: =IF(tblProductos[[#This Row],[SKU]]="","",COUNTIF(tblMovimientos[SKU],tblProductos[[#This Row],[SKU]])) | N14: =IF(AND(tblProductos[[#This Row],[SKU]]="",tblProductos[[#This Row],[Producto]]=""),"",IF(OR(tblProductos[[#This Row],[SKU]]="",tblProductos[[#This Row],[Producto]]="",tblProductos[[#This Row],[Categoría]]="",tblProductos[[#This Row],[Unidad]]=""),"⚠ Faltan datos",IF(COUNTIF(tblProductos[SKU],tblProductos[[#This Row],[SKU]])>1,"✖ SKU duplicado",IF(ISNUMBER(FIND(" ",tblProductos[[#This Row],[SKU]])),"✖ SKU con espacios",IF(ISNA(MATCH(tblProductos[[#This Row],[Categoría]],lstCategorias,0)),"✖ Categoría no existe",IF(ISNA(MATCH(tblProductos[[#This Row],[Unidad]],lstUniCod,0)),"✖ Unidad no existe",IF(AND(tblProductos[[#This Row],[Proveedor]]<>"",ISNA(MATCH(tblProductos[[#This Row],[Proveedor]],tblProveedores[Proveedor],0))),"✖ Proveedor no existe",IF(AND(N(tblProductos[[#This Row],[StockMax]])>0,N(tblProductos[[#This Row],[StockMin]])>N(tblProductos[[#This Row],[StockMax]])),"⚠ Mínimo mayor que máximo",IF(tblProductos[[#This Row],[Activo]]="NO","● Inactivo","✔ OK")))))))))
L15: =IF(OR(tblProductos[[#This Row],[SKU]]="",tblProductos[[#This Row],[Producto]]=""),"",tblProductos[[#This Row],[SKU]]&" · "&tblProductos[[#This Row],[Producto]]) | M15: =IF(tblProductos[[#This Row],[SKU]]="","",COUNTIF(tblMovimientos[SKU],tblProductos[[#This Row],[SKU]])) | N15: =IF(AND(tblProductos[[#This Row],[SKU]]="",tblProductos[[#This Row],[Producto]]=""),"",IF(OR(tblProductos[[#This Row],[SKU]]="",tblProductos[[#This Row],[Producto]]="",tblProductos[[#This Row],[Categoría]]="",tblProductos[[#This Row],[Unidad]]=""),"⚠ Faltan datos",IF(COUNTIF(tblProductos[SKU],tblProductos[[#This Row],[SKU]])>1,"✖ SKU duplicado",IF(ISNUMBER(FIND(" ",tblProductos[[#This Row],[SKU]])),"✖ SKU con espacios",IF(ISNA(MATCH(tblProductos[[#This Row],[Categoría]],lstCategorias,0)),"✖ Categoría no existe",IF(ISNA(MATCH(tblProductos[[#This Row],[Unidad]],lstUniCod,0)),"✖ Unidad no existe",IF(AND(tblProductos[[#This Row],[Proveedor]]<>"",ISNA(MATCH(tblProductos[[#This Row],[Proveedor]],tblProveedores[Proveedor],0))),"✖ Proveedor no existe",IF(AND(N(tblProductos[[#This Row],[StockMax]])>0,N(tblProductos[[#This Row],[StockMin]])>N(tblProductos[[#This Row],[StockMax]])),"⚠ Mínimo mayor que máximo",IF(tblProductos[[#This Row],[Activo]]="NO","● Inactivo","✔ OK")))))))))
L16: =IF(OR(tblProductos[[#This Row],[SKU]]="",tblProductos[[#This Row],[Producto]]=""),"",tblProductos[[#This Row],[SKU]]&" · "&tblProductos[[#This Row],[Producto]]) | M16: =IF(tblProductos[[#This Row],[SKU]]="","",COUNTIF(tblMovimientos[SKU],tblProductos[[#This Row],[SKU]])) | N16: =IF(AND(tblProductos[[#This Row],[SKU]]="",tblProductos[[#This Row],[Producto]]=""),"",IF(OR(tblProductos[[#This Row],[SKU]]="",tblProductos[[#This Row],[Producto]]="",tblProductos[[#This Row],[Categoría]]="",tblProductos[[#This Row],[Unidad]]=""),"⚠ Faltan datos",IF(COUNTIF(tblProductos[SKU],tblProductos[[#This Row],[SKU]])>1,"✖ SKU duplicado",IF(ISNUMBER(FIND(" ",tblProductos[[#This Row],[SKU]])),"✖ SKU con espacios",IF(ISNA(MATCH(tblProductos[[#This Row],[Categoría]],lstCategorias,0)),"✖ Categoría no existe",IF(ISNA(MATCH(tblProductos[[#This Row],[Unidad]],lstUniCod,0)),"✖ Unidad no existe",IF(AND(tblProductos[[#This Row],[Proveedor]]<>"",ISNA(MATCH(tblProductos[[#This Row],[Proveedor]],tblProveedores[Proveedor],0))),"✖ Proveedor no existe",IF(AND(N(tblProductos[[#This Row],[StockMax]])>0,N(tblProductos[[#This Row],[StockMin]])>N(tblProductos[[#This Row],[StockMax]])),"⚠ Mínimo mayor que máximo",IF(tblProductos[[#This Row],[Activo]]="NO","● Inactivo","✔ OK")))))))))
L17: =IF(OR(tblProductos[[#This Row],[SKU]]="",tblProductos[[#This Row],[Producto]]=""),"",tblProductos[[#This Row],[SKU]]&" · "&tblProductos[[#This Row],[Producto]]) | M17: =IF(tblProductos[[#This Row],[SKU]]="","",COUNTIF(tblMovimientos[SKU],tblProductos[[#This Row],[SKU]])) | N17: =IF(AND(tblProductos[[#This Row],[SKU]]="",tblProductos[[#This Row],[Producto]]=""),"",IF(OR(tblProductos[[#This Row],[SKU]]="",tblProductos[[#This Row],[Producto]]="",tblProductos[[#This Row],[Categoría]]="",tblProductos[[#This Row],[Unidad]]=""),"⚠ Faltan datos",IF(COUNTIF(tblProductos[SKU],tblProductos[[#This Row],[SKU]])>1,"✖ SKU duplicado",IF(ISNUMBER(FIND(" ",tblProductos[[#This Row],[SKU]])),"✖ SKU con espacios",IF(ISNA(MATCH(tblProductos[[#This Row],[Categoría]],lstCategorias,0)),"✖ Categoría no existe",IF(ISNA(MATCH(tblProductos[[#This Row],[Unidad]],lstUniCod,0)),"✖ Unidad no existe",IF(AND(tblProductos[[#This Row],[Proveedor]]<>"",ISNA(MATCH(tblProductos[[#This Row],[Proveedor]],tblProveedores[Proveedor],0))),"✖ Proveedor no existe",IF(AND(N(tblProductos[[#This Row],[StockMax]])>0,N(tblProductos[[#This Row],[StockMin]])>N(tblProductos[[#This Row],[StockMax]])),"⚠ Mínimo mayor que máximo",IF(tblProductos[[#This Row],[Activo]]="NO","● Inactivo","✔ OK")))))))))
L18: =IF(OR(tblProductos[[#This Row],[SKU]]="",tblProductos[[#This Row],[Producto]]=""),"",tblProductos[[#This Row],[SKU]]&" · "&tblProductos[[#This Row],[Producto]]) | M18: =IF(tblProductos[[#This Row],[SKU]]="","",COUNTIF(tblMovimientos[SKU],tblProductos[[#This Row],[SKU]])) | N18: =IF(AND(tblProductos[[#This Row],[SKU]]="",tblProductos[[#This Row],[Producto]]=""),"",IF(OR(tblProductos[[#This Row],[SKU]]="",tblProductos[[#This Row],[Producto]]="",tblProductos[[#This Row],[Categoría]]="",tblProductos[[#This Row],[Unidad]]=""),"⚠ Faltan datos",IF(COUNTIF(tblProductos[SKU],tblProductos[[#This Row],[SKU]])>1,"✖ SKU duplicado",IF(ISNUMBER(FIND(" ",tblProductos[[#This Row],[SKU]])),"✖ SKU con espacios",IF(ISNA(MATCH(tblProductos[[#This Row],[Categoría]],lstCategorias,0)),"✖ Categoría no existe",IF(ISNA(MATCH(tblProductos[[#This Row],[Unidad]],lstUniCod,0)),"✖ Unidad no existe",IF(AND(tblProductos[[#This Row],[Proveedor]]<>"",ISNA(MATCH(tblProductos[[#This Row],[Proveedor]],tblProveedores[Proveedor],0))),"✖ Proveedor no existe",IF(AND(N(tblProductos[[#This Row],[StockMax]])>0,N(tblProductos[[#This Row],[StockMin]])>N(tblProductos[[#This Row],[StockMax]])),"⚠ Mínimo mayor que máximo",IF(tblProductos[[#This Row],[Activo]]="NO","● Inactivo","✔ OK")))))))))
L19: =IF(OR(tblProductos[[#This Row],[SKU]]="",tblProductos[[#This Row],[Producto]]=""),"",tblProductos[[#This Row],[SKU]]&" · "&tblProductos[[#This Row],[Producto]]) | M19: =IF(tblProductos[[#This Row],[SKU]]="","",COUNTIF(tblMovimientos[SKU],tblProductos[[#This Row],[SKU]])) | N19: =IF(AND(tblProductos[[#This Row],[SKU]]="",tblProductos[[#This Row],[Producto]]=""),"",IF(OR(tblProductos[[#This Row],[SKU]]="",tblProductos[[#This Row],[Producto]]="",tblProductos[[#This Row],[Categoría]]="",tblProductos[[#This Row],[Unidad]]=""),"⚠ Faltan datos",IF(COUNTIF(tblProductos[SKU],tblProductos[[#This Row],[SKU]])>1,"✖ SKU duplicado",IF(ISNUMBER(FIND(" ",tblProductos[[#This Row],[SKU]])),"✖ SKU con espacios",IF(ISNA(MATCH(tblProductos[[#This Row],[Categoría]],lstCategorias,0)),"✖ Categoría no existe",IF(ISNA(MATCH(tblProductos[[#This Row],[Unidad]],lstUniCod,0)),"✖ Unidad no existe",IF(AND(tblProductos[[#This Row],[Proveedor]]<>"",ISNA(MATCH(tblProductos[[#This Row],[Proveedor]],tblProveedores[Proveedor],0))),"✖ Proveedor no existe",IF(AND(N(tblProductos[[#This Row],[StockMax]])>0,N(tblProductos[[#This Row],[StockMin]])>N(tblProductos[[#This Row],[StockMax]])),"⚠ Mínimo mayor que máximo",IF(tblProductos[[#This Row],[Activo]]="NO","● Inactivo","✔ OK")))))))))
... L507: =IF(OR(tblProductos[[#This Row],[SKU]]="",tblProductos[[#This Row],[Producto]]=""),"",tblProductos[[#This Row],[SKU]]&" · "&tblProductos[[#This Row],[Producto]]) | M507: =IF(tblProductos[[#This Row],[SKU]]="","",COUNTIF(tblMovimientos[SKU],tblProductos[[#This Row],[SKU]])) | N507: =IF(AND(tblProductos[[#This Row],[SKU]]="",tblProductos[[#This Row],[Producto]]=""),"",IF(OR(tblProductos[[#This Row],[SKU]]="",tblProductos[[#This Row],[Producto]]="",tblProductos[[#This Row],[Categoría]]="",tblProductos[[#This Row],[Unidad]]=""),"⚠ Faltan datos",IF(COUNTIF(tblProductos[SKU],tblProductos[[#This Row],[SKU]])>1,"✖ SKU duplicado",IF(ISNUMBER(FIND(" ",tblProductos[[#This Row],[SKU]])),"✖ SKU con espacios",IF(ISNA(MATCH(tblProductos[[#This Row],[Categoría]],lstCategorias,0)),"✖ Categoría no existe",IF(ISNA(MATCH(tblProductos[[#This Row],[Unidad]],lstUniCod,0)),"✖ Unidad no existe",IF(AND(tblProductos[[#This Row],[Proveedor]]<>"",ISNA(MATCH(tblProductos[[#This Row],[Proveedor]],tblProveedores[Proveedor],0))),"✖ Proveedor no existe",IF(AND(N(tblProductos[[#This Row],[StockMax]])>0,N(tblProductos[[#This Row],[StockMin]])>N(tblProductos[[#This Row],[StockMax]])),"⚠ Mínimo mayor que máximo",IF(tblProductos[[#This Row],[Activo]]="NO","● Inactivo","✔ OK")))))))))

Sheet 06_UNIDADES
B2: Unidades de medida
B3: Capa de configuración (oculta) · Define si la cantidad admite decimales
B7: Código | C7: Unidad | D7: Decimales | E7: Descripción
B8: UND | C8: Unidad | D8: NO | E8: Pieza individual
B9: CAJA | C9: Caja | D9: NO | E9: Caja cerrada del proveedor
B10: PAQ | C10: Paquete | D10: NO | E10: Paquete o bolsa cerrada
B11: PAR | C11: Par | D11: NO | E11: Par (guantes, botas)
B12: ROLLO | C12: Rollo | D12: NO | E12: Rollo completo
B13: KG | C13: Kilogramo | D13: SI | E13: Peso en kilogramos
B14: GL | C14: Galón | D14: SI | E14: Volumen en galones
B15: LT | C15: Litro | D15: SI | E15: Volumen en litros
B16: MT | C16: Metro | D16: SI | E16: Longitud en metros

Sheet 10_MOVIMIENTOS
B2: Bitácora de movimientos
B3: Capa de escritura · Registro inmutable (append-only) de entradas, salidas y ajustes
B6: ƒx | C6: ✎ | D6: ✎ | E6: ✎ | F6: ✎ | G6: ƒx | H6: ƒx | I6: ✎ | J6: ƒx | K6: ƒx | L6: ƒx | M6: ƒx | N6: ✎ | O6: ✎ | P6: ✎
B7: ID | C7: Fecha | D7: Tipo | E7: Categoría | F7: Producto | G7: SKU | H7: Unidad | I7: Cantidad | J7: FactorStock | K7: CantidadNeta | L7: Saldo | M7: Estado | N7: Documento | O7: Responsable | P7: Observaciones
B8: =IF((tblMovimientos[[#This Row],[Fecha]]&tblMovimientos[[#This Row],[Tipo]]&tblMovimientos[[#This Row],[Producto]]&tblMovimientos[[#This Row],[Cantidad]])="","",ROW()-ROW(tblMovimientos[#Headers])) | G8: =IF(tblMovimientos[[#This Row],[Producto]]="","",TRIM(LEFT(tblMovimientos[[#This Row],[Producto]],FIND(" · ",tblMovimientos[[#This Row],[Producto]]&" · ")-1))) | H8: =IF(tblMovimientos[[#This Row],[SKU]]="","",IFERROR(INDEX(tblProductos[Unidad],MATCH(tblMovimientos[[#This Row],[SKU]],tblProductos[SKU],0)),"?")) | J8: =IF(tblMovimientos[[#This Row],[Tipo]]="","",IFERROR(INDEX(tblTiposMov[FactorStock],MATCH(tblMovimientos[[#This Row],[Tipo]],tblTiposMov[Tipo],0)),0)) | K8: =IF(OR(tblMovimientos[[#This Row],[Cantidad]]="",tblMovimientos[[#This Row],[FactorStock]]=""),"",IF(ISNUMBER(tblMovimientos[[#This Row],[Cantidad]]),tblMovimientos[[#This Row],[Cantidad]]*tblMovimientos[[#This Row],[FactorStock]],"")) | L8: =IF(tblMovimientos[[#This Row],[CantidadNeta]]="","",SUMIFS(INDEX(tblMovimientos[CantidadNeta],1):tblMovimientos[[#This Row],[CantidadNeta]],INDEX(tblMovimientos[SKU],1):tblMovimientos[[#This Row],[SKU]],tblMovimientos[[#This Row],[SKU]])) | M8: =IF((tblMovimientos[[#This Row],[Fecha]]&tblMovimientos[[#This Row],[Tipo]]&tblMovimientos[[#This Row],[Producto]]&tblMovimientos[[#This Row],[Cantidad]])="","",IF(OR(tblMovimientos[[#This Row],[Fecha]]="",tblMovimientos[[#This Row],[Tipo]]="",tblMovimientos[[#This Row],[Producto]]="",tblMovimientos[[#This Row],[Cantidad]]="",tblMovimientos[[#This Row],[Responsable]]=""),"⚠ Incompleto",IF(tblMovimientos[[#This Row],[Unidad]]="?","✖ Producto no existe",IF(tblMovimientos[[#This Row],[FactorStock]]=0,"✖ Tipo no válido",IF(NOT(ISNUMBER(tblMovimientos[[#This Row],[Cantidad]])),"✖ Cantidad inválida",IF(tblMovimientos[[#This Row],[Cantidad]]<=0,"✖ Cantidad inválida",IF(AND(tblMovimientos[[#This Row],[Categoría]]<>"",tblMovimientos[[#This Row],[Categoría]]<>INDEX(tblProductos[Categoría],MATCH(tblMovimientos[[#This Row],[SKU]],tblProductos[SKU],0))),"⚠ Categoría no coincide",IF(tblMovimientos[[#This Row],[Saldo]]<0,"✖ Stock insuficiente",IF(AND(LEFT(tblMovimientos[[#This Row],[Tipo]],6)="AJUSTE",tblMovimientos[[#This Row],[Observaciones]]=""),"⚠ Justifique el ajuste","✔ Registrado")))))))))
B9: =IF((tblMovimientos[[#This Row],[Fecha]]&tblMovimientos[[#This Row],[Tipo]]&tblMovimientos[[#This Row],[Producto]]&tblMovimientos[[#This Row],[Cantidad]])="","",ROW()-ROW(tblMovimientos[#Headers])) | G9: =IF(tblMovimientos[[#This Row],[Producto]]="","",TRIM(LEFT(tblMovimientos[[#This Row],[Producto]],FIND(" · ",tblMovimientos[[#This Row],[Producto]]&" · ")-1))) | H9: =IF(tblMovimientos[[#This Row],[SKU]]="","",IFERROR(INDEX(tblProductos[Unidad],MATCH(tblMovimientos[[#This Row],[SKU]],tblProductos[SKU],0)),"?")) | J9: =IF(tblMovimientos[[#This Row],[Tipo]]="","",IFERROR(INDEX(tblTiposMov[FactorStock],MATCH(tblMovimientos[[#This Row],[Tipo]],tblTiposMov[Tipo],0)),0)) | K9: =IF(OR(tblMovimientos[[#This Row],[Cantidad]]="",tblMovimientos[[#This Row],[FactorStock]]=""),"",IF(ISNUMBER(tblMovimientos[[#This Row],[Cantidad]]),tblMovimientos[[#This Row],[Cantidad]]*tblMovimientos[[#This Row],[FactorStock]],"")) | L9: =IF(tblMovimientos[[#This Row],[CantidadNeta]]="","",SUMIFS(INDEX(tblMovimientos[CantidadNeta],1):tblMovimientos[[#This Row],[CantidadNeta]],INDEX(tblMovimientos[SKU],1):tblMovimientos[[#This Row],[SKU]],tblMovimientos[[#This Row],[SKU]])) | M9: =IF((tblMovimientos[[#This Row],[Fecha]]&tblMovimientos[[#This Row],[Tipo]]&tblMovimientos[[#This Row],[Producto]]&tblMovimientos[[#This Row],[Cantidad]])="","",IF(OR(tblMovimientos[[#This Row],[Fecha]]="",tblMovimientos[[#This Row],[Tipo]]="",tblMovimientos[[#This Row],[Producto]]="",tblMovimientos[[#This Row],[Cantidad]]="",tblMovimientos[[#This Row],[Responsable]]=""),"⚠ Incompleto",IF(tblMovimientos[[#This Row],[Unidad]]="?","✖ Producto no existe",IF(tblMovimientos[[#This Row],[FactorStock]]=0,"✖ Tipo no válido",IF(NOT(ISNUMBER(tblMovimientos[[#This Row],[Cantidad]])),"✖ Cantidad inválida",IF(tblMovimientos[[#This Row],[Cantidad]]<=0,"✖ Cantidad inválida",IF(AND(tblMovimientos[[#This Row],[Categoría]]<>"",tblMovimientos[[#This Row],[Categoría]]<>INDEX(tblProductos[Categoría],MATCH(tblMovimientos[[#This Row],[SKU]],tblProductos[SKU],0))),"⚠ Categoría no coincide",IF(tblMovimientos[[#This Row],[Saldo]]<0,"✖ Stock insuficiente",IF(AND(LEFT(tblMovimientos[[#This Row],[Tipo]],6)="AJUSTE",tblMovimientos[[#This Row],[Observaciones]]=""),"⚠ Justifique el ajuste","✔ Registrado")))))))))
B10: =IF((tblMovimientos[[#This Row],[Fecha]]&tblMovimientos[[#This Row],[Tipo]]&tblMovimientos[[#This Row],[Producto]]&tblMovimientos[[#This Row],[Cantidad]])="","",ROW()-ROW(tblMovimientos[#Headers])) | G10: =IF(tblMovimientos[[#This Row],[Producto]]="","",TRIM(LEFT(tblMovimientos[[#This Row],[Producto]],FIND(" · ",tblMovimientos[[#This Row],[Producto]]&" · ")-1))) | H10: =IF(tblMovimientos[[#This Row],[SKU]]="","",IFERROR(INDEX(tblProductos[Unidad],MATCH(tblMovimientos[[#This Row],[SKU]],tblProductos[SKU],0)),"?")) | J10: =IF(tblMovimientos[[#This Row],[Tipo]]="","",IFERROR(INDEX(tblTiposMov[FactorStock],MATCH(tblMovimientos[[#This Row],[Tipo]],tblTiposMov[Tipo],0)),0)) | K10: =IF(OR(tblMovimientos[[#This Row],[Cantidad]]="",tblMovimientos[[#This Row],[FactorStock]]=""),"",IF(ISNUMBER(tblMovimientos[[#This Row],[Cantidad]]),tblMovimientos[[#This Row],[Cantidad]]*tblMovimientos[[#This Row],[FactorStock]],"")) | L10: =IF(tblMovimientos[[#This Row],[CantidadNeta]]="","",SUMIFS(INDEX(tblMovimientos[CantidadNeta],1):tblMovimientos[[#This Row],[CantidadNeta]],INDEX(tblMovimientos[SKU],1):tblMovimientos[[#This Row],[SKU]],tblMovimientos[[#This Row],[SKU]])) | M10: =IF((tblMovimientos[[#This Row],[Fecha]]&tblMovimientos[[#This Row],[Tipo]]&tblMovimientos[[#This Row],[Producto]]&tblMovimientos[[#This Row],[Cantidad]])="","",IF(OR(tblMovimientos[[#This Row],[Fecha]]="",tblMovimientos[[#This Row],[Tipo]]="",tblMovimientos[[#This Row],[Producto]]="",tblMovimientos[[#This Row],[Cantidad]]="",tblMovimientos[[#This Row],[Responsable]]=""),"⚠ Incompleto",IF(tblMovimientos[[#This Row],[Unidad]]="?","✖ Producto no existe",IF(tblMovimientos[[#This Row],[FactorStock]]=0,"✖ Tipo no válido",IF(NOT(ISNUMBER(tblMovimientos[[#This Row],[Cantidad]])),"✖ Cantidad inválida",IF(tblMovimientos[[#This Row],[Cantidad]]<=0,"✖ Cantidad inválida",IF(AND(tblMovimientos[[#This Row],[Categoría]]<>"",tblMovimientos[[#This Row],[Categoría]]<>INDEX(tblProductos[Categoría],MATCH(tblMovimientos[[#This Row],[SKU]],tblProductos[SKU],0))),"⚠ Categoría no coincide",IF(tblMovimientos[[#This Row],[Saldo]]<0,"✖ Stock insuficiente",IF(AND(LEFT(tblMovimientos[[#This Row],[Tipo]],6)="AJUSTE",tblMovimientos[[#This Row],[Observaciones]]=""),"⚠ Justifique el ajuste","✔ Registrado")))))))))
B11: =IF((tblMovimientos[[#This Row],[Fecha]]&tblMovimientos[[#This Row],[Tipo]]&tblMovimientos[[#This Row],[Producto]]&tblMovimientos[[#This Row],[Cantidad]])="","",ROW()-ROW(tblMovimientos[#Headers])) | G11: =IF(tblMovimientos[[#This Row],[Producto]]="","",TRIM(LEFT(tblMovimientos[[#This Row],[Producto]],FIND(" · ",tblMovimientos[[#This Row],[Producto]]&" · ")-1))) | H11: =IF(tblMovimientos[[#This Row],[SKU]]="","",IFERROR(INDEX(tblProductos[Unidad],MATCH(tblMovimientos[[#This Row],[SKU]],tblProductos[SKU],0)),"?")) | J11: =IF(tblMovimientos[[#This Row],[Tipo]]="","",IFERROR(INDEX(tblTiposMov[FactorStock],MATCH(tblMovimientos[[#This Row],[Tipo]],tblTiposMov[Tipo],0)),0)) | K11: =IF(OR(tblMovimientos[[#This Row],[Cantidad]]="",tblMovimientos[[#This Row],[FactorStock]]=""),"",IF(ISNUMBER(tblMovimientos[[#This Row],[Cantidad]]),tblMovimientos[[#This Row],[Cantidad]]*tblMovimientos[[#This Row],[FactorStock]],"")) | L11: =IF(tblMovimientos[[#This Row],[CantidadNeta]]="","",SUMIFS(INDEX(tblMovimientos[CantidadNeta],1):tblMovimientos[[#This Row],[CantidadNeta]],INDEX(tblMovimientos[SKU],1):tblMovimientos[[#This Row],[SKU]],tblMovimientos[[#This Row],[SKU]])) | M11: =IF((tblMovimientos[[#This Row],[Fecha]]&tblMovimientos[[#This Row],[Tipo]]&tblMovimientos[[#This Row],[Producto]]&tblMovimientos[[#This Row],[Cantidad]])="","",IF(OR(tblMovimientos[[#This Row],[Fecha]]="",tblMovimientos[[#This Row],[Tipo]]="",tblMovimientos[[#This Row],[Producto]]="",tblMovimientos[[#This Row],[Cantidad]]="",tblMovimientos[[#This Row],[Responsable]]=""),"⚠ Incompleto",IF(tblMovimientos[[#This Row],[Unidad]]="?","✖ Producto no existe",IF(tblMovimientos[[#This Row],[FactorStock]]=0,"✖ Tipo no válido",IF(NOT(ISNUMBER(tblMovimientos[[#This Row],[Cantidad]])),"✖ Cantidad inválida",IF(tblMovimientos[[#This Row],[Cantidad]]<=0,"✖ Cantidad inválida",IF(AND(tblMovimientos[[#This Row],[Categoría]]<>"",tblMovimientos[[#This Row],[Categoría]]<>INDEX(tblProductos[Categoría],MATCH(tblMovimientos[[#This Row],[SKU]],tblProductos[SKU],0))),"⚠ Categoría no coincide",IF(tblMovimientos[[#This Row],[Saldo]]<0,"✖ Stock insuficiente",IF(AND(LEFT(tblMovimientos[[#This Row],[Tipo]],6)="AJUSTE",tblMovimientos[[#This Row],[Observaciones]]=""),"⚠ Justifique el ajuste","✔ Registrado")))))))))
B12: =IF((tblMovimientos[[#This Row],[Fecha]]&tblMovimientos[[#This Row],[Tipo]]&tblMovimientos[[#This Row],[Producto]]&tblMovimientos[[#This Row],[Cantidad]])="","",ROW()-ROW(tblMovimientos[#Headers])) | G12: =IF(tblMovimientos[[#This Row],[Producto]]="","",TRIM(LEFT(tblMovimientos[[#This Row],[Producto]],FIND(" · ",tblMovimientos[[#This Row],[Producto]]&" · ")-1))) | H12: =IF(tblMovimientos[[#This Row],[SKU]]="","",IFERROR(INDEX(tblProductos[Unidad],MATCH(tblMovimientos[[#This Row],[SKU]],tblProductos[SKU],0)),"?")) | J12: =IF(tblMovimientos[[#This Row],[Tipo]]="","",IFERROR(INDEX(tblTiposMov[FactorStock],MATCH(tblMovimientos[[#This Row],[Tipo]],tblTiposMov[Tipo],0)),0)) | K12: =IF(OR(tblMovimientos[[#This Row],[Cantidad]]="",tblMovimientos[[#This Row],[FactorStock]]=""),"",IF(ISNUMBER(tblMovimientos[[#This Row],[Cantidad]]),tblMovimientos[[#This Row],[Cantidad]]*tblMovimientos[[#This Row],[FactorStock]],"")) | L12: =IF(tblMovimientos[[#This Row],[CantidadNeta]]="","",SUMIFS(INDEX(tblMovimientos[CantidadNeta],1):tblMovimientos[[#This Row],[CantidadNeta]],INDEX(tblMovimientos[SKU],1):tblMovimientos[[#This Row],[SKU]],tblMovimientos[[#This Row],[SKU]])) | M12: =IF((tblMovimientos[[#This Row],[Fecha]]&tblMovimientos[[#This Row],[Tipo]]&tblMovimientos[[#This Row],[Producto]]&tblMovimientos[[#This Row],[Cantidad]])="","",IF(OR(tblMovimientos[[#This Row],[Fecha]]="",tblMovimientos[[#This Row],[Tipo]]="",tblMovimientos[[#This Row],[Producto]]="",tblMovimientos[[#This Row],[Cantidad]]="",tblMovimientos[[#This Row],[Responsable]]=""),"⚠ Incompleto",IF(tblMovimientos[[#This Row],[Unidad]]="?","✖ Producto no existe",IF(tblMovimientos[[#This Row],[FactorStock]]=0,"✖ Tipo no válido",IF(NOT(ISNUMBER(tblMovimientos[[#This Row],[Cantidad]])),"✖ Cantidad inválida",IF(tblMovimientos[[#This Row],[Cantidad]]<=0,"✖ Cantidad inválida",IF(AND(tblMovimientos[[#This Row],[Categoría]]<>"",tblMovimientos[[#This Row],[Categoría]]<>INDEX(tblProductos[Categoría],MATCH(tblMovimientos[[#This Row],[SKU]],tblProductos[SKU],0))),"⚠ Categoría no coincide",IF(tblMovimientos[[#This Row],[Saldo]]<0,"✖ Stock insuficiente",IF(AND(LEFT(tblMovimientos[[#This Row],[Tipo]],6)="AJUSTE",tblMovimientos[[#This Row],[Observaciones]]=""),"⚠ Justifique el ajuste","✔ Registrado")))))))))
B13: =IF((tblMovimientos[[#This Row],[Fecha]]&tblMovimientos[[#This Row],[Tipo]]&tblMovimientos[[#This Row],[Producto]]&tblMovimientos[[#This Row],[Cantidad]])="","",ROW()-ROW(tblMovimientos[#Headers])) | G13: =IF(tblMovimientos[[#This Row],[Producto]]="","",TRIM(LEFT(tblMovimientos[[#This Row],[Producto]],FIND(" · ",tblMovimientos[[#This Row],[Producto]]&" · ")-1))) | H13: =IF(tblMovimientos[[#This Row],[SKU]]="","",IFERROR(INDEX(tblProductos[Unidad],MATCH(tblMovimientos[[#This Row],[SKU]],tblProductos[SKU],0)),"?")) | J13: =IF(tblMovimientos[[#This Row],[Tipo]]="","",IFERROR(INDEX(tblTiposMov[FactorStock],MATCH(tblMovimientos[[#This Row],[Tipo]],tblTiposMov[Tipo],0)),0)) | K13: =IF(OR(tblMovimientos[[#This Row],[Cantidad]]="",tblMovimientos[[#This Row],[FactorStock]]=""),"",IF(ISNUMBER(tblMovimientos[[#This Row],[Cantidad]]),tblMovimientos[[#This Row],[Cantidad]]*tblMovimientos[[#This Row],[FactorStock]],"")) | L13: =IF(tblMovimientos[[#This Row],[CantidadNeta]]="","",SUMIFS(INDEX(tblMovimientos[CantidadNeta],1):tblMovimientos[[#This Row],[CantidadNeta]],INDEX(tblMovimientos[SKU],1):tblMovimientos[[#This Row],[SKU]],tblMovimientos[[#This Row],[SKU]])) | M13: =IF((tblMovimientos[[#This Row],[Fecha]]&tblMovimientos[[#This Row],[Tipo]]&tblMovimientos[[#This Row],[Producto]]&tblMovimientos[[#This Row],[Cantidad]])="","",IF(OR(tblMovimientos[[#This Row],[Fecha]]="",tblMovimientos[[#This Row],[Tipo]]="",tblMovimientos[[#This Row],[Producto]]="",tblMovimientos[[#This Row],[Cantidad]]="",tblMovimientos[[#This Row],[Responsable]]=""),"⚠ Incompleto",IF(tblMovimientos[[#This Row],[Unidad]]="?","✖ Producto no existe",IF(tblMovimientos[[#This Row],[FactorStock]]=0,"✖ Tipo no válido",IF(NOT(ISNUMBER(tblMovimientos[[#This Row],[Cantidad]])),"✖ Cantidad inválida",IF(tblMovimientos[[#This Row],[Cantidad]]<=0,"✖ Cantidad inválida",IF(AND(tblMovimientos[[#This Row],[Categoría]]<>"",tblMovimientos[[#This Row],[Categoría]]<>INDEX(tblProductos[Categoría],MATCH(tblMovimientos[[#This Row],[SKU]],tblProductos[SKU],0))),"⚠ Categoría no coincide",IF(tblMovimientos[[#This Row],[Saldo]]<0,"✖ Stock insuficiente",IF(AND(LEFT(tblMovimientos[[#This Row],[Tipo]],6)="AJUSTE",tblMovimientos[[#This Row],[Observaciones]]=""),"⚠ Justifique el ajuste","✔ Registrado")))))))))
B14: =IF((tblMovimientos[[#This Row],[Fecha]]&tblMovimientos[[#This Row],[Tipo]]&tblMovimientos[[#This Row],[Producto]]&tblMovimientos[[#This Row],[Cantidad]])="","",ROW()-ROW(tblMovimientos[#Headers])) | G14: =IF(tblMovimientos[[#This Row],[Producto]]="","",TRIM(LEFT(tblMovimientos[[#This Row],[Producto]],FIND(" · ",tblMovimientos[[#This Row],[Producto]]&" · ")-1))) | H14: =IF(tblMovimientos[[#This Row],[SKU]]="","",IFERROR(INDEX(tblProductos[Unidad],MATCH(tblMovimientos[[#This Row],[SKU]],tblProductos[SKU],0)),"?")) | J14: =IF(tblMovimientos[[#This Row],[Tipo]]="","",IFERROR(INDEX(tblTiposMov[FactorStock],MATCH(tblMovimientos[[#This Row],[Tipo]],tblTiposMov[Tipo],0)),0)) | K14: =IF(OR(tblMovimientos[[#This Row],[Cantidad]]="",tblMovimientos[[#This Row],[FactorStock]]=""),"",IF(ISNUMBER(tblMovimientos[[#This Row],[Cantidad]]),tblMovimientos[[#This Row],[Cantidad]]*tblMovimientos[[#This Row],[FactorStock]],"")) | L14: =IF(tblMovimientos[[#This Row],[CantidadNeta]]="","",SUMIFS(INDEX(tblMovimientos[CantidadNeta],1):tblMovimientos[[#This Row],[CantidadNeta]],INDEX(tblMovimientos[SKU],1):tblMovimientos[[#This Row],[SKU]],tblMovimientos[[#This Row],[SKU]])) | M14: =IF((tblMovimientos[[#This Row],[Fecha]]&tblMovimientos[[#This Row],[Tipo]]&tblMovimientos[[#This Row],[Producto]]&tblMovimientos[[#This Row],[Cantidad]])="","",IF(OR(tblMovimientos[[#This Row],[Fecha]]="",tblMovimientos[[#This Row],[Tipo]]="",tblMovimientos[[#This Row],[Producto]]="",tblMovimientos[[#This Row],[Cantidad]]="",tblMovimientos[[#This Row],[Responsable]]=""),"⚠ Incompleto",IF(tblMovimientos[[#This Row],[Unidad]]="?","✖ Producto no existe",IF(tblMovimientos[[#This Row],[FactorStock]]=0,"✖ Tipo no válido",IF(NOT(ISNUMBER(tblMovimientos[[#This Row],[Cantidad]])),"✖ Cantidad inválida",IF(tblMovimientos[[#This Row],[Cantidad]]<=0,"✖ Cantidad inválida",IF(AND(tblMovimientos[[#This Row],[Categoría]]<>"",tblMovimientos[[#This Row],[Categoría]]<>INDEX(tblProductos[Categoría],MATCH(tblMovimientos[[#This Row],[SKU]],tblProductos[SKU],0))),"⚠ Categoría no coincide",IF(tblMovimientos[[#This Row],[Saldo]]<0,"✖ Stock insuficiente",IF(AND(LEFT(tblMovimientos[[#This Row],[Tipo]],6)="AJUSTE",tblMovimientos[[#This Row],[Observaciones]]=""),"⚠ Justifique el ajuste","✔ Registrado")))))))))
B15: =IF((tblMovimientos[[#This Row],[Fecha]]&tblMovimientos[[#This Row],[Tipo]]&tblMovimientos[[#This Row],[Producto]]&tblMovimientos[[#This Row],[Cantidad]])="","",ROW()-ROW(tblMovimientos[#Headers])) | G15: =IF(tblMovimientos[[#This Row],[Producto]]="","",TRIM(LEFT(tblMovimientos[[#This Row],[Producto]],FIND(" · ",tblMovimientos[[#This Row],[Producto]]&" · ")-1))) | H15: =IF(tblMovimientos[[#This Row],[SKU]]="","",IFERROR(INDEX(tblProductos[Unidad],MATCH(tblMovimientos[[#This Row],[SKU]],tblProductos[SKU],0)),"?")) | J15: =IF(tblMovimientos[[#This Row],[Tipo]]="","",IFERROR(INDEX(tblTiposMov[FactorStock],MATCH(tblMovimientos[[#This Row],[Tipo]],tblTiposMov[Tipo],0)),0)) | K15: =IF(OR(tblMovimientos[[#This Row],[Cantidad]]="",tblMovimientos[[#This Row],[FactorStock]]=""),"",IF(ISNUMBER(tblMovimientos[[#This Row],[Cantidad]]),tblMovimientos[[#This Row],[Cantidad]]*tblMovimientos[[#This Row],[FactorStock]],"")) | L15: =IF(tblMovimientos[[#This Row],[CantidadNeta]]="","",SUMIFS(INDEX(tblMovimientos[CantidadNeta],1):tblMovimientos[[#This Row],[CantidadNeta]],INDEX(tblMovimientos[SKU],1):tblMovimientos[[#This Row],[SKU]],tblMovimientos[[#This Row],[SKU]])) | M15: =IF((tblMovimientos[[#This Row],[Fecha]]&tblMovimientos[[#This Row],[Tipo]]&tblMovimientos[[#This Row],[Producto]]&tblMovimientos[[#This Row],[Cantidad]])="","",IF(OR(tblMovimientos[[#This Row],[Fecha]]="",tblMovimientos[[#This Row],[Tipo]]="",tblMovimientos[[#This Row],[Producto]]="",tblMovimientos[[#This Row],[Cantidad]]="",tblMovimientos[[#This Row],[Responsable]]=""),"⚠ Incompleto",IF(tblMovimientos[[#This Row],[Unidad]]="?","✖ Producto no existe",IF(tblMovimientos[[#This Row],[FactorStock]]=0,"✖ Tipo no válido",IF(NOT(ISNUMBER(tblMovimientos[[#This Row],[Cantidad]])),"✖ Cantidad inválida",IF(tblMovimientos[[#This Row],[Cantidad]]<=0,"✖ Cantidad inválida",IF(AND(tblMovimientos[[#This Row],[Categoría]]<>"",tblMovimientos[[#This Row],[Categoría]]<>INDEX(tblProductos[Categoría],MATCH(tblMovimientos[[#This Row],[SKU]],tblProductos[SKU],0))),"⚠ Categoría no coincide",IF(tblMovimientos[[#This Row],[Saldo]]<0,"✖ Stock insuficiente",IF(AND(LEFT(tblMovimientos[[#This Row],[Tipo]],6)="AJUSTE",tblMovimientos[[#This Row],[Observaciones]]=""),"⚠ Justifique el ajuste","✔ Registrado")))))))))
B16: =IF((tblMovimientos[[#This Row],[Fecha]]&tblMovimientos[[#This Row],[Tipo]]&tblMovimientos[[#This Row],[Producto]]&tblMovimientos[[#This Row],[Cantidad]])="","",ROW()-ROW(tblMovimientos[#Headers])) | G16: =IF(tblMovimientos[[#This Row],[Producto]]="","",TRIM(LEFT(tblMovimientos[[#This Row],[Producto]],FIND(" · ",tblMovimientos[[#This Row],[Producto]]&" · ")-1))) | H16: =IF(tblMovimientos[[#This Row],[SKU]]="","",IFERROR(INDEX(tblProductos[Unidad],MATCH(tblMovimientos[[#This Row],[SKU]],tblProductos[SKU],0)),"?")) | J16: =IF(tblMovimientos[[#This Row],[Tipo]]="","",IFERROR(INDEX(tblTiposMov[FactorStock],MATCH(tblMovimientos[[#This Row],[Tipo]],tblTiposMov[Tipo],0)),0)) | K16: =IF(OR(tblMovimientos[[#This Row],[Cantidad]]="",tblMovimientos[[#This Row],[FactorStock]]=""),"",IF(ISNUMBER(tblMovimientos[[#This Row],[Cantidad]]),tblMovimientos[[#This Row],[Cantidad]]*tblMovimientos[[#This Row],[FactorStock]],"")) | L16: =IF(tblMovimientos[[#This Row],[CantidadNeta]]="","",SUMIFS(INDEX(tblMovimientos[CantidadNeta],1):tblMovimientos[[#This Row],[CantidadNeta]],INDEX(tblMovimientos[SKU],1):tblMovimientos[[#This Row],[SKU]],tblMovimientos[[#This Row],[SKU]])) | M16: =IF((tblMovimientos[[#This Row],[Fecha]]&tblMovimientos[[#This Row],[Tipo]]&tblMovimientos[[#This Row],[Producto]]&tblMovimientos[[#This Row],[Cantidad]])="","",IF(OR(tblMovimientos[[#This Row],[Fecha]]="",tblMovimientos[[#This Row],[Tipo]]="",tblMovimientos[[#This Row],[Producto]]="",tblMovimientos[[#This Row],[Cantidad]]="",tblMovimientos[[#This Row],[Responsable]]=""),"⚠ Incompleto",IF(tblMovimientos[[#This Row],[Unidad]]="?","✖ Producto no existe",IF(tblMovimientos[[#This Row],[FactorStock]]=0,"✖ Tipo no válido",IF(NOT(ISNUMBER(tblMovimientos[[#This Row],[Cantidad]])),"✖ Cantidad inválida",IF(tblMovimientos[[#This Row],[Cantidad]]<=0,"✖ Cantidad inválida",IF(AND(tblMovimientos[[#This Row],[Categoría]]<>"",tblMovimientos[[#This Row],[Categoría]]<>INDEX(tblProductos[Categoría],MATCH(tblMovimientos[[#This Row],[SKU]],tblProductos[SKU],0))),"⚠ Categoría no coincide",IF(tblMovimientos[[#This Row],[Saldo]]<0,"✖ Stock insuficiente",IF(AND(LEFT(tblMovimientos[[#This Row],[Tipo]],6)="AJUSTE",tblMovimientos[[#This Row],[Observaciones]]=""),"⚠ Justifique el ajuste","✔ Registrado")))))))))
B17: =IF((tblMovimientos[[#This Row],[Fecha]]&tblMovimientos[[#This Row],[Tipo]]&tblMovimientos[[#This Row],[Producto]]&tblMovimientos[[#This Row],[Cantidad]])="","",ROW()-ROW(tblMovimientos[#Headers])) | G17: =IF(tblMovimientos[[#This Row],[Producto]]="","",TRIM(LEFT(tblMovimientos[[#This Row],[Producto]],FIND(" · ",tblMovimientos[[#This Row],[Producto]]&" · ")-1))) | H17: =IF(tblMovimientos[[#This Row],[SKU]]="","",IFERROR(INDEX(tblProductos[Unidad],MATCH(tblMovimientos[[#This Row],[SKU]],tblProductos[SKU],0)),"?")) | J17: =IF(tblMovimientos[[#This Row],[Tipo]]="","",IFERROR(INDEX(tblTiposMov[FactorStock],MATCH(tblMovimientos[[#This Row],[Tipo]],tblTiposMov[Tipo],0)),0)) | K17: =IF(OR(tblMovimientos[[#This Row],[Cantidad]]="",tblMovimientos[[#This Row],[FactorStock]]=""),"",IF(ISNUMBER(tblMovimientos[[#This Row],[Cantidad]]),tblMovimientos[[#This Row],[Cantidad]]*tblMovimientos[[#This Row],[FactorStock]],"")) | L17: =IF(tblMovimientos[[#This Row],[CantidadNeta]]="","",SUMIFS(INDEX(tblMovimientos[CantidadNeta],1):tblMovimientos[[#This Row],[CantidadNeta]],INDEX(tblMovimientos[SKU],1):tblMovimientos[[#This Row],[SKU]],tblMovimientos[[#This Row],[SKU]])) | M17: =IF((tblMovimientos[[#This Row],[Fecha]]&tblMovimientos[[#This Row],[Tipo]]&tblMovimientos[[#This Row],[Producto]]&tblMovimientos[[#This Row],[Cantidad]])="","",IF(OR(tblMovimientos[[#This Row],[Fecha]]="",tblMovimientos[[#This Row],[Tipo]]="",tblMovimientos[[#This Row],[Producto]]="",tblMovimientos[[#This Row],[Cantidad]]="",tblMovimientos[[#This Row],[Responsable]]=""),"⚠ Incompleto",IF(tblMovimientos[[#This Row],[Unidad]]="?","✖ Producto no existe",IF(tblMovimientos[[#This Row],[FactorStock]]=0,"✖ Tipo no válido",IF(NOT(ISNUMBER(tblMovimientos[[#This Row],[Cantidad]])),"✖ Cantidad inválida",IF(tblMovimientos[[#This Row],[Cantidad]]<=0,"✖ Cantidad inválida",IF(AND(tblMovimientos[[#This Row],[Categoría]]<>"",tblMovimientos[[#This Row],[Categoría]]<>INDEX(tblProductos[Categoría],MATCH(tblMovimientos[[#This Row],[SKU]],tblProductos[SKU],0))),"⚠ Categoría no coincide",IF(tblMovimientos[[#This Row],[Saldo]]<0,"✖ Stock insuficiente",IF(AND(LEFT(tblMovimientos[[#This Row],[Tipo]],6)="AJUSTE",tblMovimientos[[#This Row],[Observaciones]]=""),"⚠ Justifique el ajuste","✔ Registrado")))))))))
B18: =IF((tblMovimientos[[#This Row],[Fecha]]&tblMovimientos[[#This Row],[Tipo]]&tblMovimientos[[#This Row],[Producto]]&tblMovimientos[[#This Row],[Cantidad]])="","",ROW()-ROW(tblMovimientos[#Headers])) | G18: =IF(tblMovimientos[[#This Row],[Producto]]="","",TRIM(LEFT(tblMovimientos[[#This Row],[Producto]],FIND(" · ",tblMovimientos[[#This Row],[Producto]]&" · ")-1))) | H18: =IF(tblMovimientos[[#This Row],[SKU]]="","",IFERROR(INDEX(tblProductos[Unidad],MATCH(tblMovimientos[[#This Row],[SKU]],tblProductos[SKU],0)),"?")) | J18: =IF(tblMovimientos[[#This Row],[Tipo]]="","",IFERROR(INDEX(tblTiposMov[FactorStock],MATCH(tblMovimientos[[#This Row],[Tipo]],tblTiposMov[Tipo],0)),0)) | K18: =IF(OR(tblMovimientos[[#This Row],[Cantidad]]="",tblMovimientos[[#This Row],[FactorStock]]=""),"",IF(ISNUMBER(tblMovimientos[[#This Row],[Cantidad]]),tblMovimientos[[#This Row],[Cantidad]]*tblMovimientos[[#This Row],[FactorStock]],"")) | L18: =IF(tblMovimientos[[#This Row],[CantidadNeta]]="","",SUMIFS(INDEX(tblMovimientos[CantidadNeta],1):tblMovimientos[[#This Row],[CantidadNeta]],INDEX(tblMovimientos[SKU],1):tblMovimientos[[#This Row],[SKU]],tblMovimientos[[#This Row],[SKU]])) | M18: =IF((tblMovimientos[[#This Row],[Fecha]]&tblMovimientos[[#This Row],[Tipo]]&tblMovimientos[[#This Row],[Producto]]&tblMovimientos[[#This Row],[Cantidad]])="","",IF(OR(tblMovimientos[[#This Row],[Fecha]]="",tblMovimientos[[#This Row],[Tipo]]="",tblMovimientos[[#This Row],[Producto]]="",tblMovimientos[[#This Row],[Cantidad]]="",tblMovimientos[[#This Row],[Responsable]]=""),"⚠ Incompleto",IF(tblMovimientos[[#This Row],[Unidad]]="?","✖ Producto no existe",IF(tblMovimientos[[#This Row],[FactorStock]]=0,"✖ Tipo no válido",IF(NOT(ISNUMBER(tblMovimientos[[#This Row],[Cantidad]])),"✖ Cantidad inválida",IF(tblMovimientos[[#This Row],[Cantidad]]<=0,"✖ Cantidad inválida",IF(AND(tblMovimientos[[#This Row],[Categoría]]<>"",tblMovimientos[[#This Row],[Categoría]]<>INDEX(tblProductos[Categoría],MATCH(tblMovimientos[[#This Row],[SKU]],tblProductos[SKU],0))),"⚠ Categoría no coincide",IF(tblMovimientos[[#This Row],[Saldo]]<0,"✖ Stock insuficiente",IF(AND(LEFT(tblMovimientos[[#This Row],[Tipo]],6)="AJUSTE",tblMovimientos[[#This Row],[Observaciones]]=""),"⚠ Justifique el ajuste","✔ Registrado")))))))))
B19: =IF((tblMovimientos[[#This Row],[Fecha]]&tblMovimientos[[#This Row],[Tipo]]&tblMovimientos[[#This Row],[Producto]]&tblMovimientos[[#This Row],[Cantidad]])="","",ROW()-ROW(tblMovimientos[#Headers])) | G19: =IF(tblMovimientos[[#This Row],[Producto]]="","",TRIM(LEFT(tblMovimientos[[#This Row],[Producto]],FIND(" · ",tblMovimientos[[#This Row],[Producto]]&" · ")-1))) | H19: =IF(tblMovimientos[[#This Row],[SKU]]="","",IFERROR(INDEX(tblProductos[Unidad],MATCH(tblMovimientos[[#This Row],[SKU]],tblProductos[SKU],0)),"?")) | J19: =IF(tblMovimientos[[#This Row],[Tipo]]="","",IFERROR(INDEX(tblTiposMov[FactorStock],MATCH(tblMovimientos[[#This Row],[Tipo]],tblTiposMov[Tipo],0)),0)) | K19: =IF(OR(tblMovimientos[[#This Row],[Cantidad]]="",tblMovimientos[[#This Row],[FactorStock]]=""),"",IF(ISNUMBER(tblMovimientos[[#This Row],[Cantidad]]),tblMovimientos[[#This Row],[Cantidad]]*tblMovimientos[[#This Row],[FactorStock]],"")) | L19: =IF(tblMovimientos[[#This Row],[CantidadNeta]]="","",SUMIFS(INDEX(tblMovimientos[CantidadNeta],1):tblMovimientos[[#This Row],[CantidadNeta]],INDEX(tblMovimientos[SKU],1):tblMovimientos[[#This Row],[SKU]],tblMovimientos[[#This Row],[SKU]])) | M19: =IF((tblMovimientos[[#This Row],[Fecha]]&tblMovimientos[[#This Row],[Tipo]]&tblMovimientos[[#This Row],[Producto]]&tblMovimientos[[#This Row],[Cantidad]])="","",IF(OR(tblMovimientos[[#This Row],[Fecha]]="",tblMovimientos[[#This Row],[Tipo]]="",tblMovimientos[[#This Row],[Producto]]="",tblMovimientos[[#This Row],[Cantidad]]="",tblMovimientos[[#This Row],[Responsable]]=""),"⚠ Incompleto",IF(tblMovimientos[[#This Row],[Unidad]]="?","✖ Producto no existe",IF(tblMovimientos[[#This Row],[FactorStock]]=0,"✖ Tipo no válido",IF(NOT(ISNUMBER(tblMovimientos[[#This Row],[Cantidad]])),"✖ Cantidad inválida",IF(tblMovimientos[[#This Row],[Cantidad]]<=0,"✖ Cantidad inválida",IF(AND(tblMovimientos[[#This Row],[Categoría]]<>"",tblMovimientos[[#This Row],[Categoría]]<>INDEX(tblProductos[Categoría],MATCH(tblMovimientos[[#This Row],[SKU]],tblProductos[SKU],0))),"⚠ Categoría no coincide",IF(tblMovimientos[[#This Row],[Saldo]]<0,"✖ Stock insuficiente",IF(AND(LEFT(tblMovimientos[[#This Row],[Tipo]],6)="AJUSTE",tblMovimientos[[#This Row],[Observaciones]]=""),"⚠ Justifique el ajuste","✔ Registrado")))))))))
... B5007: =IF((tblMovimientos[[#This Row],[Fecha]]&tblMovimientos[[#This Row],[Tipo]]&tblMovimientos[[#This Row],[Producto]]&tblMovimientos[[#This Row],[Cantidad]])="","",ROW()-ROW(tblMovimientos[#Headers])) | G5007: =IF(tblMovimientos[[#This Row],[Producto]]="","",TRIM(LEFT(tblMovimientos[[#This Row],[Producto]],FIND(" · ",tblMovimientos[[#This Row],[Producto]]&" · ")-1))) | H5007: =IF(tblMovimientos[[#This Row],[SKU]]="","",IFERROR(INDEX(tblProductos[Unidad],MATCH(tblMovimientos[[#This Row],[SKU]],tblProductos[SKU],0)),"?")) | J5007: =IF(tblMovimientos[[#This Row],[Tipo]]="","",IFERROR(INDEX(tblTiposMov[FactorStock],MATCH(tblMovimientos[[#This Row],[Tipo]],tblTiposMov[Tipo],0)),0)) | K5007: =IF(OR(tblMovimientos[[#This Row],[Cantidad]]="",tblMovimientos[[#This Row],[FactorStock]]=""),"",IF(ISNUMBER(tblMovimientos[[#This Row],[Cantidad]]),tblMovimientos[[#This Row],[Cantidad]]*tblMovimientos[[#This Row],[FactorStock]],"")) | L5007: =IF(tblMovimientos[[#This Row],[CantidadNeta]]="","",SUMIFS(INDEX(tblMovimientos[CantidadNeta],1):tblMovimientos[[#This Row],[CantidadNeta]],INDEX(tblMovimientos[SKU],1):tblMovimientos[[#This Row],[SKU]],tblMovimientos[[#This Row],[SKU]])) | M5007: =IF((tblMovimientos[[#This Row],[Fecha]]&tblMovimientos[[#This Row],[Tipo]]&tblMovimientos[[#This Row],[Producto]]&tblMovimientos[[#This Row],[Cantidad]])="","",IF(OR(tblMovimientos[[#This Row],[Fecha]]="",tblMovimientos[[#This Row],[Tipo]]="",tblMovimientos[[#This Row],[Producto]]="",tblMovimientos[[#This Row],[Cantidad]]="",tblMovimientos[[#This Row],[Responsable]]=""),"⚠ Incompleto",IF(tblMovimientos[[#This Row],[Unidad]]="?","✖ Producto no existe",IF(tblMovimientos[[#This Row],[FactorStock]]=0,"✖ Tipo no válido",IF(NOT(ISNUMBER(tblMovimientos[[#This Row],[Cantidad]])),"✖ Cantidad inválida",IF(tblMovimientos[[#This Row],[Cantidad]]<=0,"✖ Cantidad inválida",IF(AND(tblMovimientos[[#This Row],[Categoría]]<>"",tblMovimientos[[#This Row],[Categoría]]<>INDEX(tblProductos[Categoría],MATCH(tblMovimientos[[#This Row],[SKU]],tblProductos[SKU],0))),"⚠ Categoría no coincide",IF(tblMovimientos[[#This Row],[Saldo]]<0,"✖ Stock insuficiente",IF(AND(LEFT(tblMovimientos[[#This Row],[Tipo]],6)="AJUSTE",tblMovimientos[[#This Row],[Observaciones]]=""),"⚠ Justifique el ajuste","✔ Registrado")))))))))

Sheet 13_CONTEO
B2: Toma física de inventario
B3: Comando · Compare el conteo con el sistema y convierta las diferencias en ajustes de la bitácora
J5: Fecha: | L5: Responsable:
B6: ƒx | C6: ƒx | D6: ƒx | E6: ƒx | F6: ƒx | G6: ƒx | H6: ƒx | I6: ✎ | J6: ƒx | K6: ƒx | L6: ƒx | M6: ƒx
B7: SKU | C7: Producto | D7: Categoría | E7: Ubicación | F7: Unidad | G7: Activo | H7: StockSistema | I7: Conteo | J7: Diferencia | K7: ValorDiferencia | L7: Resultado | M7: AjusteSugerido
B8: =IF('05_PRODUCTOS'!$B8="","",'05_PRODUCTOS'!$B8) | C8: =IF($B8="","",'05_PRODUCTOS'!$C8) | D8: =IF($B8="","",'05_PRODUCTOS'!$D8) | E8: =IF($B8="","",'05_PRODUCTOS'!$J8&"") | F8: =IF($B8="","",'05_PRODUCTOS'!$E8) | G8: =IF($B8="","",IF('05_PRODUCTOS'!$K8="NO","NO","SI")) | H8: =IF($B8="","",N('15_STOCK'!$J8)) | J8: =IF(OR(tblConteo[[#This Row],[SKU]]="",tblConteo[[#This Row],[Conteo]]=""),"",tblConteo[[#This Row],[Conteo]]-tblConteo[[#This Row],[StockSistema]]) | K8: =IF($J8="","",$J8*N('15_STOCK'!$O8)) | L8: =IF(tblConteo[[#This Row],[Diferencia]]="","",IF(tblConteo[[#This Row],[Diferencia]]=0,"✔ Cuadra",IF(tblConteo[[#This Row],[Diferencia]]>0,"▲ Sobrante","▼ Faltante"))) | M8: =IF(OR(tblConteo[[#This Row],[Diferencia]]="",tblConteo[[#This Row],[Diferencia]]=0),"",IF(tblConteo[[#This Row],[Diferencia]]>0,"AJUSTE (+) ","AJUSTE (-) ")&ABS(tblConteo[[#This Row],[Diferencia]])&" "&tblConteo[[#This Row],[Unidad]])
B9: =IF('05_PRODUCTOS'!$B9="","",'05_PRODUCTOS'!$B9) | C9: =IF($B9="","",'05_PRODUCTOS'!$C9) | D9: =IF($B9="","",'05_PRODUCTOS'!$D9) | E9: =IF($B9="","",'05_PRODUCTOS'!$J9&"") | F9: =IF($B9="","",'05_PRODUCTOS'!$E9) | G9: =IF($B9="","",IF('05_PRODUCTOS'!$K9="NO","NO","SI")) | H9: =IF($B9="","",N('15_STOCK'!$J9)) | J9: =IF(OR(tblConteo[[#This Row],[SKU]]="",tblConteo[[#This Row],[Conteo]]=""),"",tblConteo[[#This Row],[Conteo]]-tblConteo[[#This Row],[StockSistema]]) | K9: =IF($J9="","",$J9*N('15_STOCK'!$O9)) | L9: =IF(tblConteo[[#This Row],[Diferencia]]="","",IF(tblConteo[[#This Row],[Diferencia]]=0,"✔ Cuadra",IF(tblConteo[[#This Row],[Diferencia]]>0,"▲ Sobrante","▼ Faltante"))) | M9: =IF(OR(tblConteo[[#This Row],[Diferencia]]="",tblConteo[[#This Row],[Diferencia]]=0),"",IF(tblConteo[[#This Row],[Diferencia]]>0,"AJUSTE (+) ","AJUSTE (-) ")&ABS(tblConteo[[#This Row],[Diferencia]])&" "&tblConteo[[#This Row],[Unidad]])
B10: =IF('05_PRODUCTOS'!$B10="","",'05_PRODUCTOS'!$B10) | C10: =IF($B10="","",'05_PRODUCTOS'!$C10) | D10: =IF($B10="","",'05_PRODUCTOS'!$D10) | E10: =IF($B10="","",'05_PRODUCTOS'!$J10&"") | F10: =IF($B10="","",'05_PRODUCTOS'!$E10) | G10: =IF($B10="","",IF('05_PRODUCTOS'!$K10="NO","NO","SI")) | H10: =IF($B10="","",N('15_STOCK'!$J10)) | J10: =IF(OR(tblConteo[[#This Row],[SKU]]="",tblConteo[[#This Row],[Conteo]]=""),"",tblConteo[[#This Row],[Conteo]]-tblConteo[[#This Row],[StockSistema]]) | K10: =IF($J10="","",$J10*N('15_STOCK'!$O10)) | L10: =IF(tblConteo[[#This Row],[Diferencia]]="","",IF(tblConteo[[#This Row],[Diferencia]]=0,"✔ Cuadra",IF(tblConteo[[#This Row],[Diferencia]]>0,"▲ Sobrante","▼ Faltante"))) | M10: =IF(OR(tblConteo[[#This Row],[Diferencia]]="",tblConteo[[#This Row],[Diferencia]]=0),"",IF(tblConteo[[#This Row],[Diferencia]]>0,"AJUSTE (+) ","AJUSTE (-) ")&ABS(tblConteo[[#This Row],[Diferencia]])&" "&tblConteo[[#This Row],[Unidad]])
B11: =IF('05_PRODUCTOS'!$B11="","",'05_PRODUCTOS'!$B11) | C11: =IF($B11="","",'05_PRODUCTOS'!$C11) | D11: =IF($B11="","",'05_PRODUCTOS'!$D11) | E11: =IF($B11="","",'05_PRODUCTOS'!$J11&"") | F11: =IF($B11="","",'05_PRODUCTOS'!$E11) | G11: =IF($B11="","",IF('05_PRODUCTOS'!$K11="NO","NO","SI")) | H11: =IF($B11="","",N('15_STOCK'!$J11)) | J11: =IF(OR(tblConteo[[#This Row],[SKU]]="",tblConteo[[#This Row],[Conteo]]=""),"",tblConteo[[#This Row],[Conteo]]-tblConteo[[#This Row],[StockSistema]]) | K11: =IF($J11="","",$J11*N('15_STOCK'!$O11)) | L11: =IF(tblConteo[[#This Row],[Diferencia]]="","",IF(tblConteo[[#This Row],[Diferencia]]=0,"✔ Cuadra",IF(tblConteo[[#This Row],[Diferencia]]>0,"▲ Sobrante","▼ Faltante"))) | M11: =IF(OR(tblConteo[[#This Row],[Diferencia]]="",tblConteo[[#This Row],[Diferencia]]=0),"",IF(tblConteo[[#This Row],[Diferencia]]>0,"AJUSTE (+) ","AJUSTE (-) ")&ABS(tblConteo[[#This Row],[Diferencia]])&" "&tblConteo[[#This Row],[Unidad]])
B12: =IF('05_PRODUCTOS'!$B12="","",'05_PRODUCTOS'!$B12) | C12: =IF($B12="","",'05_PRODUCTOS'!$C12) | D12: =IF($B12="","",'05_PRODUCTOS'!$D12) | E12: =IF($B12="","",'05_PRODUCTOS'!$J12&"") | F12: =IF($B12="","",'05_PRODUCTOS'!$E12) | G12: =IF($B12="","",IF('05_PRODUCTOS'!$K12="NO","NO","SI")) | H12: =IF($B12="","",N('15_STOCK'!$J12)) | J12: =IF(OR(tblConteo[[#This Row],[SKU]]="",tblConteo[[#This Row],[Conteo]]=""),"",tblConteo[[#This Row],[Conteo]]-tblConteo[[#This Row],[StockSistema]]) | K12: =IF($J12="","",$J12*N('15_STOCK'!$O12)) | L12: =IF(tblConteo[[#This Row],[Diferencia]]="","",IF(tblConteo[[#This Row],[Diferencia]]=0,"✔ Cuadra",IF(tblConteo[[#This Row],[Diferencia]]>0,"▲ Sobrante","▼ Faltante"))) | M12: =IF(OR(tblConteo[[#This Row],[Diferencia]]="",tblConteo[[#This Row],[Diferencia]]=0),"",IF(tblConteo[[#This Row],[Diferencia]]>0,"AJUSTE (+) ","AJUSTE (-) ")&ABS(tblConteo[[#This Row],[Diferencia]])&" "&tblConteo[[#This Row],[Unidad]])
B13: =IF('05_PRODUCTOS'!$B13="","",'05_PRODUCTOS'!$B13) | C13: =IF($B13="","",'05_PRODUCTOS'!$C13) | D13: =IF($B13="","",'05_PRODUCTOS'!$D13) | E13: =IF($B13="","",'05_PRODUCTOS'!$J13&"") | F13: =IF($B13="","",'05_PRODUCTOS'!$E13) | G13: =IF($B13="","",IF('05_PRODUCTOS'!$K13="NO","NO","SI")) | H13: =IF($B13="","",N('15_STOCK'!$J13)) | J13: =IF(OR(tblConteo[[#This Row],[SKU]]="",tblConteo[[#This Row],[Conteo]]=""),"",tblConteo[[#This Row],[Conteo]]-tblConteo[[#This Row],[StockSistema]]) | K13: =IF($J13="","",$J13*N('15_STOCK'!$O13)) | L13: =IF(tblConteo[[#This Row],[Diferencia]]="","",IF(tblConteo[[#This Row],[Diferencia]]=0,"✔ Cuadra",IF(tblConteo[[#This Row],[Diferencia]]>0,"▲ Sobrante","▼ Faltante"))) | M13: =IF(OR(tblConteo[[#This Row],[Diferencia]]="",tblConteo[[#This Row],[Diferencia]]=0),"",IF(tblConteo[[#This Row],[Diferencia]]>0,"AJUSTE (+) ","AJUSTE (-) ")&ABS(tblConteo[[#This Row],[Diferencia]])&" "&tblConteo[[#This Row],[Unidad]])
B14: =IF('05_PRODUCTOS'!$B14="","",'05_PRODUCTOS'!$B14) | C14: =IF($B14="","",'05_PRODUCTOS'!$C14) | D14: =IF($B14="","",'05_PRODUCTOS'!$D14) | E14: =IF($B14="","",'05_PRODUCTOS'!$J14&"") | F14: =IF($B14="","",'05_PRODUCTOS'!$E14) | G14: =IF($B14="","",IF('05_PRODUCTOS'!$K14="NO","NO","SI")) | H14: =IF($B14="","",N('15_STOCK'!$J14)) | J14: =IF(OR(tblConteo[[#This Row],[SKU]]="",tblConteo[[#This Row],[Conteo]]=""),"",tblConteo[[#This Row],[Conteo]]-tblConteo[[#This Row],[StockSistema]]) | K14: =IF($J14="","",$J14*N('15_STOCK'!$O14)) | L14: =IF(tblConteo[[#This Row],[Diferencia]]="","",IF(tblConteo[[#This Row],[Diferencia]]=0,"✔ Cuadra",IF(tblConteo[[#This Row],[Diferencia]]>0,"▲ Sobrante","▼ Faltante"))) | M14: =IF(OR(tblConteo[[#This Row],[Diferencia]]="",tblConteo[[#This Row],[Diferencia]]=0),"",IF(tblConteo[[#This Row],[Diferencia]]>0,"AJUSTE (+) ","AJUSTE (-) ")&ABS(tblConteo[[#This Row],[Diferencia]])&" "&tblConteo[[#This Row],[Unidad]])
B15: =IF('05_PRODUCTOS'!$B15="","",'05_PRODUCTOS'!$B15) | C15: =IF($B15="","",'05_PRODUCTOS'!$C15) | D15: =IF($B15="","",'05_PRODUCTOS'!$D15) | E15: =IF($B15="","",'05_PRODUCTOS'!$J15&"") | F15: =IF($B15="","",'05_PRODUCTOS'!$E15) | G15: =IF($B15="","",IF('05_PRODUCTOS'!$K15="NO","NO","SI")) | H15: =IF($B15="","",N('15_STOCK'!$J15)) | J15: =IF(OR(tblConteo[[#This Row],[SKU]]="",tblConteo[[#This Row],[Conteo]]=""),"",tblConteo[[#This Row],[Conteo]]-tblConteo[[#This Row],[StockSistema]]) | K15: =IF($J15="","",$J15*N('15_STOCK'!$O15)) | L15: =IF(tblConteo[[#This Row],[Diferencia]]="","",IF(tblConteo[[#This Row],[Diferencia]]=0,"✔ Cuadra",IF(tblConteo[[#This Row],[Diferencia]]>0,"▲ Sobrante","▼ Faltante"))) | M15: =IF(OR(tblConteo[[#This Row],[Diferencia]]="",tblConteo[[#This Row],[Diferencia]]=0),"",IF(tblConteo[[#This Row],[Diferencia]]>0,"AJUSTE (+) ","AJUSTE (-) ")&ABS(tblConteo[[#This Row],[Diferencia]])&" "&tblConteo[[#This Row],[Unidad]])
B16: =IF('05_PRODUCTOS'!$B16="","",'05_PRODUCTOS'!$B16) | C16: =IF($B16="","",'05_PRODUCTOS'!$C16) | D16: =IF($B16="","",'05_PRODUCTOS'!$D16) | E16: =IF($B16="","",'05_PRODUCTOS'!$J16&"") | F16: =IF($B16="","",'05_PRODUCTOS'!$E16) | G16: =IF($B16="","",IF('05_PRODUCTOS'!$K16="NO","NO","SI")) | H16: =IF($B16="","",N('15_STOCK'!$J16)) | J16: =IF(OR(tblConteo[[#This Row],[SKU]]="",tblConteo[[#This Row],[Conteo]]=""),"",tblConteo[[#This Row],[Conteo]]-tblConteo[[#This Row],[StockSistema]]) | K16: =IF($J16="","",$J16*N('15_STOCK'!$O16)) | L16: =IF(tblConteo[[#This Row],[Diferencia]]="","",IF(tblConteo[[#This Row],[Diferencia]]=0,"✔ Cuadra",IF(tblConteo[[#This Row],[Diferencia]]>0,"▲ Sobrante","▼ Faltante"))) | M16: =IF(OR(tblConteo[[#This Row],[Diferencia]]="",tblConteo[[#This Row],[Diferencia]]=0),"",IF(tblConteo[[#This Row],[Diferencia]]>0,"AJUSTE (+) ","AJUSTE (-) ")&ABS(tblConteo[[#This Row],[Diferencia]])&" "&tblConteo[[#This Row],[Unidad]])
B17: =IF('05_PRODUCTOS'!$B17="","",'05_PRODUCTOS'!$B17) | C17: =IF($B17="","",'05_PRODUCTOS'!$C17) | D17: =IF($B17="","",'05_PRODUCTOS'!$D17) | E17: =IF($B17="","",'05_PRODUCTOS'!$J17&"") | F17: =IF($B17="","",'05_PRODUCTOS'!$E17) | G17: =IF($B17="","",IF('05_PRODUCTOS'!$K17="NO","NO","SI")) | H17: =IF($B17="","",N('15_STOCK'!$J17)) | J17: =IF(OR(tblConteo[[#This Row],[SKU]]="",tblConteo[[#This Row],[Conteo]]=""),"",tblConteo[[#This Row],[Conteo]]-tblConteo[[#This Row],[StockSistema]]) | K17: =IF($J17="","",$J17*N('15_STOCK'!$O17)) | L17: =IF(tblConteo[[#This Row],[Diferencia]]="","",IF(tblConteo[[#This Row],[Diferencia]]=0,"✔ Cuadra",IF(tblConteo[[#This Row],[Diferencia]]>0,"▲ Sobrante","▼ Faltante"))) | M17: =IF(OR(tblConteo[[#This Row],[Diferencia]]="",tblConteo[[#This Row],[Diferencia]]=0),"",IF(tblConteo[[#This Row],[Diferencia]]>0,"AJUSTE (+) ","AJUSTE (-) ")&ABS(tblConteo[[#This Row],[Diferencia]])&" "&tblConteo[[#This Row],[Unidad]])
B18: =IF('05_PRODUCTOS'!$B18="","",'05_PRODUCTOS'!$B18) | C18: =IF($B18="","",'05_PRODUCTOS'!$C18) | D18: =IF($B18="","",'05_PRODUCTOS'!$D18) | E18: =IF($B18="","",'05_PRODUCTOS'!$J18&"") | F18: =IF($B18="","",'05_PRODUCTOS'!$E18) | G18: =IF($B18="","",IF('05_PRODUCTOS'!$K18="NO","NO","SI")) | H18: =IF($B18="","",N('15_STOCK'!$J18)) | J18: =IF(OR(tblConteo[[#This Row],[SKU]]="",tblConteo[[#This Row],[Conteo]]=""),"",tblConteo[[#This Row],[Conteo]]-tblConteo[[#This Row],[StockSistema]]) | K18: =IF($J18="","",$J18*N('15_STOCK'!$O18)) | L18: =IF(tblConteo[[#This Row],[Diferencia]]="","",IF(tblConteo[[#This Row],[Diferencia]]=0,"✔ Cuadra",IF(tblConteo[[#This Row],[Diferencia]]>0,"▲ Sobrante","▼ Faltante"))) | M18: =IF(OR(tblConteo[[#This Row],[Diferencia]]="",tblConteo[[#This Row],[Diferencia]]=0),"",IF(tblConteo[[#This Row],[Diferencia]]>0,"AJUSTE (+) ","AJUSTE (-) ")&ABS(tblConteo[[#This Row],[Diferencia]])&" "&tblConteo[[#This Row],[Unidad]])
B19: =IF('05_PRODUCTOS'!$B19="","",'05_PRODUCTOS'!$B19) | C19: =IF($B19="","",'05_PRODUCTOS'!$C19) | D19: =IF($B19="","",'05_PRODUCTOS'!$D19) | E19: =IF($B19="","",'05_PRODUCTOS'!$J19&"") | F19: =IF($B19="","",'05_PRODUCTOS'!$E19) | G19: =IF($B19="","",IF('05_PRODUCTOS'!$K19="NO","NO","SI")) | H19: =IF($B19="","",N('15_STOCK'!$J19)) | J19: =IF(OR(tblConteo[[#This Row],[SKU]]="",tblConteo[[#This Row],[Conteo]]=""),"",tblConteo[[#This Row],[Conteo]]-tblConteo[[#This Row],[StockSistema]]) | K19: =IF($J19="","",$J19*N('15_STOCK'!$O19)) | L19: =IF(tblConteo[[#This Row],[Diferencia]]="","",IF(tblConteo[[#This Row],[Diferencia]]=0,"✔ Cuadra",IF(tblConteo[[#This Row],[Diferencia]]>0,"▲ Sobrante","▼ Faltante"))) | M19: =IF(OR(tblConteo[[#This Row],[Diferencia]]="",tblConteo[[#This Row],[Diferencia]]=0),"",IF(tblConteo[[#This Row],[Diferencia]]>0,"AJUSTE (+) ","AJUSTE (-) ")&ABS(tblConteo[[#This Row],[Diferencia]])&" "&tblConteo[[#This Row],[Unidad]])
... B507: =IF('05_PRODUCTOS'!$B507="","",'05_PRODUCTOS'!$B507) | C507: =IF($B507="","",'05_PRODUCTOS'!$C507) | D507: =IF($B507="","",'05_PRODUCTOS'!$D507) | E507: =IF($B507="","",'05_PRODUCTOS'!$J507&"") | F507: =IF($B507="","",'05_PRODUCTOS'!$E507) | G507: =IF($B507="","",IF('05_PRODUCTOS'!$K507="NO","NO","SI")) | H507: =IF($B507="","",N('15_STOCK'!$J507)) | J507: =IF(OR(tblConteo[[#This Row],[SKU]]="",tblConteo[[#This Row],[Conteo]]=""),"",tblConteo[[#This Row],[Conteo]]-tblConteo[[#This Row],[StockSistema]]) | K507: =IF($J507="","",$J507*N('15_STOCK'!$O507)) | L507: =IF(tblConteo[[#This Row],[Diferencia]]="","",IF(tblConteo[[#This Row],[Diferencia]]=0,"✔ Cuadra",IF(tblConteo[[#This Row],[Diferencia]]>0,"▲ Sobrante","▼ Faltante"))) | M507: =IF(OR(tblConteo[[#This Row],[Diferencia]]="",tblConteo[[#This Row],[Diferencia]]=0),"",IF(tblConteo[[#This Row],[Diferencia]]>0,"AJUSTE (+) ","AJUSTE (-) ")&ABS(tblConteo[[#This Row],[Diferencia]])&" "&tblConteo[[#This Row],[Unidad]])

Sheet 15_STOCK
B2: Stock actual
B3: Capa de lectura · Proyección calculada con SUMAR.SI.CONJUNTO sobre la bitácora (no editable)
B6: ƒx | C6: ƒx | D6: ƒx | E6: ƒx | F6: ƒx | G6: ƒx | H6: ƒx | I6: ƒx | J6: ƒx | K6: ƒx | L6: ƒx | M6: ƒx | N6: ƒx | O6: ƒx | P6: ƒx | Q6: ƒx | R6: ƒx
B7: SKU | C7: Producto | D7: Categoría | E7: Proveedor | F7: Unidad | G7: Activo | H7: Entradas | I7: Salidas | J7: StockActual | K7: StockMin | L7: StockMax | M7: Nivel | N7: Estado | O7: CostoUnitario | P7: ValorInventario | Q7: UltimoMov | R7: DiasSinMov
B8: =IF('05_PRODUCTOS'!$B8="","",'05_PRODUCTOS'!$B8) | C8: =IF($B8="","",'05_PRODUCTOS'!$C8) | D8: =IF($B8="","",'05_PRODUCTOS'!$D8) | E8: =IF($B8="","",'05_PRODUCTOS'!$I8&"") | F8: =IF($B8="","",'05_PRODUCTOS'!$E8) | G8: =IF($B8="","",IF('05_PRODUCTOS'!$K8="NO","NO","SI")) | H8: =IF(tblStock[[#This Row],[SKU]]="","",SUMIFS(tblMovimientos[CantidadNeta],tblMovimientos[SKU],tblStock[[#This Row],[SKU]],tblMovimientos[FactorStock],1)) | I8: =IF(tblStock[[#This Row],[SKU]]="","",-SUMIFS(tblMovimientos[CantidadNeta],tblMovimientos[SKU],tblStock[[#This Row],[SKU]],tblMovimientos[FactorStock],-1)) | J8: =IF(tblStock[[#This Row],[SKU]]="","",SUMIFS(tblMovimientos[CantidadNeta],tblMovimientos[SKU],tblStock[[#This Row],[SKU]])) | K8: =IF($B8="","",N('05_PRODUCTOS'!$F8)) | L8: =IF($B8="","",N('05_PRODUCTOS'!$G8)) | M8: =IF(OR(tblStock[[#This Row],[SKU]]="",N(tblStock[[#This Row],[StockMax]])=0),"",MAX(0,tblStock[[#This Row],[StockActual]])/tblStock[[#This Row],[StockMax]]) | N8: =IF(tblStock[[#This Row],[SKU]]="","",IF(tblStock[[#This Row],[Activo]]="NO","INACTIVO",IF(tblStock[[#This Row],[StockActual]]<0,"INCONSISTENTE",IF(tblStock[[#This Row],[StockActual]]=0,"AGOTADO",IF(tblStock[[#This Row],[StockActual]]<=tblStock[[#This Row],[StockMin]],"CRÍTICO",IF(tblStock[[#This Row],[StockActual]]<=tblStock[[#This Row],[StockMin]]*(1+cfgMargenAlerta),"BAJO",IF(AND(tblStock[[#This Row],[StockMax]]>0,tblStock[[#This Row],[StockActual]]>tblStock[[#This Row],[StockMax]]),"SOBRESTOCK","ÓPTIMO"))))))) | O8: =IF($B8="","",N('05_PRODUCTOS'!$H8)) | P8: =IF(tblStock[[#This Row],[SKU]]="","",MAX(0,tblStock[[#This Row],[StockActual]])*tblStock[[#This Row],[CostoUnitario]]) | Q8: =IF(tblStock[[#This Row],[SKU]]="","",IFERROR(_xlfn.AGGREGATE(14,6,tblMovimientos[Fecha]/(tblMovimientos[SKU]=tblStock[[#This Row],[SKU]]),1),"")) | R8: =IF(OR(tblStock[[#This Row],[SKU]]="",tblStock[[#This Row],[UltimoMov]]=""),"",TODAY()-tblStock[[#This Row],[UltimoMov]])
B9: =IF('05_PRODUCTOS'!$B9="","",'05_PRODUCTOS'!$B9) | C9: =IF($B9="","",'05_PRODUCTOS'!$C9) | D9: =IF($B9="","",'05_PRODUCTOS'!$D9) | E9: =IF($B9="","",'05_PRODUCTOS'!$I9&"") | F9: =IF($B9="","",'05_PRODUCTOS'!$E9) | G9: =IF($B9="","",IF('05_PRODUCTOS'!$K9="NO","NO","SI")) | H9: =IF(tblStock[[#This Row],[SKU]]="","",SUMIFS(tblMovimientos[CantidadNeta],tblMovimientos[SKU],tblStock[[#This Row],[SKU]],tblMovimientos[FactorStock],1)) | I9: =IF(tblStock[[#This Row],[SKU]]="","",-SUMIFS(tblMovimientos[CantidadNeta],tblMovimientos[SKU],tblStock[[#This Row],[SKU]],tblMovimientos[FactorStock],-1)) | J9: =IF(tblStock[[#This Row],[SKU]]="","",SUMIFS(tblMovimientos[CantidadNeta],tblMovimientos[SKU],tblStock[[#This Row],[SKU]])) | K9: =IF($B9="","",N('05_PRODUCTOS'!$F9)) | L9: =IF($B9="","",N('05_PRODUCTOS'!$G9)) | M9: =IF(OR(tblStock[[#This Row],[SKU]]="",N(tblStock[[#This Row],[StockMax]])=0),"",MAX(0,tblStock[[#This Row],[StockActual]])/tblStock[[#This Row],[StockMax]]) | N9: =IF(tblStock[[#This Row],[SKU]]="","",IF(tblStock[[#This Row],[Activo]]="NO","INACTIVO",IF(tblStock[[#This Row],[StockActual]]<0,"INCONSISTENTE",IF(tblStock[[#This Row],[StockActual]]=0,"AGOTADO",IF(tblStock[[#This Row],[StockActual]]<=tblStock[[#This Row],[StockMin]],"CRÍTICO",IF(tblStock[[#This Row],[StockActual]]<=tblStock[[#This Row],[StockMin]]*(1+cfgMargenAlerta),"BAJO",IF(AND(tblStock[[#This Row],[StockMax]]>0,tblStock[[#This Row],[StockActual]]>tblStock[[#This Row],[StockMax]]),"SOBRESTOCK","ÓPTIMO"))))))) | O9: =IF($B9="","",N('05_PRODUCTOS'!$H9)) | P9: =IF(tblStock[[#This Row],[SKU]]="","",MAX(0,tblStock[[#This Row],[StockActual]])*tblStock[[#This Row],[CostoUnitario]]) | Q9: =IF(tblStock[[#This Row],[SKU]]="","",IFERROR(_xlfn.AGGREGATE(14,6,tblMovimientos[Fecha]/(tblMovimientos[SKU]=tblStock[[#This Row],[SKU]]),1),"")) | R9: =IF(OR(tblStock[[#This Row],[SKU]]="",tblStock[[#This Row],[UltimoMov]]=""),"",TODAY()-tblStock[[#This Row],[UltimoMov]])
B10: =IF('05_PRODUCTOS'!$B10="","",'05_PRODUCTOS'!$B10) | C10: =IF($B10="","",'05_PRODUCTOS'!$C10) | D10: =IF($B10="","",'05_PRODUCTOS'!$D10) | E10: =IF($B10="","",'05_PRODUCTOS'!$I10&"") | F10: =IF($B10="","",'05_PRODUCTOS'!$E10) | G10: =IF($B10="","",IF('05_PRODUCTOS'!$K10="NO","NO","SI")) | H10: =IF(tblStock[[#This Row],[SKU]]="","",SUMIFS(tblMovimientos[CantidadNeta],tblMovimientos[SKU],tblStock[[#This Row],[SKU]],tblMovimientos[FactorStock],1)) | I10: =IF(tblStock[[#This Row],[SKU]]="","",-SUMIFS(tblMovimientos[CantidadNeta],tblMovimientos[SKU],tblStock[[#This Row],[SKU]],tblMovimientos[FactorStock],-1)) | J10: =IF(tblStock[[#This Row],[SKU]]="","",SUMIFS(tblMovimientos[CantidadNeta],tblMovimientos[SKU],tblStock[[#This Row],[SKU]])) | K10: =IF($B10="","",N('05_PRODUCTOS'!$F10)) | L10: =IF($B10="","",N('05_PRODUCTOS'!$G10)) | M10: =IF(OR(tblStock[[#This Row],[SKU]]="",N(tblStock[[#This Row],[StockMax]])=0),"",MAX(0,tblStock[[#This Row],[StockActual]])/tblStock[[#This Row],[StockMax]]) | N10: =IF(tblStock[[#This Row],[SKU]]="","",IF(tblStock[[#This Row],[Activo]]="NO","INACTIVO",IF(tblStock[[#This Row],[StockActual]]<0,"INCONSISTENTE",IF(tblStock[[#This Row],[StockActual]]=0,"AGOTADO",IF(tblStock[[#This Row],[StockActual]]<=tblStock[[#This Row],[StockMin]],"CRÍTICO",IF(tblStock[[#This Row],[StockActual]]<=tblStock[[#This Row],[StockMin]]*(1+cfgMargenAlerta),"BAJO",IF(AND(tblStock[[#This Row],[StockMax]]>0,tblStock[[#This Row],[StockActual]]>tblStock[[#This Row],[StockMax]]),"SOBRESTOCK","ÓPTIMO"))))))) | O10: =IF($B10="","",N('05_PRODUCTOS'!$H10)) | P10: =IF(tblStock[[#This Row],[SKU]]="","",MAX(0,tblStock[[#This Row],[StockActual]])*tblStock[[#This Row],[CostoUnitario]]) | Q10: =IF(tblStock[[#This Row],[SKU]]="","",IFERROR(_xlfn.AGGREGATE(14,6,tblMovimientos[Fecha]/(tblMovimientos[SKU]=tblStock[[#This Row],[SKU]]),1),"")) | R10: =IF(OR(tblStock[[#This Row],[SKU]]="",tblStock[[#This Row],[UltimoMov]]=""),"",TODAY()-tblStock[[#This Row],[UltimoMov]])
B11: =IF('05_PRODUCTOS'!$B11="","",'05_PRODUCTOS'!$B11) | C11: =IF($B11="","",'05_PRODUCTOS'!$C11) | D11: =IF($B11="","",'05_PRODUCTOS'!$D11) | E11: =IF($B11="","",'05_PRODUCTOS'!$I11&"") | F11: =IF($B11="","",'05_PRODUCTOS'!$E11) | G11: =IF($B11="","",IF('05_PRODUCTOS'!$K11="NO","NO","SI")) | H11: =IF(tblStock[[#This Row],[SKU]]="","",SUMIFS(tblMovimientos[CantidadNeta],tblMovimientos[SKU],tblStock[[#This Row],[SKU]],tblMovimientos[FactorStock],1)) | I11: =IF(tblStock[[#This Row],[SKU]]="","",-SUMIFS(tblMovimientos[CantidadNeta],tblMovimientos[SKU],tblStock[[#This Row],[SKU]],tblMovimientos[FactorStock],-1)) | J11: =IF(tblStock[[#This Row],[SKU]]="","",SUMIFS(tblMovimientos[CantidadNeta],tblMovimientos[SKU],tblStock[[#This Row],[SKU]])) | K11: =IF($B11="","",N('05_PRODUCTOS'!$F11)) | L11: =IF($B11="","",N('05_PRODUCTOS'!$G11)) | M11: =IF(OR(tblStock[[#This Row],[SKU]]="",N(tblStock[[#This Row],[StockMax]])=0),"",MAX(0,tblStock[[#This Row],[StockActual]])/tblStock[[#This Row],[StockMax]]) | N11: =IF(tblStock[[#This Row],[SKU]]="","",IF(tblStock[[#This Row],[Activo]]="NO","INACTIVO",IF(tblStock[[#This Row],[StockActual]]<0,"INCONSISTENTE",IF(tblStock[[#This Row],[StockActual]]=0,"AGOTADO",IF(tblStock[[#This Row],[StockActual]]<=tblStock[[#This Row],[StockMin]],"CRÍTICO",IF(tblStock[[#This Row],[StockActual]]<=tblStock[[#This Row],[StockMin]]*(1+cfgMargenAlerta),"BAJO",IF(AND(tblStock[[#This Row],[StockMax]]>0,tblStock[[#This Row],[StockActual]]>tblStock[[#This Row],[StockMax]]),"SOBRESTOCK","ÓPTIMO"))))))) | O11: =IF($B11="","",N('05_PRODUCTOS'!$H11)) | P11: =IF(tblStock[[#This Row],[SKU]]="","",MAX(0,tblStock[[#This Row],[StockActual]])*tblStock[[#This Row],[CostoUnitario]]) | Q11: =IF(tblStock[[#This Row],[SKU]]="","",IFERROR(_xlfn.AGGREGATE(14,6,tblMovimientos[Fecha]/(tblMovimientos[SKU]=tblStock[[#This Row],[SKU]]),1),"")) | R11: =IF(OR(tblStock[[#This Row],[SKU]]="",tblStock[[#This Row],[UltimoMov]]=""),"",TODAY()-tblStock[[#This Row],[UltimoMov]])
B12: =IF('05_PRODUCTOS'!$B12="","",'05_PRODUCTOS'!$B12) | C12: =IF($B12="","",'05_PRODUCTOS'!$C12) | D12: =IF($B12="","",'05_PRODUCTOS'!$D12) | E12: =IF($B12="","",'05_PRODUCTOS'!$I12&"") | F12: =IF($B12="","",'05_PRODUCTOS'!$E12) | G12: =IF($B12="","",IF('05_PRODUCTOS'!$K12="NO","NO","SI")) | H12: =IF(tblStock[[#This Row],[SKU]]="","",SUMIFS(tblMovimientos[CantidadNeta],tblMovimientos[SKU],tblStock[[#This Row],[SKU]],tblMovimientos[FactorStock],1)) | I12: =IF(tblStock[[#This Row],[SKU]]="","",-SUMIFS(tblMovimientos[CantidadNeta],tblMovimientos[SKU],tblStock[[#This Row],[SKU]],tblMovimientos[FactorStock],-1)) | J12: =IF(tblStock[[#This Row],[SKU]]="","",SUMIFS(tblMovimientos[CantidadNeta],tblMovimientos[SKU],tblStock[[#This Row],[SKU]])) | K12: =IF($B12="","",N('05_PRODUCTOS'!$F12)) | L12: =IF($B12="","",N('05_PRODUCTOS'!$G12)) | M12: =IF(OR(tblStock[[#This Row],[SKU]]="",N(tblStock[[#This Row],[StockMax]])=0),"",MAX(0,tblStock[[#This Row],[StockActual]])/tblStock[[#This Row],[StockMax]]) | N12: =IF(tblStock[[#This Row],[SKU]]="","",IF(tblStock[[#This Row],[Activo]]="NO","INACTIVO",IF(tblStock[[#This Row],[StockActual]]<0,"INCONSISTENTE",IF(tblStock[[#This Row],[StockActual]]=0,"AGOTADO",IF(tblStock[[#This Row],[StockActual]]<=tblStock[[#This Row],[StockMin]],"CRÍTICO",IF(tblStock[[#This Row],[StockActual]]<=tblStock[[#This Row],[StockMin]]*(1+cfgMargenAlerta),"BAJO",IF(AND(tblStock[[#This Row],[StockMax]]>0,tblStock[[#This Row],[StockActual]]>tblStock[[#This Row],[StockMax]]),"SOBRESTOCK","ÓPTIMO"))))))) | O12: =IF($B12="","",N('05_PRODUCTOS'!$H12)) | P12: =IF(tblStock[[#This Row],[SKU]]="","",MAX(0,tblStock[[#This Row],[StockActual]])*tblStock[[#This Row],[CostoUnitario]]) | Q12: =IF(tblStock[[#This Row],[SKU]]="","",IFERROR(_xlfn.AGGREGATE(14,6,tblMovimientos[Fecha]/(tblMovimientos[SKU]=tblStock[[#This Row],[SKU]]),1),"")) | R12: =IF(OR(tblStock[[#This Row],[SKU]]="",tblStock[[#This Row],[UltimoMov]]=""),"",TODAY()-tblStock[[#This Row],[UltimoMov]])
B13: =IF('05_PRODUCTOS'!$B13="","",'05_PRODUCTOS'!$B13) | C13: =IF($B13="","",'05_PRODUCTOS'!$C13) | D13: =IF($B13="","",'05_PRODUCTOS'!$D13) | E13: =IF($B13="","",'05_PRODUCTOS'!$I13&"") | F13: =IF($B13="","",'05_PRODUCTOS'!$E13) | G13: =IF($B13="","",IF('05_PRODUCTOS'!$K13="NO","NO","SI")) | H13: =IF(tblStock[[#This Row],[SKU]]="","",SUMIFS(tblMovimientos[CantidadNeta],tblMovimientos[SKU],tblStock[[#This Row],[SKU]],tblMovimientos[FactorStock],1)) | I13: =IF(tblStock[[#This Row],[SKU]]="","",-SUMIFS(tblMovimientos[CantidadNeta],tblMovimientos[SKU],tblStock[[#This Row],[SKU]],tblMovimientos[FactorStock],-1)) | J13: =IF(tblStock[[#This Row],[SKU]]="","",SUMIFS(tblMovimientos[CantidadNeta],tblMovimientos[SKU],tblStock[[#This Row],[SKU]])) | K13: =IF($B13="","",N('05_PRODUCTOS'!$F13)) | L13: =IF($B13="","",N('05_PRODUCTOS'!$G13)) | M13: =IF(OR(tblStock[[#This Row],[SKU]]="",N(tblStock[[#This Row],[StockMax]])=0),"",MAX(0,tblStock[[#This Row],[StockActual]])/tblStock[[#This Row],[StockMax]]) | N13: =IF(tblStock[[#This Row],[SKU]]="","",IF(tblStock[[#This Row],[Activo]]="NO","INACTIVO",IF(tblStock[[#This Row],[StockActual]]<0,"INCONSISTENTE",IF(tblStock[[#This Row],[StockActual]]=0,"AGOTADO",IF(tblStock[[#This Row],[StockActual]]<=tblStock[[#This Row],[StockMin]],"CRÍTICO",IF(tblStock[[#This Row],[StockActual]]<=tblStock[[#This Row],[StockMin]]*(1+cfgMargenAlerta),"BAJO",IF(AND(tblStock[[#This Row],[StockMax]]>0,tblStock[[#This Row],[StockActual]]>tblStock[[#This Row],[StockMax]]),"SOBRESTOCK","ÓPTIMO"))))))) | O13: =IF($B13="","",N('05_PRODUCTOS'!$H13)) | P13: =IF(tblStock[[#This Row],[SKU]]="","",MAX(0,tblStock[[#This Row],[StockActual]])*tblStock[[#This Row],[CostoUnitario]]) | Q13: =IF(tblStock[[#This Row],[SKU]]="","",IFERROR(_xlfn.AGGREGATE(14,6,tblMovimientos[Fecha]/(tblMovimientos[SKU]=tblStock[[#This Row],[SKU]]),1),"")) | R13: =IF(OR(tblStock[[#This Row],[SKU]]="",tblStock[[#This Row],[UltimoMov]]=""),"",TODAY()-tblStock[[#This Row],[UltimoMov]])
B14: =IF('05_PRODUCTOS'!$B14="","",'05_PRODUCTOS'!$B14) | C14: =IF($B14="","",'05_PRODUCTOS'!$C14) | D14: =IF($B14="","",'05_PRODUCTOS'!$D14) | E14: =IF($B14="","",'05_PRODUCTOS'!$I14&"") | F14: =IF($B14="","",'05_PRODUCTOS'!$E14) | G14: =IF($B14="","",IF('05_PRODUCTOS'!$K14="NO","NO","SI")) | H14: =IF(tblStock[[#This Row],[SKU]]="","",SUMIFS(tblMovimientos[CantidadNeta],tblMovimientos[SKU],tblStock[[#This Row],[SKU]],tblMovimientos[FactorStock],1)) | I14: =IF(tblStock[[#This Row],[SKU]]="","",-SUMIFS(tblMovimientos[CantidadNeta],tblMovimientos[SKU],tblStock[[#This Row],[SKU]],tblMovimientos[FactorStock],-1)) | J14: =IF(tblStock[[#This Row],[SKU]]="","",SUMIFS(tblMovimientos[CantidadNeta],tblMovimientos[SKU],tblStock[[#This Row],[SKU]])) | K14: =IF($B14="","",N('05_PRODUCTOS'!$F14)) | L14: =IF($B14="","",N('05_PRODUCTOS'!$G14)) | M14: =IF(OR(tblStock[[#This Row],[SKU]]="",N(tblStock[[#This Row],[StockMax]])=0),"",MAX(0,tblStock[[#This Row],[StockActual]])/tblStock[[#This Row],[StockMax]]) | N14: =IF(tblStock[[#This Row],[SKU]]="","",IF(tblStock[[#This Row],[Activo]]="NO","INACTIVO",IF(tblStock[[#This Row],[StockActual]]<0,"INCONSISTENTE",IF(tblStock[[#This Row],[StockActual]]=0,"AGOTADO",IF(tblStock[[#This Row],[StockActual]]<=tblStock[[#This Row],[StockMin]],"CRÍTICO",IF(tblStock[[#This Row],[StockActual]]<=tblStock[[#This Row],[StockMin]]*(1+cfgMargenAlerta),"BAJO",IF(AND(tblStock[[#This Row],[StockMax]]>0,tblStock[[#This Row],[StockActual]]>tblStock[[#This Row],[StockMax]]),"SOBRESTOCK","ÓPTIMO"))))))) | O14: =IF($B14="","",N('05_PRODUCTOS'!$H14)) | P14: =IF(tblStock[[#This Row],[SKU]]="","",MAX(0,tblStock[[#This Row],[StockActual]])*tblStock[[#This Row],[CostoUnitario]]) | Q14: =IF(tblStock[[#This Row],[SKU]]="","",IFERROR(_xlfn.AGGREGATE(14,6,tblMovimientos[Fecha]/(tblMovimientos[SKU]=tblStock[[#This Row],[SKU]]),1),"")) | R14: =IF(OR(tblStock[[#This Row],[SKU]]="",tblStock[[#This Row],[UltimoMov]]=""),"",TODAY()-tblStock[[#This Row],[UltimoMov]])
B15: =IF('05_PRODUCTOS'!$B15="","",'05_PRODUCTOS'!$B15) | C15: =IF($B15="","",'05_PRODUCTOS'!$C15) | D15: =IF($B15="","",'05_PRODUCTOS'!$D15) | E15: =IF($B15="","",'05_PRODUCTOS'!$I15&"") | F15: =IF($B15="","",'05_PRODUCTOS'!$E15) | G15: =IF($B15="","",IF('05_PRODUCTOS'!$K15="NO","NO","SI")) | H15: =IF(tblStock[[#This Row],[SKU]]="","",SUMIFS(tblMovimientos[CantidadNeta],tblMovimientos[SKU],tblStock[[#This Row],[SKU]],tblMovimientos[FactorStock],1)) | I15: =IF(tblStock[[#This Row],[SKU]]="","",-SUMIFS(tblMovimientos[CantidadNeta],tblMovimientos[SKU],tblStock[[#This Row],[SKU]],tblMovimientos[FactorStock],-1)) | J15: =IF(tblStock[[#This Row],[SKU]]="","",SUMIFS(tblMovimientos[CantidadNeta],tblMovimientos[SKU],tblStock[[#This Row],[SKU]])) | K15: =IF($B15="","",N('05_PRODUCTOS'!$F15)) | L15: =IF($B15="","",N('05_PRODUCTOS'!$G15)) | M15: =IF(OR(tblStock[[#This Row],[SKU]]="",N(tblStock[[#This Row],[StockMax]])=0),"",MAX(0,tblStock[[#This Row],[StockActual]])/tblStock[[#This Row],[StockMax]]) | N15: =IF(tblStock[[#This Row],[SKU]]="","",IF(tblStock[[#This Row],[Activo]]="NO","INACTIVO",IF(tblStock[[#This Row],[StockActual]]<0,"INCONSISTENTE",IF(tblStock[[#This Row],[StockActual]]=0,"AGOTADO",IF(tblStock[[#This Row],[StockActual]]<=tblStock[[#This Row],[StockMin]],"CRÍTICO",IF(tblStock[[#This Row],[StockActual]]<=tblStock[[#This Row],[StockMin]]*(1+cfgMargenAlerta),"BAJO",IF(AND(tblStock[[#This Row],[StockMax]]>0,tblStock[[#This Row],[StockActual]]>tblStock[[#This Row],[StockMax]]),"SOBRESTOCK","ÓPTIMO"))))))) | O15: =IF($B15="","",N('05_PRODUCTOS'!$H15)) | P15: =IF(tblStock[[#This Row],[SKU]]="","",MAX(0,tblStock[[#This Row],[StockActual]])*tblStock[[#This Row],[CostoUnitario]]) | Q15: =IF(tblStock[[#This Row],[SKU]]="","",IFERROR(_xlfn.AGGREGATE(14,6,tblMovimientos[Fecha]/(tblMovimientos[SKU]=tblStock[[#This Row],[SKU]]),1),"")) | R15: =IF(OR(tblStock[[#This Row],[SKU]]="",tblStock[[#This Row],[UltimoMov]]=""),"",TODAY()-tblStock[[#This Row],[UltimoMov]])
B16: =IF('05_PRODUCTOS'!$B16="","",'05_PRODUCTOS'!$B16) | C16: =IF($B16="","",'05_PRODUCTOS'!$C16) | D16: =IF($B16="","",'05_PRODUCTOS'!$D16) | E16: =IF($B16="","",'05_PRODUCTOS'!$I16&"") | F16: =IF($B16="","",'05_PRODUCTOS'!$E16) | G16: =IF($B16="","",IF('05_PRODUCTOS'!$K16="NO","NO","SI")) | H16: =IF(tblStock[[#This Row],[SKU]]="","",SUMIFS(tblMovimientos[CantidadNeta],tblMovimientos[SKU],tblStock[[#This Row],[SKU]],tblMovimientos[FactorStock],1)) | I16: =IF(tblStock[[#This Row],[SKU]]="","",-SUMIFS(tblMovimientos[CantidadNeta],tblMovimientos[SKU],tblStock[[#This Row],[SKU]],tblMovimientos[FactorStock],-1)) | J16: =IF(tblStock[[#This Row],[SKU]]="","",SUMIFS(tblMovimientos[CantidadNeta],tblMovimientos[SKU],tblStock[[#This Row],[SKU]])) | K16: =IF($B16="","",N('05_PRODUCTOS'!$F16)) | L16: =IF($B16="","",N('05_PRODUCTOS'!$G16)) | M16: =IF(OR(tblStock[[#This Row],[SKU]]="",N(tblStock[[#This Row],[StockMax]])=0),"",MAX(0,tblStock[[#This Row],[StockActual]])/tblStock[[#This Row],[StockMax]]) | N16: =IF(tblStock[[#This Row],[SKU]]="","",IF(tblStock[[#This Row],[Activo]]="NO","INACTIVO",IF(tblStock[[#This Row],[StockActual]]<0,"INCONSISTENTE",IF(tblStock[[#This Row],[StockActual]]=0,"AGOTADO",IF(tblStock[[#This Row],[StockActual]]<=tblStock[[#This Row],[StockMin]],"CRÍTICO",IF(tblStock[[#This Row],[StockActual]]<=tblStock[[#This Row],[StockMin]]*(1+cfgMargenAlerta),"BAJO",IF(AND(tblStock[[#This Row],[StockMax]]>0,tblStock[[#This Row],[StockActual]]>tblStock[[#This Row],[StockMax]]),"SOBRESTOCK","ÓPTIMO"))))))) | O16: =IF($B16="","",N('05_PRODUCTOS'!$H16)) | P16: =IF(tblStock[[#This Row],[SKU]]="","",MAX(0,tblStock[[#This Row],[StockActual]])*tblStock[[#This Row],[CostoUnitario]]) | Q16: =IF(tblStock[[#This Row],[SKU]]="","",IFERROR(_xlfn.AGGREGATE(14,6,tblMovimientos[Fecha]/(tblMovimientos[SKU]=tblStock[[#This Row],[SKU]]),1),"")) | R16: =IF(OR(tblStock[[#This Row],[SKU]]="",tblStock[[#This Row],[UltimoMov]]=""),"",TODAY()-tblStock[[#This Row],[UltimoMov]])
B17: =IF('05_PRODUCTOS'!$B17="","",'05_PRODUCTOS'!$B17) | C17: =IF($B17="","",'05_PRODUCTOS'!$C17) | D17: =IF($B17="","",'05_PRODUCTOS'!$D17) | E17: =IF($B17="","",'05_PRODUCTOS'!$I17&"") | F17: =IF($B17="","",'05_PRODUCTOS'!$E17) | G17: =IF($B17="","",IF('05_PRODUCTOS'!$K17="NO","NO","SI")) | H17: =IF(tblStock[[#This Row],[SKU]]="","",SUMIFS(tblMovimientos[CantidadNeta],tblMovimientos[SKU],tblStock[[#This Row],[SKU]],tblMovimientos[FactorStock],1)) | I17: =IF(tblStock[[#This Row],[SKU]]="","",-SUMIFS(tblMovimientos[CantidadNeta],tblMovimientos[SKU],tblStock[[#This Row],[SKU]],tblMovimientos[FactorStock],-1)) | J17: =IF(tblStock[[#This Row],[SKU]]="","",SUMIFS(tblMovimientos[CantidadNeta],tblMovimientos[SKU],tblStock[[#This Row],[SKU]])) | K17: =IF($B17="","",N('05_PRODUCTOS'!$F17)) | L17: =IF($B17="","",N('05_PRODUCTOS'!$G17)) | M17: =IF(OR(tblStock[[#This Row],[SKU]]="",N(tblStock[[#This Row],[StockMax]])=0),"",MAX(0,tblStock[[#This Row],[StockActual]])/tblStock[[#This Row],[StockMax]]) | N17: =IF(tblStock[[#This Row],[SKU]]="","",IF(tblStock[[#This Row],[Activo]]="NO","INACTIVO",IF(tblStock[[#This Row],[StockActual]]<0,"INCONSISTENTE",IF(tblStock[[#This Row],[StockActual]]=0,"AGOTADO",IF(tblStock[[#This Row],[StockActual]]<=tblStock[[#This Row],[StockMin]],"CRÍTICO",IF(tblStock[[#This Row],[StockActual]]<=tblStock[[#This Row],[StockMin]]*(1+cfgMargenAlerta),"BAJO",IF(AND(tblStock[[#This Row],[StockMax]]>0,tblStock[[#This Row],[StockActual]]>tblStock[[#This Row],[StockMax]]),"SOBRESTOCK","ÓPTIMO"))))))) | O17: =IF($B17="","",N('05_PRODUCTOS'!$H17)) | P17: =IF(tblStock[[#This Row],[SKU]]="","",MAX(0,tblStock[[#This Row],[StockActual]])*tblStock[[#This Row],[CostoUnitario]]) | Q17: =IF(tblStock[[#This Row],[SKU]]="","",IFERROR(_xlfn.AGGREGATE(14,6,tblMovimientos[Fecha]/(tblMovimientos[SKU]=tblStock[[#This Row],[SKU]]),1),"")) | R17: =IF(OR(tblStock[[#This Row],[SKU]]="",tblStock[[#This Row],[UltimoMov]]=""),"",TODAY()-tblStock[[#This Row],[UltimoMov]])
B18: =IF('05_PRODUCTOS'!$B18="","",'05_PRODUCTOS'!$B18) | C18: =IF($B18="","",'05_PRODUCTOS'!$C18) | D18: =IF($B18="","",'05_PRODUCTOS'!$D18) | E18: =IF($B18="","",'05_PRODUCTOS'!$I18&"") | F18: =IF($B18="","",'05_PRODUCTOS'!$E18) | G18: =IF($B18="","",IF('05_PRODUCTOS'!$K18="NO","NO","SI")) | H18: =IF(tblStock[[#This Row],[SKU]]="","",SUMIFS(tblMovimientos[CantidadNeta],tblMovimientos[SKU],tblStock[[#This Row],[SKU]],tblMovimientos[FactorStock],1)) | I18: =IF(tblStock[[#This Row],[SKU]]="","",-SUMIFS(tblMovimientos[CantidadNeta],tblMovimientos[SKU],tblStock[[#This Row],[SKU]],tblMovimientos[FactorStock],-1)) | J18: =IF(tblStock[[#This Row],[SKU]]="","",SUMIFS(tblMovimientos[CantidadNeta],tblMovimientos[SKU],tblStock[[#This Row],[SKU]])) | K18: =IF($B18="","",N('05_PRODUCTOS'!$F18)) | L18: =IF($B18="","",N('05_PRODUCTOS'!$G18)) | M18: =IF(OR(tblStock[[#This Row],[SKU]]="",N(tblStock[[#This Row],[StockMax]])=0),"",MAX(0,tblStock[[#This Row],[StockActual]])/tblStock[[#This Row],[StockMax]]) | N18: =IF(tblStock[[#This Row],[SKU]]="","",IF(tblStock[[#This Row],[Activo]]="NO","INACTIVO",IF(tblStock[[#This Row],[StockActual]]<0,"INCONSISTENTE",IF(tblStock[[#This Row],[StockActual]]=0,"AGOTADO",IF(tblStock[[#This Row],[StockActual]]<=tblStock[[#This Row],[StockMin]],"CRÍTICO",IF(tblStock[[#This Row],[StockActual]]<=tblStock[[#This Row],[StockMin]]*(1+cfgMargenAlerta),"BAJO",IF(AND(tblStock[[#This Row],[StockMax]]>0,tblStock[[#This Row],[StockActual]]>tblStock[[#This Row],[StockMax]]),"SOBRESTOCK","ÓPTIMO"))))))) | O18: =IF($B18="","",N('05_PRODUCTOS'!$H18)) | P18: =IF(tblStock[[#This Row],[SKU]]="","",MAX(0,tblStock[[#This Row],[StockActual]])*tblStock[[#This Row],[CostoUnitario]]) | Q18: =IF(tblStock[[#This Row],[SKU]]="","",IFERROR(_xlfn.AGGREGATE(14,6,tblMovimientos[Fecha]/(tblMovimientos[SKU]=tblStock[[#This Row],[SKU]]),1),"")) | R18: =IF(OR(tblStock[[#This Row],[SKU]]="",tblStock[[#This Row],[UltimoMov]]=""),"",TODAY()-tblStock[[#This Row],[UltimoMov]])
B19: =IF('05_PRODUCTOS'!$B19="","",'05_PRODUCTOS'!$B19) | C19: =IF($B19="","",'05_PRODUCTOS'!$C19) | D19: =IF($B19="","",'05_PRODUCTOS'!$D19) | E19: =IF($B19="","",'05_PRODUCTOS'!$I19&"") | F19: =IF($B19="","",'05_PRODUCTOS'!$E19) | G19: =IF($B19="","",IF('05_PRODUCTOS'!$K19="NO","NO","SI")) | H19: =IF(tblStock[[#This Row],[SKU]]="","",SUMIFS(tblMovimientos[CantidadNeta],tblMovimientos[SKU],tblStock[[#This Row],[SKU]],tblMovimientos[FactorStock],1)) | I19: =IF(tblStock[[#This Row],[SKU]]="","",-SUMIFS(tblMovimientos[CantidadNeta],tblMovimientos[SKU],tblStock[[#This Row],[SKU]],tblMovimientos[FactorStock],-1)) | J19: =IF(tblStock[[#This Row],[SKU]]="","",SUMIFS(tblMovimientos[CantidadNeta],tblMovimientos[SKU],tblStock[[#This Row],[SKU]])) | K19: =IF($B19="","",N('05_PRODUCTOS'!$F19)) | L19: =IF($B19="","",N('05_PRODUCTOS'!$G19)) | M19: =IF(OR(tblStock[[#This Row],[SKU]]="",N(tblStock[[#This Row],[StockMax]])=0),"",MAX(0,tblStock[[#This Row],[StockActual]])/tblStock[[#This Row],[StockMax]]) | N19: =IF(tblStock[[#This Row],[SKU]]="","",IF(tblStock[[#This Row],[Activo]]="NO","INACTIVO",IF(tblStock[[#This Row],[StockActual]]<0,"INCONSISTENTE",IF(tblStock[[#This Row],[StockActual]]=0,"AGOTADO",IF(tblStock[[#This Row],[StockActual]]<=tblStock[[#This Row],[StockMin]],"CRÍTICO",IF(tblStock[[#This Row],[StockActual]]<=tblStock[[#This Row],[StockMin]]*(1+cfgMargenAlerta),"BAJO",IF(AND(tblStock[[#This Row],[StockMax]]>0,tblStock[[#This Row],[StockActual]]>tblStock[[#This Row],[StockMax]]),"SOBRESTOCK","ÓPTIMO"))))))) | O19: =IF($B19="","",N('05_PRODUCTOS'!$H19)) | P19: =IF(tblStock[[#This Row],[SKU]]="","",MAX(0,tblStock[[#This Row],[StockActual]])*tblStock[[#This Row],[CostoUnitario]]) | Q19: =IF(tblStock[[#This Row],[SKU]]="","",IFERROR(_xlfn.AGGREGATE(14,6,tblMovimientos[Fecha]/(tblMovimientos[SKU]=tblStock[[#This Row],[SKU]]),1),"")) | R19: =IF(OR(tblStock[[#This Row],[SKU]]="",tblStock[[#This Row],[UltimoMov]]=""),"",TODAY()-tblStock[[#This Row],[UltimoMov]])
... B507: =IF('05_PRODUCTOS'!$B507="","",'05_PRODUCTOS'!$B507) | C507: =IF($B507="","",'05_PRODUCTOS'!$C507) | D507: =IF($B507="","",'05_PRODUCTOS'!$D507) | E507: =IF($B507="","",'05_PRODUCTOS'!$I507&"") | F507: =IF($B507="","",'05_PRODUCTOS'!$E507) | G507: =IF($B507="","",IF('05_PRODUCTOS'!$K507="NO","NO","SI")) | H507: =IF(tblStock[[#This Row],[SKU]]="","",SUMIFS(tblMovimientos[CantidadNeta],tblMovimientos[SKU],tblStock[[#This Row],[SKU]],tblMovimientos[FactorStock],1)) | I507: =IF(tblStock[[#This Row],[SKU]]="","",-SUMIFS(tblMovimientos[CantidadNeta],tblMovimientos[SKU],tblStock[[#This Row],[SKU]],tblMovimientos[FactorStock],-1)) | J507: =IF(tblStock[[#This Row],[SKU]]="","",SUMIFS(tblMovimientos[CantidadNeta],tblMovimientos[SKU],tblStock[[#This Row],[SKU]])) | K507: =IF($B507="","",N('05_PRODUCTOS'!$F507)) | L507: =IF($B507="","",N('05_PRODUCTOS'!$G507)) | M507: =IF(OR(tblStock[[#This Row],[SKU]]="",N(tblStock[[#This Row],[StockMax]])=0),"",MAX(0,tblStock[[#This Row],[StockActual]])/tblStock[[#This Row],[StockMax]]) | N507: =IF(tblStock[[#This Row],[SKU]]="","",IF(tblStock[[#This Row],[Activo]]="NO","INACTIVO",IF(tblStock[[#This Row],[StockActual]]<0,"INCONSISTENTE",IF(tblStock[[#This Row],[StockActual]]=0,"AGOTADO",IF(tblStock[[#This Row],[StockActual]]<=tblStock[[#This Row],[StockMin]],"CRÍTICO",IF(tblStock[[#This Row],[StockActual]]<=tblStock[[#This Row],[StockMin]]*(1+cfgMargenAlerta),"BAJO",IF(AND(tblStock[[#This Row],[StockMax]]>0,tblStock[[#This Row],[StockActual]]>tblStock[[#This Row],[StockMax]]),"SOBRESTOCK","ÓPTIMO"))))))) | O507: =IF($B507="","",N('05_PRODUCTOS'!$H507)) | P507: =IF(tblStock[[#This Row],[SKU]]="","",MAX(0,tblStock[[#This Row],[StockActual]])*tblStock[[#This Row],[CostoUnitario]]) | Q507: =IF(tblStock[[#This Row],[SKU]]="","",IFERROR(_xlfn.AGGREGATE(14,6,tblMovimientos[Fecha]/(tblMovimientos[SKU]=tblStock[[#This Row],[SKU]]),1),"")) | R507: =IF(OR(tblStock[[#This Row],[SKU]]="",tblStock[[#This Row],[UltimoMov]]=""),"",TODAY()-tblStock[[#This Row],[UltimoMov]])

Sheet 16_ALERTAS
B2: Alertas de inventario
B3: Capa de lectura · Productos que requieren acción, ordenados por prioridad (se actualiza sola)
B6: ƒx | C6: ƒx | D6: ƒx | E6: ƒx | F6: ƒx | G6: ƒx | H6: ƒx | I6: ƒx | J6: ƒx | K6: ƒx | L6: ƒx | M6: ƒx | N6: ƒx | O6: ƒx
B7: # | C7: Nivel | D7: SKU | E7: Producto | F7: Categoría | G7: Proveedor | H7: Stock | I7: Mínimo | J7: Máximo | K7: Unidad | L7: Faltante | M7: SugeridoPedir | N7: AcciónSugerida | O7: UltimoMov
B8: =IF('91_KPIS'!$Q8="","",'91_KPIS'!$O8) | C8: =IF($B8="","",INDEX(tblStock[Estado],'91_KPIS'!$Q8)) | D8: =IF($B8="","",INDEX(tblStock[SKU],'91_KPIS'!$Q8)) | E8: =IF($B8="","",INDEX(tblStock[Producto],'91_KPIS'!$Q8)) | F8: =IF($B8="","",INDEX(tblStock[Categoría],'91_KPIS'!$Q8)) | G8: =IF($B8="","",INDEX(tblStock[Proveedor],'91_KPIS'!$Q8)&"") | H8: =IF($B8="","",INDEX(tblStock[StockActual],'91_KPIS'!$Q8)) | I8: =IF($B8="","",INDEX(tblStock[StockMin],'91_KPIS'!$Q8)) | J8: =IF($B8="","",INDEX(tblStock[StockMax],'91_KPIS'!$Q8)) | K8: =IF($B8="","",INDEX(tblStock[Unidad],'91_KPIS'!$Q8)) | L8: =IF($B8="","",MAX(0,$I8-$H8)) | M8: =IF($B8="","",IF(OR($C8="SOBRESTOCK",$C8="INCONSISTENTE"),0,MAX(0,IF($J8>0,$J8,2*$I8)-MAX(0,$H8)))) | N8: =IF($B8="","",IFERROR(INDEX(tblEstados[Acción],MATCH($C8,tblEstados[Estado],0)),"")) | O8: =IF($B8="","",INDEX(tblStock[UltimoMov],'91_KPIS'!$Q8))
B9: =IF('91_KPIS'!$Q9="","",'91_KPIS'!$O9) | C9: =IF($B9="","",INDEX(tblStock[Estado],'91_KPIS'!$Q9)) | D9: =IF($B9="","",INDEX(tblStock[SKU],'91_KPIS'!$Q9)) | E9: =IF($B9="","",INDEX(tblStock[Producto],'91_KPIS'!$Q9)) | F9: =IF($B9="","",INDEX(tblStock[Categoría],'91_KPIS'!$Q9)) | G9: =IF($B9="","",INDEX(tblStock[Proveedor],'91_KPIS'!$Q9)&"") | H9: =IF($B9="","",INDEX(tblStock[StockActual],'91_KPIS'!$Q9)) | I9: =IF($B9="","",INDEX(tblStock[StockMin],'91_KPIS'!$Q9)) | J9: =IF($B9="","",INDEX(tblStock[StockMax],'91_KPIS'!$Q9)) | K9: =IF($B9="","",INDEX(tblStock[Unidad],'91_KPIS'!$Q9)) | L9: =IF($B9="","",MAX(0,$I9-$H9)) | M9: =IF($B9="","",IF(OR($C9="SOBRESTOCK",$C9="INCONSISTENTE"),0,MAX(0,IF($J9>0,$J9,2*$I9)-MAX(0,$H9)))) | N9: =IF($B9="","",IFERROR(INDEX(tblEstados[Acción],MATCH($C9,tblEstados[Estado],0)),"")) | O9: =IF($B9="","",INDEX(tblStock[UltimoMov],'91_KPIS'!$Q9))
B10: =IF('91_KPIS'!$Q10="","",'91_KPIS'!$O10) | C10: =IF($B10="","",INDEX(tblStock[Estado],'91_KPIS'!$Q10)) | D10: =IF($B10="","",INDEX(tblStock[SKU],'91_KPIS'!$Q10)) | E10: =IF($B10="","",INDEX(tblStock[Producto],'91_KPIS'!$Q10)) | F10: =IF($B10="","",INDEX(tblStock[Categoría],'91_KPIS'!$Q10)) | G10: =IF($B10="","",INDEX(tblStock[Proveedor],'91_KPIS'!$Q10)&"") | H10: =IF($B10="","",INDEX(tblStock[StockActual],'91_KPIS'!$Q10)) | I10: =IF($B10="","",INDEX(tblStock[StockMin],'91_KPIS'!$Q10)) | J10: =IF($B10="","",INDEX(tblStock[StockMax],'91_KPIS'!$Q10)) | K10: =IF($B10="","",INDEX(tblStock[Unidad],'91_KPIS'!$Q10)) | L10: =IF($B10="","",MAX(0,$I10-$H10)) | M10: =IF($B10="","",IF(OR($C10="SOBRESTOCK",$C10="INCONSISTENTE"),0,MAX(0,IF($J10>0,$J10,2*$I10)-MAX(0,$H10)))) | N10: =IF($B10="","",IFERROR(INDEX(tblEstados[Acción],MATCH($C10,tblEstados[Estado],0)),"")) | O10: =IF($B10="","",INDEX(tblStock[UltimoMov],'91_KPIS'!$Q10))
B11: =IF('91_KPIS'!$Q11="","",'91_KPIS'!$O11) | C11: =IF($B11="","",INDEX(tblStock[Estado],'91_KPIS'!$Q11)) | D11: =IF($B11="","",INDEX(tblStock[SKU],'91_KPIS'!$Q11)) | E11: =IF($B11="","",INDEX(tblStock[Producto],'91_KPIS'!$Q11)) | F11: =IF($B11="","",INDEX(tblStock[Categoría],'91_KPIS'!$Q11)) | G11: =IF($B11="","",INDEX(tblStock[Proveedor],'91_KPIS'!$Q11)&"") | H11: =IF($B11="","",INDEX(tblStock[StockActual],'91_KPIS'!$Q11)) | I11: =IF($B11="","",INDEX(tblStock[StockMin],'91_KPIS'!$Q11)) | J11: =IF($B11="","",INDEX(tblStock[StockMax],'91_KPIS'!$Q11)) | K11: =IF($B11="","",INDEX(tblStock[Unidad],'91_KPIS'!$Q11)) | L11: =IF($B11="","",MAX(0,$I11-$H11)) | M11: =IF($B11="","",IF(OR($C11="SOBRESTOCK",$C11="INCONSISTENTE"),0,MAX(0,IF($J11>0,$J11,2*$I11)-MAX(0,$H11)))) | N11: =IF($B11="","",IFERROR(INDEX(tblEstados[Acción],MATCH($C11,tblEstados[Estado],0)),"")) | O11: =IF($B11="","",INDEX(tblStock[UltimoMov],'91_KPIS'!$Q11))
B12: =IF('91_KPIS'!$Q12="","",'91_KPIS'!$O12) | C12: =IF($B12="","",INDEX(tblStock[Estado],'91_KPIS'!$Q12)) | D12: =IF($B12="","",INDEX(tblStock[SKU],'91_KPIS'!$Q12)) | E12: =IF($B12="","",INDEX(tblStock[Producto],'91_KPIS'!$Q12)) | F12: =IF($B12="","",INDEX(tblStock[Categoría],'91_KPIS'!$Q12)) | G12: =IF($B12="","",INDEX(tblStock[Proveedor],'91_KPIS'!$Q12)&"") | H12: =IF($B12="","",INDEX(tblStock[StockActual],'91_KPIS'!$Q12)) | I12: =IF($B12="","",INDEX(tblStock[StockMin],'91_KPIS'!$Q12)) | J12: =IF($B12="","",INDEX(tblStock[StockMax],'91_KPIS'!$Q12)) | K12: =IF($B12="","",INDEX(tblStock[Unidad],'91_KPIS'!$Q12)) | L12: =IF($B12="","",MAX(0,$I12-$H12)) | M12: =IF($B12="","",IF(OR($C12="SOBRESTOCK",$C12="INCONSISTENTE"),0,MAX(0,IF($J12>0,$J12,2*$I12)-MAX(0,$H12)))) | N12: =IF($B12="","",IFERROR(INDEX(tblEstados[Acción],MATCH($C12,tblEstados[Estado],0)),"")) | O12: =IF($B12="","",INDEX(tblStock[UltimoMov],'91_KPIS'!$Q12))
B13: =IF('91_KPIS'!$Q13="","",'91_KPIS'!$O13) | C13: =IF($B13="","",INDEX(tblStock[Estado],'91_KPIS'!$Q13)) | D13: =IF($B13="","",INDEX(tblStock[SKU],'91_KPIS'!$Q13)) | E13: =IF($B13="","",INDEX(tblStock[Producto],'91_KPIS'!$Q13)) | F13: =IF($B13="","",INDEX(tblStock[Categoría],'91_KPIS'!$Q13)) | G13: =IF($B13="","",INDEX(tblStock[Proveedor],'91_KPIS'!$Q13)&"") | H13: =IF($B13="","",INDEX(tblStock[StockActual],'91_KPIS'!$Q13)) | I13: =IF($B13="","",INDEX(tblStock[StockMin],'91_KPIS'!$Q13)) | J13: =IF($B13="","",INDEX(tblStock[StockMax],'91_KPIS'!$Q13)) | K13: =IF($B13="","",INDEX(tblStock[Unidad],'91_KPIS'!$Q13)) | L13: =IF($B13="","",MAX(0,$I13-$H13)) | M13: =IF($B13="","",IF(OR($C13="SOBRESTOCK",$C13="INCONSISTENTE"),0,MAX(0,IF($J13>0,$J13,2*$I13)-MAX(0,$H13)))) | N13: =IF($B13="","",IFERROR(INDEX(tblEstados[Acción],MATCH($C13,tblEstados[Estado],0)),"")) | O13: =IF($B13="","",INDEX(tblStock[UltimoMov],'91_KPIS'!$Q13))
B14: =IF('91_KPIS'!$Q14="","",'91_KPIS'!$O14) | C14: =IF($B14="","",INDEX(tblStock[Estado],'91_KPIS'!$Q14)) | D14: =IF($B14="","",INDEX(tblStock[SKU],'91_KPIS'!$Q14)) | E14: =IF($B14="","",INDEX(tblStock[Producto],'91_KPIS'!$Q14)) | F14: =IF($B14="","",INDEX(tblStock[Categoría],'91_KPIS'!$Q14)) | G14: =IF($B14="","",INDEX(tblStock[Proveedor],'91_KPIS'!$Q14)&"") | H14: =IF($B14="","",INDEX(tblStock[StockActual],'91_KPIS'!$Q14)) | I14: =IF($B14="","",INDEX(tblStock[StockMin],'91_KPIS'!$Q14)) | J14: =IF($B14="","",INDEX(tblStock[StockMax],'91_KPIS'!$Q14)) | K14: =IF($B14="","",INDEX(tblStock[Unidad],'91_KPIS'!$Q14)) | L14: =IF($B14="","",MAX(0,$I14-$H14)) | M14: =IF($B14="","",IF(OR($C14="SOBRESTOCK",$C14="INCONSISTENTE"),0,MAX(0,IF($J14>0,$J14,2*$I14)-MAX(0,$H14)))) | N14: =IF($B14="","",IFERROR(INDEX(tblEstados[Acción],MATCH($C14,tblEstados[Estado],0)),"")) | O14: =IF($B14="","",INDEX(tblStock[UltimoMov],'91_KPIS'!$Q14))
B15: =IF('91_KPIS'!$Q15="","",'91_KPIS'!$O15) | C15: =IF($B15="","",INDEX(tblStock[Estado],'91_KPIS'!$Q15)) | D15: =IF($B15="","",INDEX(tblStock[SKU],'91_KPIS'!$Q15)) | E15: =IF($B15="","",INDEX(tblStock[Producto],'91_KPIS'!$Q15)) | F15: =IF($B15="","",INDEX(tblStock[Categoría],'91_KPIS'!$Q15)) | G15: =IF($B15="","",INDEX(tblStock[Proveedor],'91_KPIS'!$Q15)&"") | H15: =IF($B15="","",INDEX(tblStock[StockActual],'91_KPIS'!$Q15)) | I15: =IF($B15="","",INDEX(tblStock[StockMin],'91_KPIS'!$Q15)) | J15: =IF($B15="","",INDEX(tblStock[StockMax],'91_KPIS'!$Q15)) | K15: =IF($B15="","",INDEX(tblStock[Unidad],'91_KPIS'!$Q15)) | L15: =IF($B15="","",MAX(0,$I15-$H15)) | M15: =IF($B15="","",IF(OR($C15="SOBRESTOCK",$C15="INCONSISTENTE"),0,MAX(0,IF($J15>0,$J15,2*$I15)-MAX(0,$H15)))) | N15: =IF($B15="","",IFERROR(INDEX(tblEstados[Acción],MATCH($C15,tblEstados[Estado],0)),"")) | O15: =IF($B15="","",INDEX(tblStock[UltimoMov],'91_KPIS'!$Q15))
B16: =IF('91_KPIS'!$Q16="","",'91_KPIS'!$O16) | C16: =IF($B16="","",INDEX(tblStock[Estado],'91_KPIS'!$Q16)) | D16: =IF($B16="","",INDEX(tblStock[SKU],'91_KPIS'!$Q16)) | E16: =IF($B16="","",INDEX(tblStock[Producto],'91_KPIS'!$Q16)) | F16: =IF($B16="","",INDEX(tblStock[Categoría],'91_KPIS'!$Q16)) | G16: =IF($B16="","",INDEX(tblStock[Proveedor],'91_KPIS'!$Q16)&"") | H16: =IF($B16="","",INDEX(tblStock[StockActual],'91_KPIS'!$Q16)) | I16: =IF($B16="","",INDEX(tblStock[StockMin],'91_KPIS'!$Q16)) | J16: =IF($B16="","",INDEX(tblStock[StockMax],'91_KPIS'!$Q16)) | K16: =IF($B16="","",INDEX(tblStock[Unidad],'91_KPIS'!$Q16)) | L16: =IF($B16="","",MAX(0,$I16-$H16)) | M16: =IF($B16="","",IF(OR($C16="SOBRESTOCK",$C16="INCONSISTENTE"),0,MAX(0,IF($J16>0,$J16,2*$I16)-MAX(0,$H16)))) | N16: =IF($B16="","",IFERROR(INDEX(tblEstados[Acción],MATCH($C16,tblEstados[Estado],0)),"")) | O16: =IF($B16="","",INDEX(tblStock[UltimoMov],'91_KPIS'!$Q16))
B17: =IF('91_KPIS'!$Q17="","",'91_KPIS'!$O17) | C17: =IF($B17="","",INDEX(tblStock[Estado],'91_KPIS'!$Q17)) | D17: =IF($B17="","",INDEX(tblStock[SKU],'91_KPIS'!$Q17)) | E17: =IF($B17="","",INDEX(tblStock[Producto],'91_KPIS'!$Q17)) | F17: =IF($B17="","",INDEX(tblStock[Categoría],'91_KPIS'!$Q17)) | G17: =IF($B17="","",INDEX(tblStock[Proveedor],'91_KPIS'!$Q17)&"") | H17: =IF($B17="","",INDEX(tblStock[StockActual],'91_KPIS'!$Q17)) | I17: =IF($B17="","",INDEX(tblStock[StockMin],'91_KPIS'!$Q17)) | J17: =IF($B17="","",INDEX(tblStock[StockMax],'91_KPIS'!$Q17)) | K17: =IF($B17="","",INDEX(tblStock[Unidad],'91_KPIS'!$Q17)) | L17: =IF($B17="","",MAX(0,$I17-$H17)) | M17: =IF($B17="","",IF(OR($C17="SOBRESTOCK",$C17="INCONSISTENTE"),0,MAX(0,IF($J17>0,$J17,2*$I17)-MAX(0,$H17)))) | N17: =IF($B17="","",IFERROR(INDEX(tblEstados[Acción],MATCH($C17,tblEstados[Estado],0)),"")) | O17: =IF($B17="","",INDEX(tblStock[UltimoMov],'91_KPIS'!$Q17))
B18: =IF('91_KPIS'!$Q18="","",'91_KPIS'!$O18) | C18: =IF($B18="","",INDEX(tblStock[Estado],'91_KPIS'!$Q18)) | D18: =IF($B18="","",INDEX(tblStock[SKU],'91_KPIS'!$Q18)) | E18: =IF($B18="","",INDEX(tblStock[Producto],'91_KPIS'!$Q18)) | F18: =IF($B18="","",INDEX(tblStock[Categoría],'91_KPIS'!$Q18)) | G18: =IF($B18="","",INDEX(tblStock[Proveedor],'91_KPIS'!$Q18)&"") | H18: =IF($B18="","",INDEX(tblStock[StockActual],'91_KPIS'!$Q18)) | I18: =IF($B18="","",INDEX(tblStock[StockMin],'91_KPIS'!$Q18)) | J18: =IF($B18="","",INDEX(tblStock[StockMax],'91_KPIS'!$Q18)) | K18: =IF($B18="","",INDEX(tblStock[Unidad],'91_KPIS'!$Q18)) | L18: =IF($B18="","",MAX(0,$I18-$H18)) | M18: =IF($B18="","",IF(OR($C18="SOBRESTOCK",$C18="INCONSISTENTE"),0,MAX(0,IF($J18>0,$J18,2*$I18)-MAX(0,$H18)))) | N18: =IF($B18="","",IFERROR(INDEX(tblEstados[Acción],MATCH($C18,tblEstados[Estado],0)),"")) | O18: =IF($B18="","",INDEX(tblStock[UltimoMov],'91_KPIS'!$Q18))
B19: =IF('91_KPIS'!$Q19="","",'91_KPIS'!$O19) | C19: =IF($B19="","",INDEX(tblStock[Estado],'91_KPIS'!$Q19)) | D19: =IF($B19="","",INDEX(tblStock[SKU],'91_KPIS'!$Q19)) | E19: =IF($B19="","",INDEX(tblStock[Producto],'91_KPIS'!$Q19)) | F19: =IF($B19="","",INDEX(tblStock[Categoría],'91_KPIS'!$Q19)) | G19: =IF($B19="","",INDEX(tblStock[Proveedor],'91_KPIS'!$Q19)&"") | H19: =IF($B19="","",INDEX(tblStock[StockActual],'91_KPIS'!$Q19)) | I19: =IF($B19="","",INDEX(tblStock[StockMin],'91_KPIS'!$Q19)) | J19: =IF($B19="","",INDEX(tblStock[StockMax],'91_KPIS'!$Q19)) | K19: =IF($B19="","",INDEX(tblStock[Unidad],'91_KPIS'!$Q19)) | L19: =IF($B19="","",MAX(0,$I19-$H19)) | M19: =IF($B19="","",IF(OR($C19="SOBRESTOCK",$C19="INCONSISTENTE"),0,MAX(0,IF($J19>0,$J19,2*$I19)-MAX(0,$H19)))) | N19: =IF($B19="","",IFERROR(INDEX(tblEstados[Acción],MATCH($C19,tblEstados[Estado],0)),"")) | O19: =IF($B19="","",INDEX(tblStock[UltimoMov],'91_KPIS'!$Q19))
... B507: =IF('91_KPIS'!$Q507="","",'91_KPIS'!$O507) | C507: =IF($B507="","",INDEX(tblStock[Estado],'91_KPIS'!$Q507)) | D507: =IF($B507="","",INDEX(tblStock[SKU],'91_KPIS'!$Q507)) | E507: =IF($B507="","",INDEX(tblStock[Producto],'91_KPIS'!$Q507)) | F507: =IF($B507="","",INDEX(tblStock[Categoría],'91_KPIS'!$Q507)) | G507: =IF($B507="","",INDEX(tblStock[Proveedor],'91_KPIS'!$Q507)&"") | H507: =IF($B507="","",INDEX(tblStock[StockActual],'91_KPIS'!$Q507)) | I507: =IF($B507="","",INDEX(tblStock[StockMin],'91_KPIS'!$Q507)) | J507: =IF($B507="","",INDEX(tblStock[StockMax],'91_KPIS'!$Q507)) | K507: =IF($B507="","",INDEX(tblStock[Unidad],'91_KPIS'!$Q507)) | L507: =IF($B507="","",MAX(0,$I507-$H507)) | M507: =IF($B507="","",IF(OR($C507="SOBRESTOCK",$C507="INCONSISTENTE"),0,MAX(0,IF($J507>0,$J507,2*$I507)-MAX(0,$H507)))) | N507: =IF($B507="","",IFERROR(INDEX(tblEstados[Acción],MATCH($C507,tblEstados[Estado],0)),"")) | O507: =IF($B507="","",INDEX(tblStock[UltimoMov],'91_KPIS'!$Q507))

Sheet 17_KARDEX
B2: Consulta de producto
B3: Capa de lectura · Busque un producto y vea su ficha, su evolución y su historial (kardex)
B7: CATEGORÍA (opcional) | E7: BUSCAR (nombre o SKU) | H7: PRODUCTO
H9: =txtKardexCoinciden -> 0 producto(s) en el catálogo · use Buscar para filtrar
B11: =IF(kxExiste,kxProducto,"Elija un producto para ver su ficha") -> Elija un producto para ver su ficha
B12: =txtKardexMeta
B13: STOCK ACTUAL | D13: ESTADO | F13: VALOR
B14: =IF(kxExiste,INDEX(tblStock[StockActual],kxFila),"—") -> — | D14: =IF(kxExiste,INDEX(tblStock[Estado],kxFila),"") | F14: =IF(kxExiste,INDEX(tblStock[ValorInventario],kxFila),"")
B16: =IF(kxExiste,"MÍN "&INDEX(tblStock[StockMin],kxFila),"") | C16: =IF(kxExiste,"MÁX "&INDEX(tblStock[StockMax],kxFila),"") | D16: ÚLTIMO MOVIMIENTO | F16: DÍAS SIN MOVIMIENTO
B17: =IF(kxExiste,INDEX(tblStock[Unidad],kxFila),"") | D17: =IF(kxExiste,INDEX(tblStock[UltimoMov],kxFila),"") | F17: =IF(kxExiste,INDEX(tblStock[DiasSinMov],kxFila),"")
B18: =txtKardexTotales
B20: ▍ HISTORIAL DE MOVIMIENTOS (del más reciente al más antiguo) | J20: =txtKardexMostrando
B21: ID | C21: Fecha | D21: Tipo | E21: Entrada (+) | F21: Salida (-) | G21: Saldo | H21: Documento | I21: Responsable | K21: Observaciones
B22: =IF(kxSKU="","",IFERROR(_xlfn.AGGREGATE(14,6,tblMovimientos[ID]/(tblMovimientos[SKU]=kxSKU),1),"")) | C22: =IF($B22="","",INDEX(tblMovimientos[Fecha],$B22)) | D22: =IF($B22="","",INDEX(tblMovimientos[Tipo],$B22)) | E22: =IF($B22="","",IF(INDEX(tblMovimientos[CantidadNeta],$B22)>0,INDEX(tblMovimientos[CantidadNeta],$B22),"")) | F22: =IF($B22="","",IF(INDEX(tblMovimientos[CantidadNeta],$B22)<0,-INDEX(tblMovimientos[CantidadNeta],$B22),"")) | G22: =IF($B22="","",INDEX(tblMovimientos[Saldo],$B22)) | H22: =IF($B22="","",INDEX(tblMovimientos[Documento],$B22)&"") | I22: =IF($B22="","",INDEX(tblMovimientos[Responsable],$B22)&"") | K22: =IF($B22="","",INDEX(tblMovimientos[Observaciones],$B22)&"")
B23: =IF(kxSKU="","",IFERROR(_xlfn.AGGREGATE(14,6,tblMovimientos[ID]/(tblMovimientos[SKU]=kxSKU),2),"")) | C23: =IF($B23="","",INDEX(tblMovimientos[Fecha],$B23)) | D23: =IF($B23="","",INDEX(tblMovimientos[Tipo],$B23)) | E23: =IF($B23="","",IF(INDEX(tblMovimientos[CantidadNeta],$B23)>0,INDEX(tblMovimientos[CantidadNeta],$B23),"")) | F23: =IF($B23="","",IF(INDEX(tblMovimientos[CantidadNeta],$B23)<0,-INDEX(tblMovimientos[CantidadNeta],$B23),"")) | G23: =IF($B23="","",INDEX(tblMovimientos[Saldo],$B23)) | H23: =IF($B23="","",INDEX(tblMovimientos[Documento],$B23)&"") | I23: =IF($B23="","",INDEX(tblMovimientos[Responsable],$B23)&"") | K23: =IF($B23="","",INDEX(tblMovimientos[Observaciones],$B23)&"")
B24: =IF(kxSKU="","",IFERROR(_xlfn.AGGREGATE(14,6,tblMovimientos[ID]/(tblMovimientos[SKU]=kxSKU),3),"")) | C24: =IF($B24="","",INDEX(tblMovimientos[Fecha],$B24)) | D24: =IF($B24="","",INDEX(tblMovimientos[Tipo],$B24)) | E24: =IF($B24="","",IF(INDEX(tblMovimientos[CantidadNeta],$B24)>0,INDEX(tblMovimientos[CantidadNeta],$B24),"")) | F24: =IF($B24="","",IF(INDEX(tblMovimientos[CantidadNeta],$B24)<0,-INDEX(tblMovimientos[CantidadNeta],$B24),"")) | G24: =IF($B24="","",INDEX(tblMovimientos[Saldo],$B24)) | H24: =IF($B24="","",INDEX(tblMovimientos[Documento],$B24)&"") | I24: =IF($B24="","",INDEX(tblMovimientos[Responsable],$B24)&"") | K24: =IF($B24="","",INDEX(tblMovimientos[Observaciones],$B24)&"")
B25: =IF(kxSKU="","",IFERROR(_xlfn.AGGREGATE(14,6,tblMovimientos[ID]/(tblMovimientos[SKU]=kxSKU),4),"")) | C25: =IF($B25="","",INDEX(tblMovimientos[Fecha],$B25)) | D25: =IF($B25="","",INDEX(tblMovimientos[Tipo],$B25)) | E25: =IF($B25="","",IF(INDEX(tblMovimientos[CantidadNeta],$B25)>0,INDEX(tblMovimientos[CantidadNeta],$B25),"")) | F25: =IF($B25="","",IF(INDEX(tblMovimientos[CantidadNeta],$B25)<0,-INDEX(tblMovimientos[CantidadNeta],$B25),"")) | G25: =IF($B25="","",INDEX(tblMovimientos[Saldo],$B25)) | H25: =IF($B25="","",INDEX(tblMovimientos[Documento],$B25)&"") | I25: =IF($B25="","",INDEX(tblMovimientos[Responsable],$B25)&"") | K25: =IF($B25="","",INDEX(tblMovimientos[Observaciones],$B25)&"")
B26: =IF(kxSKU="","",IFERROR(_xlfn.AGGREGATE(14,6,tblMovimientos[ID]/(tblMovimientos[SKU]=kxSKU),5),"")) | C26: =IF($B26="","",INDEX(tblMovimientos[Fecha],$B26)) | D26: =IF($B26="","",INDEX(tblMovimientos[Tipo],$B26)) | E26: =IF($B26="","",IF(INDEX(tblMovimientos[CantidadNeta],$B26)>0,INDEX(tblMovimientos[CantidadNeta],$B26),"")) | F26: =IF($B26="","",IF(INDEX(tblMovimientos[CantidadNeta],$B26)<0,-INDEX(tblMovimientos[CantidadNeta],$B26),"")) | G26: =IF($B26="","",INDEX(tblMovimientos[Saldo],$B26)) | H26: =IF($B26="","",INDEX(tblMovimientos[Documento],$B26)&"") | I26: =IF($B26="","",INDEX(tblMovimientos[Responsable],$B26)&"") | K26: =IF($B26="","",INDEX(tblMovimientos[Observaciones],$B26)&"")
B27: =IF(kxSKU="","",IFERROR(_xlfn.AGGREGATE(14,6,tblMovimientos[ID]/(tblMovimientos[SKU]=kxSKU),6),"")) | C27: =IF($B27="","",INDEX(tblMovimientos[Fecha],$B27)) | D27: =IF($B27="","",INDEX(tblMovimientos[Tipo],$B27)) | E27: =IF($B27="","",IF(INDEX(tblMovimientos[CantidadNeta],$B27)>0,INDEX(tblMovimientos[CantidadNeta],$B27),"")) | F27: =IF($B27="","",IF(INDEX(tblMovimientos[CantidadNeta],$B27)<0,-INDEX(tblMovimientos[CantidadNeta],$B27),"")) | G27: =IF($B27="","",INDEX(tblMovimientos[Saldo],$B27)) | H27: =IF($B27="","",INDEX(tblMovimientos[Documento],$B27)&"") | I27: =IF($B27="","",INDEX(tblMovimientos[Responsable],$B27)&"") | K27: =IF($B27="","",INDEX(tblMovimientos[Observaciones],$B27)&"")
B28: =IF(kxSKU="","",IFERROR(_xlfn.AGGREGATE(14,6,tblMovimientos[ID]/(tblMovimientos[SKU]=kxSKU),7),"")) | C28: =IF($B28="","",INDEX(tblMovimientos[Fecha],$B28)) | D28: =IF($B28="","",INDEX(tblMovimientos[Tipo],$B28)) | E28: =IF($B28="","",IF(INDEX(tblMovimientos[CantidadNeta],$B28)>0,INDEX(tblMovimientos[CantidadNeta],$B28),"")) | F28: =IF($B28="","",IF(INDEX(tblMovimientos[CantidadNeta],$B28)<0,-INDEX(tblMovimientos[CantidadNeta],$B28),"")) | G28: =IF($B28="","",INDEX(tblMovimientos[Saldo],$B28)) | H28: =IF($B28="","",INDEX(tblMovimientos[Documento],$B28)&"") | I28: =IF($B28="","",INDEX(tblMovimientos[Responsable],$B28)&"") | K28: =IF($B28="","",INDEX(tblMovimientos[Observaciones],$B28)&"")
B29: =IF(kxSKU="","",IFERROR(_xlfn.AGGREGATE(14,6,tblMovimientos[ID]/(tblMovimientos[SKU]=kxSKU),8),"")) | C29: =IF($B29="","",INDEX(tblMovimientos[Fecha],$B29)) | D29: =IF($B29="","",INDEX(tblMovimientos[Tipo],$B29)) | E29: =IF($B29="","",IF(INDEX(tblMovimientos[CantidadNeta],$B29)>0,INDEX(tblMovimientos[CantidadNeta],$B29),"")) | F29: =IF($B29="","",IF(INDEX(tblMovimientos[CantidadNeta],$B29)<0,-INDEX(tblMovimientos[CantidadNeta],$B29),"")) | G29: =IF($B29="","",INDEX(tblMovimientos[Saldo],$B29)) | H29: =IF($B29="","",INDEX(tblMovimientos[Documento],$B29)&"") | I29: =IF($B29="","",INDEX(tblMovimientos[Responsable],$B29)&"") | K29: =IF($B29="","",INDEX(tblMovimientos[Observaciones],$B29)&"")
B30: =IF(kxSKU="","",IFERROR(_xlfn.AGGREGATE(14,6,tblMovimientos[ID]/(tblMovimientos[SKU]=kxSKU),9),"")) | C30: =IF($B30="","",INDEX(tblMovimientos[Fecha],$B30)) | D30: =IF($B30="","",INDEX(tblMovimientos[Tipo],$B30)) | E30: =IF($B30="","",IF(INDEX(tblMovimientos[CantidadNeta],$B30)>0,INDEX(tblMovimientos[CantidadNeta],$B30),"")) | F30: =IF($B30="","",IF(INDEX(tblMovimientos[CantidadNeta],$B30)<0,-INDEX(tblMovimientos[CantidadNeta],$B30),"")) | G30: =IF($B30="","",INDEX(tblMovimientos[Saldo],$B30)) | H30: =IF($B30="","",INDEX(tblMovimientos[Documento],$B30)&"") | I30: =IF($B30="","",INDEX(tblMovimientos[Responsable],$B30)&"") | K30: =IF($B30="","",INDEX(tblMovimientos[Observaciones],$B30)&"")
B31: =IF(kxSKU="","",IFERROR(_xlfn.AGGREGATE(14,6,tblMovimientos[ID]/(tblMovimientos[SKU]=kxSKU),10),"")) | C31: =IF($B31="","",INDEX(tblMovimientos[Fecha],$B31)) | D31: =IF($B31="","",INDEX(tblMovimientos[Tipo],$B31)) | E31: =IF($B31="","",IF(INDEX(tblMovimientos[CantidadNeta],$B31)>0,INDEX(tblMovimientos[CantidadNeta],$B31),"")) | F31: =IF($B31="","",IF(INDEX(tblMovimientos[CantidadNeta],$B31)<0,-INDEX(tblMovimientos[CantidadNeta],$B31),"")) | G31: =IF($B31="","",INDEX(tblMovimientos[Saldo],$B31)) | H31: =IF($B31="","",INDEX(tblMovimientos[Documento],$B31)&"") | I31: =IF($B31="","",INDEX(tblMovimientos[Responsable],$B31)&"") | K31: =IF($B31="","",INDEX(tblMovimientos[Observaciones],$B31)&"")
B32: =IF(kxSKU="","",IFERROR(_xlfn.AGGREGATE(14,6,tblMovimientos[ID]/(tblMovimientos[SKU]=kxSKU),11),"")) | C32: =IF($B32="","",INDEX(tblMovimientos[Fecha],$B32)) | D32: =IF($B32="","",INDEX(tblMovimientos[Tipo],$B32)) | E32: =IF($B32="","",IF(INDEX(tblMovimientos[CantidadNeta],$B32)>0,INDEX(tblMovimientos[CantidadNeta],$B32),"")) | F32: =IF($B32="","",IF(INDEX(tblMovimientos[CantidadNeta],$B32)<0,-INDEX(tblMovimientos[CantidadNeta],$B32),"")) | G32: =IF($B32="","",INDEX(tblMovimientos[Saldo],$B32)) | H32: =IF($B32="","",INDEX(tblMovimientos[Documento],$B32)&"") | I32: =IF($B32="","",INDEX(tblMovimientos[Responsable],$B32)&"") | K32: =IF($B32="","",INDEX(tblMovimientos[Observaciones],$B32)&"")
B33: =IF(kxSKU="","",IFERROR(_xlfn.AGGREGATE(14,6,tblMovimientos[ID]/(tblMovimientos[SKU]=kxSKU),12),"")) | C33: =IF($B33="","",INDEX(tblMovimientos[Fecha],$B33)) | D33: =IF($B33="","",INDEX(tblMovimientos[Tipo],$B33)) | E33: =IF($B33="","",IF(INDEX(tblMovimientos[CantidadNeta],$B33)>0,INDEX(tblMovimientos[CantidadNeta],$B33),"")) | F33: =IF($B33="","",IF(INDEX(tblMovimientos[CantidadNeta],$B33)<0,-INDEX(tblMovimientos[CantidadNeta],$B33),"")) | G33: =IF($B33="","",INDEX(tblMovimientos[Saldo],$B33)) | H33: =IF($B33="","",INDEX(tblMovimientos[Documento],$B33)&"") | I33: =IF($B33="","",INDEX(tblMovimientos[Responsable],$B33)&"") | K33: =IF($B33="","",INDEX(tblMovimientos[Observaciones],$B33)&"")
B34: =IF(kxSKU="","",IFERROR(_xlfn.AGGREGATE(14,6,tblMovimientos[ID]/(tblMovimientos[SKU]=kxSKU),13),"")) | C34: =IF($B34="","",INDEX(tblMovimientos[Fecha],$B34)) | D34: =IF($B34="","",INDEX(tblMovimientos[Tipo],$B34)) | E34: =IF($B34="","",IF(INDEX(tblMovimientos[CantidadNeta],$B34)>0,INDEX(tblMovimientos[CantidadNeta],$B34),"")) | F34: =IF($B34="","",IF(INDEX(tblMovimientos[CantidadNeta],$B34)<0,-INDEX(tblMovimientos[CantidadNeta],$B34),"")) | G34: =IF($B34="","",INDEX(tblMovimientos[Saldo],$B34)) | H34: =IF($B34="","",INDEX(tblMovimientos[Documento],$B34)&"") | I34: =IF($B34="","",INDEX(tblMovimientos[Responsable],$B34)&"") | K34: =IF($B34="","",INDEX(tblMovimientos[Observaciones],$B34)&"")
B35: =IF(kxSKU="","",IFERROR(_xlfn.AGGREGATE(14,6,tblMovimientos[ID]/(tblMovimientos[SKU]=kxSKU),14),"")) | C35: =IF($B35="","",INDEX(tblMovimientos[Fecha],$B35)) | D35: =IF($B35="","",INDEX(tblMovimientos[Tipo],$B35)) | E35: =IF($B35="","",IF(INDEX(tblMovimientos[CantidadNeta],$B35)>0,INDEX(tblMovimientos[CantidadNeta],$B35),"")) | F35: =IF($B35="","",IF(INDEX(tblMovimientos[CantidadNeta],$B35)<0,-INDEX(tblMovimientos[CantidadNeta],$B35),"")) | G35: =IF($B35="","",INDEX(tblMovimientos[Saldo],$B35)) | H35: =IF($B35="","",INDEX(tblMovimientos[Documento],$B35)&"") | I35: =IF($B35="","",INDEX(tblMovimientos[Responsable],$B35)&"") | K35: =IF($B35="","",INDEX(tblMovimientos[Observaciones],$B35)&"")
B36: =IF(kxSKU="","",IFERROR(_xlfn.AGGREGATE(14,6,tblMovimientos[ID]/(tblMovimientos[SKU]=kxSKU),15),"")) | C36: =IF($B36="","",INDEX(tblMovimientos[Fecha],$B36)) | D36: =IF($B36="","",INDEX(tblMovimientos[Tipo],$B36)) | E36: =IF($B36="","",IF(INDEX(tblMovimientos[CantidadNeta],$B36)>0,INDEX(tblMovimientos[CantidadNeta],$B36),"")) | F36: =IF($B36="","",IF(INDEX(tblMovimientos[CantidadNeta],$B36)<0,-INDEX(tblMovimientos[CantidadNeta],$B36),"")) | G36: =IF($B36="","",INDEX(tblMovimientos[Saldo],$B36)) | H36: =IF($B36="","",INDEX(tblMovimientos[Documento],$B36)&"") | I36: =IF($B36="","",INDEX(tblMovimientos[Responsable],$B36)&"") | K36: =IF($B36="","",INDEX(tblMovimientos[Observaciones],$B36)&"")
B37: =IF(kxSKU="","",IFERROR(_xlfn.AGGREGATE(14,6,tblMovimientos[ID]/(tblMovimientos[SKU]=kxSKU),16),"")) | C37: =IF($B37="","",INDEX(tblMovimientos[Fecha],$B37)) | D37: =IF($B37="","",INDEX(tblMovimientos[Tipo],$B37)) | E37: =IF($B37="","",IF(INDEX(tblMovimientos[CantidadNeta],$B37)>0,INDEX(tblMovimientos[CantidadNeta],$B37),"")) | F37: =IF($B37="","",IF(INDEX(tblMovimientos[CantidadNeta],$B37)<0,-INDEX(tblMovimientos[CantidadNeta],$B37),"")) | G37: =IF($B37="","",INDEX(tblMovimientos[Saldo],$B37)) | H37: =IF($B37="","",INDEX(tblMovimientos[Documento],$B37)&"") | I37: =IF($B37="","",INDEX(tblMovimientos[Responsable],$B37)&"") | K37: =IF($B37="","",INDEX(tblMovimientos[Observaciones],$B37)&"")
B38: =IF(kxSKU="","",IFERROR(_xlfn.AGGREGATE(14,6,tblMovimientos[ID]/(tblMovimientos[SKU]=kxSKU),17),"")) | C38: =IF($B38="","",INDEX(tblMovimientos[Fecha],$B38)) | D38: =IF($B38="","",INDEX(tblMovimientos[Tipo],$B38)) | E38: =IF($B38="","",IF(INDEX(tblMovimientos[CantidadNeta],$B38)>0,INDEX(tblMovimientos[CantidadNeta],$B38),"")) | F38: =IF($B38="","",IF(INDEX(tblMovimientos[CantidadNeta],$B38)<0,-INDEX(tblMovimientos[CantidadNeta],$B38),"")) | G38: =IF($B38="","",INDEX(tblMovimientos[Saldo],$B38)) | H38: =IF($B38="","",INDEX(tblMovimientos[Documento],$B38)&"") | I38: =IF($B38="","",INDEX(tblMovimientos[Responsable],$B38)&"") | K38: =IF($B38="","",INDEX(tblMovimientos[Observaciones],$B38)&"")
B39: =IF(kxSKU="","",IFERROR(_xlfn.AGGREGATE(14,6,tblMovimientos[ID]/(tblMovimientos[SKU]=kxSKU),18),"")) | C39: =IF($B39="","",INDEX(tblMovimientos[Fecha],$B39)) | D39: =IF($B39="","",INDEX(tblMovimientos[Tipo],$B39)) | E39: =IF($B39="","",IF(INDEX(tblMovimientos[CantidadNeta],$B39)>0,INDEX(tblMovimientos[CantidadNeta],$B39),"")) | F39: =IF($B39="","",IF(INDEX(tblMovimientos[CantidadNeta],$B39)<0,-INDEX(tblMovimientos[CantidadNeta],$B39),"")) | G39: =IF($B39="","",INDEX(tblMovimientos[Saldo],$B39)) | H39: =IF($B39="","",INDEX(tblMovimientos[Documento],$B39)&"") | I39: =IF($B39="","",INDEX(tblMovimientos[Responsable],$B39)&"") | K39: =IF($B39="","",INDEX(tblMovimientos[Observaciones],$B39)&"")
B40: =IF(kxSKU="","",IFERROR(_xlfn.AGGREGATE(14,6,tblMovimientos[ID]/(tblMovimientos[SKU]=kxSKU),19),"")) | C40: =IF($B40="","",INDEX(tblMovimientos[Fecha],$B40)) | D40: =IF($B40="","",INDEX(tblMovimientos[Tipo],$B40)) | E40: =IF($B40="","",IF(INDEX(tblMovimientos[CantidadNeta],$B40)>0,INDEX(tblMovimientos[CantidadNeta],$B40),"")) | F40: =IF($B40="","",IF(INDEX(tblMovimientos[CantidadNeta],$B40)<0,-INDEX(tblMovimientos[CantidadNeta],$B40),"")) | G40: =IF($B40="","",INDEX(tblMovimientos[Saldo],$B40)) | H40: =IF($B40="","",INDEX(tblMovimientos[Documento],$B40)&"") | I40: =IF($B40="","",INDEX(tblMovimientos[Responsable],$B40)&"") | K40: =IF($B40="","",INDEX(tblMovimientos[Observaciones],$B40)&"")
B41: =IF(kxSKU="","",IFERROR(_xlfn.AGGREGATE(14,6,tblMovimientos[ID]/(tblMovimientos[SKU]=kxSKU),20),"")) | C41: =IF($B41="","",INDEX(tblMovimientos[Fecha],$B41)) | D41: =IF($B41="","",INDEX(tblMovimientos[Tipo],$B41)) | E41: =IF($B41="","",IF(INDEX(tblMovimientos[CantidadNeta],$B41)>0,INDEX(tblMovimientos[CantidadNeta],$B41),"")) | F41: =IF($B41="","",IF(INDEX(tblMovimientos[CantidadNeta],$B41)<0,-INDEX(tblMovimientos[CantidadNeta],$B41),"")) | G41: =IF($B41="","",INDEX(tblMovimientos[Saldo],$B41)) | H41: =IF($B41="","",INDEX(tblMovimientos[Documento],$B41)&"") | I41: =IF($B41="","",INDEX(tblMovimientos[Responsable],$B41)&"") | K41: =IF($B41="","",INDEX(tblMovimientos[Observaciones],$B41)&"")
B42: =IF(kxSKU="","",IFERROR(_xlfn.AGGREGATE(14,6,tblMovimientos[ID]/(tblMovimientos[SKU]=kxSKU),21),"")) | C42: =IF($B42="","",INDEX(tblMovimientos[Fecha],$B42)) | D42: =IF($B42="","",INDEX(tblMovimientos[Tipo],$B42)) | E42: =IF($B42="","",IF(INDEX(tblMovimientos[CantidadNeta],$B42)>0,INDEX(tblMovimientos[CantidadNeta],$B42),"")) | F42: =IF($B42="","",IF(INDEX(tblMovimientos[CantidadNeta],$B42)<0,-INDEX(tblMovimientos[CantidadNeta],$B42),"")) | G42: =IF($B42="","",INDEX(tblMovimientos[Saldo],$B42)) | H42: =IF($B42="","",INDEX(tblMovimientos[Documento],$B42)&"") | I42: =IF($B42="","",INDEX(tblMovimientos[Responsable],$B42)&"") | K42: =IF($B42="","",INDEX(tblMovimientos[Observaciones],$B42)&"")
B43: =IF(kxSKU="","",IFERROR(_xlfn.AGGREGATE(14,6,tblMovimientos[ID]/(tblMovimientos[SKU]=kxSKU),22),"")) | C43: =IF($B43="","",INDEX(tblMovimientos[Fecha],$B43)) | D43: =IF($B43="","",INDEX(tblMovimientos[Tipo],$B43)) | E43: =IF($B43="","",IF(INDEX(tblMovimientos[CantidadNeta],$B43)>0,INDEX(tblMovimientos[CantidadNeta],$B43),"")) | F43: =IF($B43="","",IF(INDEX(tblMovimientos[CantidadNeta],$B43)<0,-INDEX(tblMovimientos[CantidadNeta],$B43),"")) | G43: =IF($B43="","",INDEX(tblMovimientos[Saldo],$B43)) | H43: =IF($B43="","",INDEX(tblMovimientos[Documento],$B43)&"") | I43: =IF($B43="","",INDEX(tblMovimientos[Responsable],$B43)&"") | K43: =IF($B43="","",INDEX(tblMovimientos[Observaciones],$B43)&"")
B44: =IF(kxSKU="","",IFERROR(_xlfn.AGGREGATE(14,6,tblMovimientos[ID]/(tblMovimientos[SKU]=kxSKU),23),"")) | C44: =IF($B44="","",INDEX(tblMovimientos[Fecha],$B44)) | D44: =IF($B44="","",INDEX(tblMovimientos[Tipo],$B44)) | E44: =IF($B44="","",IF(INDEX(tblMovimientos[CantidadNeta],$B44)>0,INDEX(tblMovimientos[CantidadNeta],$B44),"")) | F44: =IF($B44="","",IF(INDEX(tblMovimientos[CantidadNeta],$B44)<0,-INDEX(tblMovimientos[CantidadNeta],$B44),"")) | G44: =IF($B44="","",INDEX(tblMovimientos[Saldo],$B44)) | H44: =IF($B44="","",INDEX(tblMovimientos[Documento],$B44)&"") | I44: =IF($B44="","",INDEX(tblMovimientos[Responsable],$B44)&"") | K44: =IF($B44="","",INDEX(tblMovimientos[Observaciones],$B44)&"")
B45: =IF(kxSKU="","",IFERROR(_xlfn.AGGREGATE(14,6,tblMovimientos[ID]/(tblMovimientos[SKU]=kxSKU),24),"")) | C45: =IF($B45="","",INDEX(tblMovimientos[Fecha],$B45)) | D45: =IF($B45="","",INDEX(tblMovimientos[Tipo],$B45)) | E45: =IF($B45="","",IF(INDEX(tblMovimientos[CantidadNeta],$B45)>0,INDEX(tblMovimientos[CantidadNeta],$B45),"")) | F45: =IF($B45="","",IF(INDEX(tblMovimientos[CantidadNeta],$B45)<0,-INDEX(tblMovimientos[CantidadNeta],$B45),"")) | G45: =IF($B45="","",INDEX(tblMovimientos[Saldo],$B45)) | H45: =IF($B45="","",INDEX(tblMovimientos[Documento],$B45)&"") | I45: =IF($B45="","",INDEX(tblMovimientos[Responsable],$B45)&"") | K45: =IF($B45="","",INDEX(tblMovimientos[Observaciones],$B45)&"")
B46: =IF(kxSKU="","",IFERROR(_xlfn.AGGREGATE(14,6,tblMovimientos[ID]/(tblMovimientos[SKU]=kxSKU),25),"")) | C46: =IF($B46="","",INDEX(tblMovimientos[Fecha],$B46)) | D46: =IF($B46="","",INDEX(tblMovimientos[Tipo],$B46)) | E46: =IF($B46="","",IF(INDEX(tblMovimientos[CantidadNeta],$B46)>0,INDEX(tblMovimientos[CantidadNeta],$B46),"")) | F46: =IF($B46="","",IF(INDEX(tblMovimientos[CantidadNeta],$B46)<0,-INDEX(tblMovimientos[CantidadNeta],$B46),"")) | G46: =IF($B46="","",INDEX(tblMovimientos[Saldo],$B46)) | H46: =IF($B46="","",INDEX(tblMovimientos[Documento],$B46)&"") | I46: =IF($B46="","",INDEX(tblMovimientos[Responsable],$B46)&"") | K46: =IF($B46="","",INDEX(tblMovimientos[Observaciones],$B46)&"")
B47: =IF(kxSKU="","",IFERROR(_xlfn.AGGREGATE(14,6,tblMovimientos[ID]/(tblMovimientos[SKU]=kxSKU),26),"")) | C47: =IF($B47="","",INDEX(tblMovimientos[Fecha],$B47)) | D47: =IF($B47="","",INDEX(tblMovimientos[Tipo],$B47)) | E47: =IF($B47="","",IF(INDEX(tblMovimientos[CantidadNeta],$B47)>0,INDEX(tblMovimientos[CantidadNeta],$B47),"")) | F47: =IF($B47="","",IF(INDEX(tblMovimientos[CantidadNeta],$B47)<0,-INDEX(tblMovimientos[CantidadNeta],$B47),"")) | G47: =IF($B47="","",INDEX(tblMovimientos[Saldo],$B47)) | H47: =IF($B47="","",INDEX(tblMovimientos[Documento],$B47)&"") | I47: =IF($B47="","",INDEX(tblMovimientos[Responsable],$B47)&"") | K47: =IF($B47="","",INDEX(tblMovimientos[Observaciones],$B47)&"")
B48: =IF(kxSKU="","",IFERROR(_xlfn.AGGREGATE(14,6,tblMovimientos[ID]/(tblMovimientos[SKU]=kxSKU),27),"")) | C48: =IF($B48="","",INDEX(tblMovimientos[Fecha],$B48)) | D48: =IF($B48="","",INDEX(tblMovimientos[Tipo],$B48)) | E48: =IF($B48="","",IF(INDEX(tblMovimientos[CantidadNeta],$B48)>0,INDEX(tblMovimientos[CantidadNeta],$B48),"")) | F48: =IF($B48="","",IF(INDEX(tblMovimientos[CantidadNeta],$B48)<0,-INDEX(tblMovimientos[CantidadNeta],$B48),"")) | G48: =IF($B48="","",INDEX(tblMovimientos[Saldo],$B48)) | H48: =IF($B48="","",INDEX(tblMovimientos[Documento],$B48)&"") | I48: =IF($B48="","",INDEX(tblMovimientos[Responsable],$B48)&"") | K48: =IF($B48="","",INDEX(tblMovimientos[Observaciones],$B48)&"")
B49: =IF(kxSKU="","",IFERROR(_xlfn.AGGREGATE(14,6,tblMovimientos[ID]/(tblMovimientos[SKU]=kxSKU),28),"")) | C49: =IF($B49="","",INDEX(tblMovimientos[Fecha],$B49)) | D49: =IF($B49="","",INDEX(tblMovimientos[Tipo],$B49)) | E49: =IF($B49="","",IF(INDEX(tblMovimientos[CantidadNeta],$B49)>0,INDEX(tblMovimientos[CantidadNeta],$B49),"")) | F49: =IF($B49="","",IF(INDEX(tblMovimientos[CantidadNeta],$B49)<0,-INDEX(tblMovimientos[CantidadNeta],$B49),"")) | G49: =IF($B49="","",INDEX(tblMovimientos[Saldo],$B49)) | H49: =IF($B49="","",INDEX(tblMovimientos[Documento],$B49)&"") | I49: =IF($B49="","",INDEX(tblMovimientos[Responsable],$B49)&"") | K49: =IF($B49="","",INDEX(tblMovimientos[Observaciones],$B49)&"")
B50: =IF(kxSKU="","",IFERROR(_xlfn.AGGREGATE(14,6,tblMovimientos[ID]/(tblMovimientos[SKU]=kxSKU),29),"")) | C50: =IF($B50="","",INDEX(tblMovimientos[Fecha],$B50)) | D50: =IF($B50="","",INDEX(tblMovimientos[Tipo],$B50)) | E50: =IF($B50="","",IF(INDEX(tblMovimientos[CantidadNeta],$B50)>0,INDEX(tblMovimientos[CantidadNeta],$B50),"")) | F50: =IF($B50="","",IF(INDEX(tblMovimientos[CantidadNeta],$B50)<0,-INDEX(tblMovimientos[CantidadNeta],$B50),"")) | G50: =IF($B50="","",INDEX(tblMovimientos[Saldo],$B50)) | H50: =IF($B50="","",INDEX(tblMovimientos[Documento],$B50)&"") | I50: =IF($B50="","",INDEX(tblMovimientos[Responsable],$B50)&"") | K50: =IF($B50="","",INDEX(tblMovimientos[Observaciones],$B50)&"")
B51: =IF(kxSKU="","",IFERROR(_xlfn.AGGREGATE(14,6,tblMovimientos[ID]/(tblMovimientos[SKU]=kxSKU),30),"")) | C51: =IF($B51="","",INDEX(tblMovimientos[Fecha],$B51)) | D51: =IF($B51="","",INDEX(tblMovimientos[Tipo],$B51)) | E51: =IF($B51="","",IF(INDEX(tblMovimientos[CantidadNeta],$B51)>0,INDEX(tblMovimientos[CantidadNeta],$B51),"")) | F51: =IF($B51="","",IF(INDEX(tblMovimientos[CantidadNeta],$B51)<0,-INDEX(tblMovimientos[CantidadNeta],$B51),"")) | G51: =IF($B51="","",INDEX(tblMovimientos[Saldo],$B51)) | H51: =IF($B51="","",INDEX(tblMovimientos[Documento],$B51)&"") | I51: =IF($B51="","",INDEX(tblMovimientos[Responsable],$B51)&"") | K51: =IF($B51="","",INDEX(tblMovimientos[Observaciones],$B51)&"")
B52: =IF(kxSKU="","",IFERROR(_xlfn.AGGREGATE(14,6,tblMovimientos[ID]/(tblMovimientos[SKU]=kxSKU),31),"")) | C52: =IF($B52="","",INDEX(tblMovimientos[Fecha],$B52)) | D52: =IF($B52="","",INDEX(tblMovimientos[Tipo],$B52)) | E52: =IF($B52="","",IF(INDEX(tblMovimientos[CantidadNeta],$B52)>0,INDEX(tblMovimientos[CantidadNeta],$B52),"")) | F52: =IF($B52="","",IF(INDEX(tblMovimientos[CantidadNeta],$B52)<0,-INDEX(tblMovimientos[CantidadNeta],$B52),"")) | G52: =IF($B52="","",INDEX(tblMovimientos[Saldo],$B52)) | H52: =IF($B52="","",INDEX(tblMovimientos[Documento],$B52)&"") | I52: =IF($B52="","",INDEX(tblMovimientos[Responsable],$B52)&"") | K52: =IF($B52="","",INDEX(tblMovimientos[Observaciones],$B52)&"")
B53: =IF(kxSKU="","",IFERROR(_xlfn.AGGREGATE(14,6,tblMovimientos[ID]/(tblMovimientos[SKU]=kxSKU),32),"")) | C53: =IF($B53="","",INDEX(tblMovimientos[Fecha],$B53)) | D53: =IF($B53="","",INDEX(tblMovimientos[Tipo],$B53)) | E53: =IF($B53="","",IF(INDEX(tblMovimientos[CantidadNeta],$B53)>0,INDEX(tblMovimientos[CantidadNeta],$B53),"")) | F53: =IF($B53="","",IF(INDEX(tblMovimientos[CantidadNeta],$B53)<0,-INDEX(tblMovimientos[CantidadNeta],$B53),"")) | G53: =IF($B53="","",INDEX(tblMovimientos[Saldo],$B53)) | H53: =IF($B53="","",INDEX(tblMovimientos[Documento],$B53)&"") | I53: =IF($B53="","",INDEX(tblMovimientos[Responsable],$B53)&"") | K53: =IF($B53="","",INDEX(tblMovimientos[Observaciones],$B53)&"")
B54: =IF(kxSKU="","",IFERROR(_xlfn.AGGREGATE(14,6,tblMovimientos[ID]/(tblMovimientos[SKU]=kxSKU),33),"")) | C54: =IF($B54="","",INDEX(tblMovimientos[Fecha],$B54)) | D54: =IF($B54="","",INDEX(tblMovimientos[Tipo],$B54)) | E54: =IF($B54="","",IF(INDEX(tblMovimientos[CantidadNeta],$B54)>0,INDEX(tblMovimientos[CantidadNeta],$B54),"")) | F54: =IF($B54="","",IF(INDEX(tblMovimientos[CantidadNeta],$B54)<0,-INDEX(tblMovimientos[CantidadNeta],$B54),"")) | G54: =IF($B54="","",INDEX(tblMovimientos[Saldo],$B54)) | H54: =IF($B54="","",INDEX(tblMovimientos[Documento],$B54)&"") | I54: =IF($B54="","",INDEX(tblMovimientos[Responsable],$B54)&"") | K54: =IF($B54="","",INDEX(tblMovimientos[Observaciones],$B54)&"")
B55: =IF(kxSKU="","",IFERROR(_xlfn.AGGREGATE(14,6,tblMovimientos[ID]/(tblMovimientos[SKU]=kxSKU),34),"")) | C55: =IF($B55="","",INDEX(tblMovimientos[Fecha],$B55)) | D55: =IF($B55="","",INDEX(tblMovimientos[Tipo],$B55)) | E55: =IF($B55="","",IF(INDEX(tblMovimientos[CantidadNeta],$B55)>0,INDEX(tblMovimientos[CantidadNeta],$B55),"")) | F55: =IF($B55="","",IF(INDEX(tblMovimientos[CantidadNeta],$B55)<0,-INDEX(tblMovimientos[CantidadNeta],$B55),"")) | G55: =IF($B55="","",INDEX(tblMovimientos[Saldo],$B55)) | H55: =IF($B55="","",INDEX(tblMovimientos[Documento],$B55)&"") | I55: =IF($B55="","",INDEX(tblMovimientos[Responsable],$B55)&"") | K55: =IF($B55="","",INDEX(tblMovimientos[Observaciones],$B55)&"")
B56: =IF(kxSKU="","",IFERROR(_xlfn.AGGREGATE(14,6,tblMovimientos[ID]/(tblMovimientos[SKU]=kxSKU),35),"")) | C56: =IF($B56="","",INDEX(tblMovimientos[Fecha],$B56)) | D56: =IF($B56="","",INDEX(tblMovimientos[Tipo],$B56)) | E56: =IF($B56="","",IF(INDEX(tblMovimientos[CantidadNeta],$B56)>0,INDEX(tblMovimientos[CantidadNeta],$B56),"")) | F56: =IF($B56="","",IF(INDEX(tblMovimientos[CantidadNeta],$B56)<0,-INDEX(tblMovimientos[CantidadNeta],$B56),"")) | G56: =IF($B56="","",INDEX(tblMovimientos[Saldo],$B56)) | H56: =IF($B56="","",INDEX(tblMovimientos[Documento],$B56)&"") | I56: =IF($B56="","",INDEX(tblMovimientos[Responsable],$B56)&"") | K56: =IF($B56="","",INDEX(tblMovimientos[Observaciones],$B56)&"")
B57: =IF(kxSKU="","",IFERROR(_xlfn.AGGREGATE(14,6,tblMovimientos[ID]/(tblMovimientos[SKU]=kxSKU),36),"")) | C57: =IF($B57="","",INDEX(tblMovimientos[Fecha],$B57)) | D57: =IF($B57="","",INDEX(tblMovimientos[Tipo],$B57)) | E57: =IF($B57="","",IF(INDEX(tblMovimientos[CantidadNeta],$B57)>0,INDEX(tblMovimientos[CantidadNeta],$B57),"")) | F57: =IF($B57="","",IF(INDEX(tblMovimientos[CantidadNeta],$B57)<0,-INDEX(tblMovimientos[CantidadNeta],$B57),"")) | G57: =IF($B57="","",INDEX(tblMovimientos[Saldo],$B57)) | H57: =IF($B57="","",INDEX(tblMovimientos[Documento],$B57)&"") | I57: =IF($B57="","",INDEX(tblMovimientos[Responsable],$B57)&"") | K57: =IF($B57="","",INDEX(tblMovimientos[Observaciones],$B57)&"")
B58: =IF(kxSKU="","",IFERROR(_xlfn.AGGREGATE(14,6,tblMovimientos[ID]/(tblMovimientos[SKU]=kxSKU),37),"")) | C58: =IF($B58="","",INDEX(tblMovimientos[Fecha],$B58)) | D58: =IF($B58="","",INDEX(tblMovimientos[Tipo],$B58)) | E58: =IF($B58="","",IF(INDEX(tblMovimientos[CantidadNeta],$B58)>0,INDEX(tblMovimientos[CantidadNeta],$B58),"")) | F58: =IF($B58="","",IF(INDEX(tblMovimientos[CantidadNeta],$B58)<0,-INDEX(tblMovimientos[CantidadNeta],$B58),"")) | G58: =IF($B58="","",INDEX(tblMovimientos[Saldo],$B58)) | H58: =IF($B58="","",INDEX(tblMovimientos[Documento],$B58)&"") | I58: =IF($B58="","",INDEX(tblMovimientos[Responsable],$B58)&"") | K58: =IF($B58="","",INDEX(tblMovimientos[Observaciones],$B58)&"")
B59: =IF(kxSKU="","",IFERROR(_xlfn.AGGREGATE(14,6,tblMovimientos[ID]/(tblMovimientos[SKU]=kxSKU),38),"")) | C59: =IF($B59="","",INDEX(tblMovimientos[Fecha],$B59)) | D59: =IF($B59="","",INDEX(tblMovimientos[Tipo],$B59)) | E59: =IF($B59="","",IF(INDEX(tblMovimientos[CantidadNeta],$B59)>0,INDEX(tblMovimientos[CantidadNeta],$B59),"")) | F59: =IF($B59="","",IF(INDEX(tblMovimientos[CantidadNeta],$B59)<0,-INDEX(tblMovimientos[CantidadNeta],$B59),"")) | G59: =IF($B59="","",INDEX(tblMovimientos[Saldo],$B59)) | H59: =IF($B59="","",INDEX(tblMovimientos[Documento],$B59)&"") | I59: =IF($B59="","",INDEX(tblMovimientos[Responsable],$B59)&"") | K59: =IF($B59="","",INDEX(tblMovimientos[Observaciones],$B59)&"")
B60: =IF(kxSKU="","",IFERROR(_xlfn.AGGREGATE(14,6,tblMovimientos[ID]/(tblMovimientos[SKU]=kxSKU),39),"")) | C60: =IF($B60="","",INDEX(tblMovimientos[Fecha],$B60)) | D60: =IF($B60="","",INDEX(tblMovimientos[Tipo],$B60)) | E60: =IF($B60="","",IF(INDEX(tblMovimientos[CantidadNeta],$B60)>0,INDEX(tblMovimientos[CantidadNeta],$B60),"")) | F60: =IF($B60="","",IF(INDEX(tblMovimientos[CantidadNeta],$B60)<0,-INDEX(tblMovimientos[CantidadNeta],$B60),"")) | G60: =IF($B60="","",INDEX(tblMovimientos[Saldo],$B60)) | H60: =IF($B60="","",INDEX(tblMovimientos[Documento],$B60)&"") | I60: =IF($B60="","",INDEX(tblMovimientos[Responsable],$B60)&"") | K60: =IF($B60="","",INDEX(tblMovimientos[Observaciones],$B60)&"")
B61: =IF(kxSKU="","",IFERROR(_xlfn.AGGREGATE(14,6,tblMovimientos[ID]/(tblMovimientos[SKU]=kxSKU),40),"")) | C61: =IF($B61="","",INDEX(tblMovimientos[Fecha],$B61)) | D61: =IF($B61="","",INDEX(tblMovimientos[Tipo],$B61)) | E61: =IF($B61="","",IF(INDEX(tblMovimientos[CantidadNeta],$B61)>0,INDEX(tblMovimientos[CantidadNeta],$B61),"")) | F61: =IF($B61="","",IF(INDEX(tblMovimientos[CantidadNeta],$B61)<0,-INDEX(tblMovimientos[CantidadNeta],$B61),"")) | G61: =IF($B61="","",INDEX(tblMovimientos[Saldo],$B61)) | H61: =IF($B61="","",INDEX(tblMovimientos[Documento],$B61)&"") | I61: =IF($B61="","",INDEX(tblMovimientos[Responsable],$B61)&"") | K61: =IF($B61="","",INDEX(tblMovimientos[Observaciones],$B61)&"")
B62: =IF(kxSKU="","",IFERROR(_xlfn.AGGREGATE(14,6,tblMovimientos[ID]/(tblMovimientos[SKU]=kxSKU),41),"")) | C62: =IF($B62="","",INDEX(tblMovimientos[Fecha],$B62)) | D62: =IF($B62="","",INDEX(tblMovimientos[Tipo],$B62)) | E62: =IF($B62="","",IF(INDEX(tblMovimientos[CantidadNeta],$B62)>0,INDEX(tblMovimientos[CantidadNeta],$B62),"")) | F62: =IF($B62="","",IF(INDEX(tblMovimientos[CantidadNeta],$B62)<0,-INDEX(tblMovimientos[CantidadNeta],$B62),"")) | G62: =IF($B62="","",INDEX(tblMovimientos[Saldo],$B62)) | H62: =IF($B62="","",INDEX(tblMovimientos[Documento],$B62)&"") | I62: =IF($B62="","",INDEX(tblMovimientos[Responsable],$B62)&"") | K62: =IF($B62="","",INDEX(tblMovimientos[Observaciones],$B62)&"")
B63: =IF(kxSKU="","",IFERROR(_xlfn.AGGREGATE(14,6,tblMovimientos[ID]/(tblMovimientos[SKU]=kxSKU),42),"")) | C63: =IF($B63="","",INDEX(tblMovimientos[Fecha],$B63)) | D63: =IF($B63="","",INDEX(tblMovimientos[Tipo],$B63)) | E63: =IF($B63="","",IF(INDEX(tblMovimientos[CantidadNeta],$B63)>0,INDEX(tblMovimientos[CantidadNeta],$B63),"")) | F63: =IF($B63="","",IF(INDEX(tblMovimientos[CantidadNeta],$B63)<0,-INDEX(tblMovimientos[CantidadNeta],$B63),"")) | G63: =IF($B63="","",INDEX(tblMovimientos[Saldo],$B63)) | H63: =IF($B63="","",INDEX(tblMovimientos[Documento],$B63)&"") | I63: =IF($B63="","",INDEX(tblMovimientos[Responsable],$B63)&"") | K63: =IF($B63="","",INDEX(tblMovimientos[Observaciones],$B63)&"")
B64: =IF(kxSKU="","",IFERROR(_xlfn.AGGREGATE(14,6,tblMovimientos[ID]/(tblMovimientos[SKU]=kxSKU),43),"")) | C64: =IF($B64="","",INDEX(tblMovimientos[Fecha],$B64)) | D64: =IF($B64="","",INDEX(tblMovimientos[Tipo],$B64)) | E64: =IF($B64="","",IF(INDEX(tblMovimientos[CantidadNeta],$B64)>0,INDEX(tblMovimientos[CantidadNeta],$B64),"")) | F64: =IF($B64="","",IF(INDEX(tblMovimientos[CantidadNeta],$B64)<0,-INDEX(tblMovimientos[CantidadNeta],$B64),"")) | G64: =IF($B64="","",INDEX(tblMovimientos[Saldo],$B64)) | H64: =IF($B64="","",INDEX(tblMovimientos[Documento],$B64)&"") | I64: =IF($B64="","",INDEX(tblMovimientos[Responsable],$B64)&"") | K64: =IF($B64="","",INDEX(tblMovimientos[Observaciones],$B64)&"")
B65: =IF(kxSKU="","",IFERROR(_xlfn.AGGREGATE(14,6,tblMovimientos[ID]/(tblMovimientos[SKU]=kxSKU),44),"")) | C65: =IF($B65="","",INDEX(tblMovimientos[Fecha],$B65)) | D65: =IF($B65="","",INDEX(tblMovimientos[Tipo],$B65)) | E65: =IF($B65="","",IF(INDEX(tblMovimientos[CantidadNeta],$B65)>0,INDEX(tblMovimientos[CantidadNeta],$B65),"")) | F65: =IF($B65="","",IF(INDEX(tblMovimientos[CantidadNeta],$B65)<0,-INDEX(tblMovimientos[CantidadNeta],$B65),"")) | G65: =IF($B65="","",INDEX(tblMovimientos[Saldo],$B65)) | H65: =IF($B65="","",INDEX(tblMovimientos[Documento],$B65)&"") | I65: =IF($B65="","",INDEX(tblMovimientos[Responsable],$B65)&"") | K65: =IF($B65="","",INDEX(tblMovimientos[Observaciones],$B65)&"")
B66: =IF(kxSKU="","",IFERROR(_xlfn.AGGREGATE(14,6,tblMovimientos[ID]/(tblMovimientos[SKU]=kxSKU),45),"")) | C66: =IF($B66="","",INDEX(tblMovimientos[Fecha],$B66)) | D66: =IF($B66="","",INDEX(tblMovimientos[Tipo],$B66)) | E66: =IF($B66="","",IF(INDEX(tblMovimientos[CantidadNeta],$B66)>0,INDEX(tblMovimientos[CantidadNeta],$B66),"")) | F66: =IF($B66="","",IF(INDEX(tblMovimientos[CantidadNeta],$B66)<0,-INDEX(tblMovimientos[CantidadNeta],$B66),"")) | G66: =IF($B66="","",INDEX(tblMovimientos[Saldo],$B66)) | H66: =IF($B66="","",INDEX(tblMovimientos[Documento],$B66)&"") | I66: =IF($B66="","",INDEX(tblMovimientos[Responsable],$B66)&"") | K66: =IF($B66="","",INDEX(tblMovimientos[Observaciones],$B66)&"")
B67: =IF(kxSKU="","",IFERROR(_xlfn.AGGREGATE(14,6,tblMovimientos[ID]/(tblMovimientos[SKU]=kxSKU),46),"")) | C67: =IF($B67="","",INDEX(tblMovimientos[Fecha],$B67)) | D67: =IF($B67="","",INDEX(tblMovimientos[Tipo],$B67)) | E67: =IF($B67="","",IF(INDEX(tblMovimientos[CantidadNeta],$B67)>0,INDEX(tblMovimientos[CantidadNeta],$B67),"")) | F67: =IF($B67="","",IF(INDEX(tblMovimientos[CantidadNeta],$B67)<0,-INDEX(tblMovimientos[CantidadNeta],$B67),"")) | G67: =IF($B67="","",INDEX(tblMovimientos[Saldo],$B67)) | H67: =IF($B67="","",INDEX(tblMovimientos[Documento],$B67)&"") | I67: =IF($B67="","",INDEX(tblMovimientos[Responsable],$B67)&"") | K67: =IF($B67="","",INDEX(tblMovimientos[Observaciones],$B67)&"")
B68: =IF(kxSKU="","",IFERROR(_xlfn.AGGREGATE(14,6,tblMovimientos[ID]/(tblMovimientos[SKU]=kxSKU),47),"")) | C68: =IF($B68="","",INDEX(tblMovimientos[Fecha],$B68)) | D68: =IF($B68="","",INDEX(tblMovimientos[Tipo],$B68)) | E68: =IF($B68="","",IF(INDEX(tblMovimientos[CantidadNeta],$B68)>0,INDEX(tblMovimientos[CantidadNeta],$B68),"")) | F68: =IF($B68="","",IF(INDEX(tblMovimientos[CantidadNeta],$B68)<0,-INDEX(tblMovimientos[CantidadNeta],$B68),"")) | G68: =IF($B68="","",INDEX(tblMovimientos[Saldo],$B68)) | H68: =IF($B68="","",INDEX(tblMovimientos[Documento],$B68)&"") | I68: =IF($B68="","",INDEX(tblMovimientos[Responsable],$B68)&"") | K68: =IF($B68="","",INDEX(tblMovimientos[Observaciones],$B68)&"")
B69: =IF(kxSKU="","",IFERROR(_xlfn.AGGREGATE(14,6,tblMovimientos[ID]/(tblMovimientos[SKU]=kxSKU),48),"")) | C69: =IF($B69="","",INDEX(tblMovimientos[Fecha],$B69)) | D69: =IF($B69="","",INDEX(tblMovimientos[Tipo],$B69)) | E69: =IF($B69="","",IF(INDEX(tblMovimientos[CantidadNeta],$B69)>0,INDEX(tblMovimientos[CantidadNeta],$B69),"")) | F69: =IF($B69="","",IF(INDEX(tblMovimientos[CantidadNeta],$B69)<0,-INDEX(tblMovimientos[CantidadNeta],$B69),"")) | G69: =IF($B69="","",INDEX(tblMovimientos[Saldo],$B69)) | H69: =IF($B69="","",INDEX(tblMovimientos[Documento],$B69)&"") | I69: =IF($B69="","",INDEX(tblMovimientos[Responsable],$B69)&"") | K69: =IF($B69="","",INDEX(tblMovimientos[Observaciones],$B69)&"")
B70: =IF(kxSKU="","",IFERROR(_xlfn.AGGREGATE(14,6,tblMovimientos[ID]/(tblMovimientos[SKU]=kxSKU),49),"")) | C70: =IF($B70="","",INDEX(tblMovimientos[Fecha],$B70)) | D70: =IF($B70="","",INDEX(tblMovimientos[Tipo],$B70)) | E70: =IF($B70="","",IF(INDEX(tblMovimientos[CantidadNeta],$B70)>0,INDEX(tblMovimientos[CantidadNeta],$B70),"")) | F70: =IF($B70="","",IF(INDEX(tblMovimientos[CantidadNeta],$B70)<0,-INDEX(tblMovimientos[CantidadNeta],$B70),"")) | G70: =IF($B70="","",INDEX(tblMovimientos[Saldo],$B70)) | H70: =IF($B70="","",INDEX(tblMovimientos[Documento],$B70)&"") | I70: =IF($B70="","",INDEX(tblMovimientos[Responsable],$B70)&"") | K70: =IF($B70="","",INDEX(tblMovimientos[Observaciones],$B70)&"")
B71: =IF(kxSKU="","",IFERROR(_xlfn.AGGREGATE(14,6,tblMovimientos[ID]/(tblMovimientos[SKU]=kxSKU),50),"")) | C71: =IF($B71="","",INDEX(tblMovimientos[Fecha],$B71)) | D71: =IF($B71="","",INDEX(tblMovimientos[Tipo],$B71)) | E71: =IF($B71="","",IF(INDEX(tblMovimientos[CantidadNeta],$B71)>0,INDEX(tblMovimientos[CantidadNeta],$B71),"")) | F71: =IF($B71="","",IF(INDEX(tblMovimientos[CantidadNeta],$B71)<0,-INDEX(tblMovimientos[CantidadNeta],$B71),"")) | G71: =IF($B71="","",INDEX(tblMovimientos[Saldo],$B71)) | H71: =IF($B71="","",INDEX(tblMovimientos[Documento],$B71)&"") | I71: =IF($B71="","",INDEX(tblMovimientos[Responsable],$B71)&"") | K71: =IF($B71="","",INDEX(tblMovimientos[Observaciones],$B71)&"")
B72: =IF(kxSKU="","",IFERROR(_xlfn.AGGREGATE(14,6,tblMovimientos[ID]/(tblMovimientos[SKU]=kxSKU),51),"")) | C72: =IF($B72="","",INDEX(tblMovimientos[Fecha],$B72)) | D72: =IF($B72="","",INDEX(tblMovimientos[Tipo],$B72)) | E72: =IF($B72="","",IF(INDEX(tblMovimientos[CantidadNeta],$B72)>0,INDEX(tblMovimientos[CantidadNeta],$B72),"")) | F72: =IF($B72="","",IF(INDEX(tblMovimientos[CantidadNeta],$B72)<0,-INDEX(tblMovimientos[CantidadNeta],$B72),"")) | G72: =IF($B72="","",INDEX(tblMovimientos[Saldo],$B72)) | H72: =IF($B72="","",INDEX(tblMovimientos[Documento],$B72)&"") | I72: =IF($B72="","",INDEX(tblMovimientos[Responsable],$B72)&"") | K72: =IF($B72="","",INDEX(tblMovimientos[Observaciones],$B72)&"")
B73: =IF(kxSKU="","",IFERROR(_xlfn.AGGREGATE(14,6,tblMovimientos[ID]/(tblMovimientos[SKU]=kxSKU),52),"")) | C73: =IF($B73="","",INDEX(tblMovimientos[Fecha],$B73)) | D73: =IF($B73="","",INDEX(tblMovimientos[Tipo],$B73)) | E73: =IF($B73="","",IF(INDEX(tblMovimientos[CantidadNeta],$B73)>0,INDEX(tblMovimientos[CantidadNeta],$B73),"")) | F73: =IF($B73="","",IF(INDEX(tblMovimientos[CantidadNeta],$B73)<0,-INDEX(tblMovimientos[CantidadNeta],$B73),"")) | G73: =IF($B73="","",INDEX(tblMovimientos[Saldo],$B73)) | H73: =IF($B73="","",INDEX(tblMovimientos[Documento],$B73)&"") | I73: =IF($B73="","",INDEX(tblMovimientos[Responsable],$B73)&"") | K73: =IF($B73="","",INDEX(tblMovimientos[Observaciones],$B73)&"")
B74: =IF(kxSKU="","",IFERROR(_xlfn.AGGREGATE(14,6,tblMovimientos[ID]/(tblMovimientos[SKU]=kxSKU),53),"")) | C74: =IF($B74="","",INDEX(tblMovimientos[Fecha],$B74)) | D74: =IF($B74="","",INDEX(tblMovimientos[Tipo],$B74)) | E74: =IF($B74="","",IF(INDEX(tblMovimientos[CantidadNeta],$B74)>0,INDEX(tblMovimientos[CantidadNeta],$B74),"")) | F74: =IF($B74="","",IF(INDEX(tblMovimientos[CantidadNeta],$B74)<0,-INDEX(tblMovimientos[CantidadNeta],$B74),"")) | G74: =IF($B74="","",INDEX(tblMovimientos[Saldo],$B74)) | H74: =IF($B74="","",INDEX(tblMovimientos[Documento],$B74)&"") | I74: =IF($B74="","",INDEX(tblMovimientos[Responsable],$B74)&"") | K74: =IF($B74="","",INDEX(tblMovimientos[Observaciones],$B74)&"")
B75: =IF(kxSKU="","",IFERROR(_xlfn.AGGREGATE(14,6,tblMovimientos[ID]/(tblMovimientos[SKU]=kxSKU),54),"")) | C75: =IF($B75="","",INDEX(tblMovimientos[Fecha],$B75)) | D75: =IF($B75="","",INDEX(tblMovimientos[Tipo],$B75)) | E75: =IF($B75="","",IF(INDEX(tblMovimientos[CantidadNeta],$B75)>0,INDEX(tblMovimientos[CantidadNeta],$B75),"")) | F75: =IF($B75="","",IF(INDEX(tblMovimientos[CantidadNeta],$B75)<0,-INDEX(tblMovimientos[CantidadNeta],$B75),"")) | G75: =IF($B75="","",INDEX(tblMovimientos[Saldo],$B75)) | H75: =IF($B75="","",INDEX(tblMovimientos[Documento],$B75)&"") | I75: =IF($B75="","",INDEX(tblMovimientos[Responsable],$B75)&"") | K75: =IF($B75="","",INDEX(tblMovimientos[Observaciones],$B75)&"")
B76: =IF(kxSKU="","",IFERROR(_xlfn.AGGREGATE(14,6,tblMovimientos[ID]/(tblMovimientos[SKU]=kxSKU),55),"")) | C76: =IF($B76="","",INDEX(tblMovimientos[Fecha],$B76)) | D76: =IF($B76="","",INDEX(tblMovimientos[Tipo],$B76)) | E76: =IF($B76="","",IF(INDEX(tblMovimientos[CantidadNeta],$B76)>0,INDEX(tblMovimientos[CantidadNeta],$B76),"")) | F76: =IF($B76="","",IF(INDEX(tblMovimientos[CantidadNeta],$B76)<0,-INDEX(tblMovimientos[CantidadNeta],$B76),"")) | G76: =IF($B76="","",INDEX(tblMovimientos[Saldo],$B76)) | H76: =IF($B76="","",INDEX(tblMovimientos[Documento],$B76)&"") | I76: =IF($B76="","",INDEX(tblMovimientos[Responsable],$B76)&"") | K76: =IF($B76="","",INDEX(tblMovimientos[Observaciones],$B76)&"")
B77: =IF(kxSKU="","",IFERROR(_xlfn.AGGREGATE(14,6,tblMovimientos[ID]/(tblMovimientos[SKU]=kxSKU),56),"")) | C77: =IF($B77="","",INDEX(tblMovimientos[Fecha],$B77)) | D77: =IF($B77="","",INDEX(tblMovimientos[Tipo],$B77)) | E77: =IF($B77="","",IF(INDEX(tblMovimientos[CantidadNeta],$B77)>0,INDEX(tblMovimientos[CantidadNeta],$B77),"")) | F77: =IF($B77="","",IF(INDEX(tblMovimientos[CantidadNeta],$B77)<0,-INDEX(tblMovimientos[CantidadNeta],$B77),"")) | G77: =IF($B77="","",INDEX(tblMovimientos[Saldo],$B77)) | H77: =IF($B77="","",INDEX(tblMovimientos[Documento],$B77)&"") | I77: =IF($B77="","",INDEX(tblMovimientos[Responsable],$B77)&"") | K77: =IF($B77="","",INDEX(tblMovimientos[Observaciones],$B77)&"")
B78: =IF(kxSKU="","",IFERROR(_xlfn.AGGREGATE(14,6,tblMovimientos[ID]/(tblMovimientos[SKU]=kxSKU),57),"")) | C78: =IF($B78="","",INDEX(tblMovimientos[Fecha],$B78)) | D78: =IF($B78="","",INDEX(tblMovimientos[Tipo],$B78)) | E78: =IF($B78="","",IF(INDEX(tblMovimientos[CantidadNeta],$B78)>0,INDEX(tblMovimientos[CantidadNeta],$B78),"")) | F78: =IF($B78="","",IF(INDEX(tblMovimientos[CantidadNeta],$B78)<0,-INDEX(tblMovimientos[CantidadNeta],$B78),"")) | G78: =IF($B78="","",INDEX(tblMovimientos[Saldo],$B78)) | H78: =IF($B78="","",INDEX(tblMovimientos[Documento],$B78)&"") | I78: =IF($B78="","",INDEX(tblMovimientos[Responsable],$B78)&"") | K78: =IF($B78="","",INDEX(tblMovimientos[Observaciones],$B78)&"")
B79: =IF(kxSKU="","",IFERROR(_xlfn.AGGREGATE(14,6,tblMovimientos[ID]/(tblMovimientos[SKU]=kxSKU),58),"")) | C79: =IF($B79="","",INDEX(tblMovimientos[Fecha],$B79)) | D79: =IF($B79="","",INDEX(tblMovimientos[Tipo],$B79)) | E79: =IF($B79="","",IF(INDEX(tblMovimientos[CantidadNeta],$B79)>0,INDEX(tblMovimientos[CantidadNeta],$B79),"")) | F79: =IF($B79="","",IF(INDEX(tblMovimientos[CantidadNeta],$B79)<0,-INDEX(tblMovimientos[CantidadNeta],$B79),"")) | G79: =IF($B79="","",INDEX(tblMovimientos[Saldo],$B79)) | H79: =IF($B79="","",INDEX(tblMovimientos[Documento],$B79)&"") | I79: =IF($B79="","",INDEX(tblMovimientos[Responsable],$B79)&"") | K79: =IF($B79="","",INDEX(tblMovimientos[Observaciones],$B79)&"")
B80: =IF(kxSKU="","",IFERROR(_xlfn.AGGREGATE(14,6,tblMovimientos[ID]/(tblMovimientos[SKU]=kxSKU),59),"")) | C80: =IF($B80="","",INDEX(tblMovimientos[Fecha],$B80)) | D80: =IF($B80="","",INDEX(tblMovimientos[Tipo],$B80)) | E80: =IF($B80="","",IF(INDEX(tblMovimientos[CantidadNeta],$B80)>0,INDEX(tblMovimientos[CantidadNeta],$B80),"")) | F80: =IF($B80="","",IF(INDEX(tblMovimientos[CantidadNeta],$B80)<0,-INDEX(tblMovimientos[CantidadNeta],$B80),"")) | G80: =IF($B80="","",INDEX(tblMovimientos[Saldo],$B80)) | H80: =IF($B80="","",INDEX(tblMovimientos[Documento],$B80)&"") | I80: =IF($B80="","",INDEX(tblMovimientos[Responsable],$B80)&"") | K80: =IF($B80="","",INDEX(tblMovimientos[Observaciones],$B80)&"")
B81: =IF(kxSKU="","",IFERROR(_xlfn.AGGREGATE(14,6,tblMovimientos[ID]/(tblMovimientos[SKU]=kxSKU),60),"")) | C81: =IF($B81="","",INDEX(tblMovimientos[Fecha],$B81)) | D81: =IF($B81="","",INDEX(tblMovimientos[Tipo],$B81)) | E81: =IF($B81="","",IF(INDEX(tblMovimientos[CantidadNeta],$B81)>0,INDEX(tblMovimientos[CantidadNeta],$B81),"")) | F81: =IF($B81="","",IF(INDEX(tblMovimientos[CantidadNeta],$B81)<0,-INDEX(tblMovimientos[CantidadNeta],$B81),"")) | G81: =IF($B81="","",INDEX(tblMovimientos[Saldo],$B81)) | H81: =IF($B81="","",INDEX(tblMovimientos[Documento],$B81)&"") | I81: =IF($B81="","",INDEX(tblMovimientos[Responsable],$B81)&"") | K81: =IF($B81="","",INDEX(tblMovimientos[Observaciones],$B81)&"")
B82: =IF(kxSKU="","",IFERROR(_xlfn.AGGREGATE(14,6,tblMovimientos[ID]/(tblMovimientos[SKU]=kxSKU),61),"")) | C82: =IF($B82="","",INDEX(tblMovimientos[Fecha],$B82)) | D82: =IF($B82="","",INDEX(tblMovimientos[Tipo],$B82)) | E82: =IF($B82="","",IF(INDEX(tblMovimientos[CantidadNeta],$B82)>0,INDEX(tblMovimientos[CantidadNeta],$B82),"")) | F82: =IF($B82="","",IF(INDEX(tblMovimientos[CantidadNeta],$B82)<0,-INDEX(tblMovimientos[CantidadNeta],$B82),"")) | G82: =IF($B82="","",INDEX(tblMovimientos[Saldo],$B82)) | H82: =IF($B82="","",INDEX(tblMovimientos[Documento],$B82)&"") | I82: =IF($B82="","",INDEX(tblMovimientos[Responsable],$B82)&"") | K82: =IF($B82="","",INDEX(tblMovimientos[Observaciones],$B82)&"")
B83: =IF(kxSKU="","",IFERROR(_xlfn.AGGREGATE(14,6,tblMovimientos[ID]/(tblMovimientos[SKU]=kxSKU),62),"")) | C83: =IF($B83="","",INDEX(tblMovimientos[Fecha],$B83)) | D83: =IF($B83="","",INDEX(tblMovimientos[Tipo],$B83)) | E83: =IF($B83="","",IF(INDEX(tblMovimientos[CantidadNeta],$B83)>0,INDEX(tblMovimientos[CantidadNeta],$B83),"")) | F83: =IF($B83="","",IF(INDEX(tblMovimientos[CantidadNeta],$B83)<0,-INDEX(tblMovimientos[CantidadNeta],$B83),"")) | G83: =IF($B83="","",INDEX(tblMovimientos[Saldo],$B83)) | H83: =IF($B83="","",INDEX(tblMovimientos[Documento],$B83)&"") | I83: =IF($B83="","",INDEX(tblMovimientos[Responsable],$B83)&"") | K83: =IF($B83="","",INDEX(tblMovimientos[Observaciones],$B83)&"")
B84: =IF(kxSKU="","",IFERROR(_xlfn.AGGREGATE(14,6,tblMovimientos[ID]/(tblMovimientos[SKU]=kxSKU),63),"")) | C84: =IF($B84="","",INDEX(tblMovimientos[Fecha],$B84)) | D84: =IF($B84="","",INDEX(tblMovimientos[Tipo],$B84)) | E84: =IF($B84="","",IF(INDEX(tblMovimientos[CantidadNeta],$B84)>0,INDEX(tblMovimientos[CantidadNeta],$B84),"")) | F84: =IF($B84="","",IF(INDEX(tblMovimientos[CantidadNeta],$B84)<0,-INDEX(tblMovimientos[CantidadNeta],$B84),"")) | G84: =IF($B84="","",INDEX(tblMovimientos[Saldo],$B84)) | H84: =IF($B84="","",INDEX(tblMovimientos[Documento],$B84)&"") | I84: =IF($B84="","",INDEX(tblMovimientos[Responsable],$B84)&"") | K84: =IF($B84="","",INDEX(tblMovimientos[Observaciones],$B84)&"")
B85: =IF(kxSKU="","",IFERROR(_xlfn.AGGREGATE(14,6,tblMovimientos[ID]/(tblMovimientos[SKU]=kxSKU),64),"")) | C85: =IF($B85="","",INDEX(tblMovimientos[Fecha],$B85)) | D85: =IF($B85="","",INDEX(tblMovimientos[Tipo],$B85)) | E85: =IF($B85="","",IF(INDEX(tblMovimientos[CantidadNeta],$B85)>0,INDEX(tblMovimientos[CantidadNeta],$B85),"")) | F85: =IF($B85="","",IF(INDEX(tblMovimientos[CantidadNeta],$B85)<0,-INDEX(tblMovimientos[CantidadNeta],$B85),"")) | G85: =IF($B85="","",INDEX(tblMovimientos[Saldo],$B85)) | H85: =IF($B85="","",INDEX(tblMovimientos[Documento],$B85)&"") | I85: =IF($B85="","",INDEX(tblMovimientos[Responsable],$B85)&"") | K85: =IF($B85="","",INDEX(tblMovimientos[Observaciones],$B85)&"")
B86: =IF(kxSKU="","",IFERROR(_xlfn.AGGREGATE(14,6,tblMovimientos[ID]/(tblMovimientos[SKU]=kxSKU),65),"")) | C86: =IF($B86="","",INDEX(tblMovimientos[Fecha],$B86)) | D86: =IF($B86="","",INDEX(tblMovimientos[Tipo],$B86)) | E86: =IF($B86="","",IF(INDEX(tblMovimientos[CantidadNeta],$B86)>0,INDEX(tblMovimientos[CantidadNeta],$B86),"")) | F86: =IF($B86="","",IF(INDEX(tblMovimientos[CantidadNeta],$B86)<0,-INDEX(tblMovimientos[CantidadNeta],$B86),"")) | G86: =IF($B86="","",INDEX(tblMovimientos[Saldo],$B86)) | H86: =IF($B86="","",INDEX(tblMovimientos[Documento],$B86)&"") | I86: =IF($B86="","",INDEX(tblMovimientos[Responsable],$B86)&"") | K86: =IF($B86="","",INDEX(tblMovimientos[Observaciones],$B86)&"")
B87: =IF(kxSKU="","",IFERROR(_xlfn.AGGREGATE(14,6,tblMovimientos[ID]/(tblMovimientos[SKU]=kxSKU),66),"")) | C87: =IF($B87="","",INDEX(tblMovimientos[Fecha],$B87)) | D87: =IF($B87="","",INDEX(tblMovimientos[Tipo],$B87)) | E87: =IF($B87="","",IF(INDEX(tblMovimientos[CantidadNeta],$B87)>0,INDEX(tblMovimientos[CantidadNeta],$B87),"")) | F87: =IF($B87="","",IF(INDEX(tblMovimientos[CantidadNeta],$B87)<0,-INDEX(tblMovimientos[CantidadNeta],$B87),"")) | G87: =IF($B87="","",INDEX(tblMovimientos[Saldo],$B87)) | H87: =IF($B87="","",INDEX(tblMovimientos[Documento],$B87)&"") | I87: =IF($B87="","",INDEX(tblMovimientos[Responsable],$B87)&"") | K87: =IF($B87="","",INDEX(tblMovimientos[Observaciones],$B87)&"")
B88: =IF(kxSKU="","",IFERROR(_xlfn.AGGREGATE(14,6,tblMovimientos[ID]/(tblMovimientos[SKU]=kxSKU),67),"")) | C88: =IF($B88="","",INDEX(tblMovimientos[Fecha],$B88)) | D88: =IF($B88="","",INDEX(tblMovimientos[Tipo],$B88)) | E88: =IF($B88="","",IF(INDEX(tblMovimientos[CantidadNeta],$B88)>0,INDEX(tblMovimientos[CantidadNeta],$B88),"")) | F88: =IF($B88="","",IF(INDEX(tblMovimientos[CantidadNeta],$B88)<0,-INDEX(tblMovimientos[CantidadNeta],$B88),"")) | G88: =IF($B88="","",INDEX(tblMovimientos[Saldo],$B88)) | H88: =IF($B88="","",INDEX(tblMovimientos[Documento],$B88)&"") | I88: =IF($B88="","",INDEX(tblMovimientos[Responsable],$B88)&"") | K88: =IF($B88="","",INDEX(tblMovimientos[Observaciones],$B88)&"")
B89: =IF(kxSKU="","",IFERROR(_xlfn.AGGREGATE(14,6,tblMovimientos[ID]/(tblMovimientos[SKU]=kxSKU),68),"")) | C89: =IF($B89="","",INDEX(tblMovimientos[Fecha],$B89)) | D89: =IF($B89="","",INDEX(tblMovimientos[Tipo],$B89)) | E89: =IF($B89="","",IF(INDEX(tblMovimientos[CantidadNeta],$B89)>0,INDEX(tblMovimientos[CantidadNeta],$B89),"")) | F89: =IF($B89="","",IF(INDEX(tblMovimientos[CantidadNeta],$B89)<0,-INDEX(tblMovimientos[CantidadNeta],$B89),"")) | G89: =IF($B89="","",INDEX(tblMovimientos[Saldo],$B89)) | H89: =IF($B89="","",INDEX(tblMovimientos[Documento],$B89)&"") | I89: =IF($B89="","",INDEX(tblMovimientos[Responsable],$B89)&"") | K89: =IF($B89="","",INDEX(tblMovimientos[Observaciones],$B89)&"")
B90: =IF(kxSKU="","",IFERROR(_xlfn.AGGREGATE(14,6,tblMovimientos[ID]/(tblMovimientos[SKU]=kxSKU),69),"")) | C90: =IF($B90="","",INDEX(tblMovimientos[Fecha],$B90)) | D90: =IF($B90="","",INDEX(tblMovimientos[Tipo],$B90)) | E90: =IF($B90="","",IF(INDEX(tblMovimientos[CantidadNeta],$B90)>0,INDEX(tblMovimientos[CantidadNeta],$B90),"")) | F90: =IF($B90="","",IF(INDEX(tblMovimientos[CantidadNeta],$B90)<0,-INDEX(tblMovimientos[CantidadNeta],$B90),"")) | G90: =IF($B90="","",INDEX(tblMovimientos[Saldo],$B90)) | H90: =IF($B90="","",INDEX(tblMovimientos[Documento],$B90)&"") | I90: =IF($B90="","",INDEX(tblMovimientos[Responsable],$B90)&"") | K90: =IF($B90="","",INDEX(tblMovimientos[Observaciones],$B90)&"")
B91: =IF(kxSKU="","",IFERROR(_xlfn.AGGREGATE(14,6,tblMovimientos[ID]/(tblMovimientos[SKU]=kxSKU),70),"")) | C91: =IF($B91="","",INDEX(tblMovimientos[Fecha],$B91)) | D91: =IF($B91="","",INDEX(tblMovimientos[Tipo],$B91)) | E91: =IF($B91="","",IF(INDEX(tblMovimientos[CantidadNeta],$B91)>0,INDEX(tblMovimientos[CantidadNeta],$B91),"")) | F91: =IF($B91="","",IF(INDEX(tblMovimientos[CantidadNeta],$B91)<0,-INDEX(tblMovimientos[CantidadNeta],$B91),"")) | G91: =IF($B91="","",INDEX(tblMovimientos[Saldo],$B91)) | H91: =IF($B91="","",INDEX(tblMovimientos[Documento],$B91)&"") | I91: =IF($B91="","",INDEX(tblMovimientos[Responsable],$B91)&"") | K91: =IF($B91="","",INDEX(tblMovimientos[Observaciones],$B91)&"")
B92: =IF(kxSKU="","",IFERROR(_xlfn.AGGREGATE(14,6,tblMovimientos[ID]/(tblMovimientos[SKU]=kxSKU),71),"")) | C92: =IF($B92="","",INDEX(tblMovimientos[Fecha],$B92)) | D92: =IF($B92="","",INDEX(tblMovimientos[Tipo],$B92)) | E92: =IF($B92="","",IF(INDEX(tblMovimientos[CantidadNeta],$B92)>0,INDEX(tblMovimientos[CantidadNeta],$B92),"")) | F92: =IF($B92="","",IF(INDEX(tblMovimientos[CantidadNeta],$B92)<0,-INDEX(tblMovimientos[CantidadNeta],$B92),"")) | G92: =IF($B92="","",INDEX(tblMovimientos[Saldo],$B92)) | H92: =IF($B92="","",INDEX(tblMovimientos[Documento],$B92)&"") | I92: =IF($B92="","",INDEX(tblMovimientos[Responsable],$B92)&"") | K92: =IF($B92="","",INDEX(tblMovimientos[Observaciones],$B92)&"")
B93: =IF(kxSKU="","",IFERROR(_xlfn.AGGREGATE(14,6,tblMovimientos[ID]/(tblMovimientos[SKU]=kxSKU),72),"")) | C93: =IF($B93="","",INDEX(tblMovimientos[Fecha],$B93)) | D93: =IF($B93="","",INDEX(tblMovimientos[Tipo],$B93)) | E93: =IF($B93="","",IF(INDEX(tblMovimientos[CantidadNeta],$B93)>0,INDEX(tblMovimientos[CantidadNeta],$B93),"")) | F93: =IF($B93="","",IF(INDEX(tblMovimientos[CantidadNeta],$B93)<0,-INDEX(tblMovimientos[CantidadNeta],$B93),"")) | G93: =IF($B93="","",INDEX(tblMovimientos[Saldo],$B93)) | H93: =IF($B93="","",INDEX(tblMovimientos[Documento],$B93)&"") | I93: =IF($B93="","",INDEX(tblMovimientos[Responsable],$B93)&"") | K93: =IF($B93="","",INDEX(tblMovimientos[Observaciones],$B93)&"")
B94: =IF(kxSKU="","",IFERROR(_xlfn.AGGREGATE(14,6,tblMovimientos[ID]/(tblMovimientos[SKU]=kxSKU),73),"")) | C94: =IF($B94="","",INDEX(tblMovimientos[Fecha],$B94)) | D94: =IF($B94="","",INDEX(tblMovimientos[Tipo],$B94)) | E94: =IF($B94="","",IF(INDEX(tblMovimientos[CantidadNeta],$B94)>0,INDEX(tblMovimientos[CantidadNeta],$B94),"")) | F94: =IF($B94="","",IF(INDEX(tblMovimientos[CantidadNeta],$B94)<0,-INDEX(tblMovimientos[CantidadNeta],$B94),"")) | G94: =IF($B94="","",INDEX(tblMovimientos[Saldo],$B94)) | H94: =IF($B94="","",INDEX(tblMovimientos[Documento],$B94)&"") | I94: =IF($B94="","",INDEX(tblMovimientos[Responsable],$B94)&"") | K94: =IF($B94="","",INDEX(tblMovimientos[Observaciones],$B94)&"")
B95: =IF(kxSKU="","",IFERROR(_xlfn.AGGREGATE(14,6,tblMovimientos[ID]/(tblMovimientos[SKU]=kxSKU),74),"")) | C95: =IF($B95="","",INDEX(tblMovimientos[Fecha],$B95)) | D95: =IF($B95="","",INDEX(tblMovimientos[Tipo],$B95)) | E95: =IF($B95="","",IF(INDEX(tblMovimientos[CantidadNeta],$B95)>0,INDEX(tblMovimientos[CantidadNeta],$B95),"")) | F95: =IF($B95="","",IF(INDEX(tblMovimientos[CantidadNeta],$B95)<0,-INDEX(tblMovimientos[CantidadNeta],$B95),"")) | G95: =IF($B95="","",INDEX(tblMovimientos[Saldo],$B95)) | H95: =IF($B95="","",INDEX(tblMovimientos[Documento],$B95)&"") | I95: =IF($B95="","",INDEX(tblMovimientos[Responsable],$B95)&"") | K95: =IF($B95="","",INDEX(tblMovimientos[Observaciones],$B95)&"")
B96: =IF(kxSKU="","",IFERROR(_xlfn.AGGREGATE(14,6,tblMovimientos[ID]/(tblMovimientos[SKU]=kxSKU),75),"")) | C96: =IF($B96="","",INDEX(tblMovimientos[Fecha],$B96)) | D96: =IF($B96="","",INDEX(tblMovimientos[Tipo],$B96)) | E96: =IF($B96="","",IF(INDEX(tblMovimientos[CantidadNeta],$B96)>0,INDEX(tblMovimientos[CantidadNeta],$B96),"")) | F96: =IF($B96="","",IF(INDEX(tblMovimientos[CantidadNeta],$B96)<0,-INDEX(tblMovimientos[CantidadNeta],$B96),"")) | G96: =IF($B96="","",INDEX(tblMovimientos[Saldo],$B96)) | H96: =IF($B96="","",INDEX(tblMovimientos[Documento],$B96)&"") | I96: =IF($B96="","",INDEX(tblMovimientos[Responsable],$B96)&"") | K96: =IF($B96="","",INDEX(tblMovimientos[Observaciones],$B96)&"")
B97: =IF(kxSKU="","",IFERROR(_xlfn.AGGREGATE(14,6,tblMovimientos[ID]/(tblMovimientos[SKU]=kxSKU),76),"")) | C97: =IF($B97="","",INDEX(tblMovimientos[Fecha],$B97)) | D97: =IF($B97="","",INDEX(tblMovimientos[Tipo],$B97)) | E97: =IF($B97="","",IF(INDEX(tblMovimientos[CantidadNeta],$B97)>0,INDEX(tblMovimientos[CantidadNeta],$B97),"")) | F97: =IF($B97="","",IF(INDEX(tblMovimientos[CantidadNeta],$B97)<0,-INDEX(tblMovimientos[CantidadNeta],$B97),"")) | G97: =IF($B97="","",INDEX(tblMovimientos[Saldo],$B97)) | H97: =IF($B97="","",INDEX(tblMovimientos[Documento],$B97)&"") | I97: =IF($B97="","",INDEX(tblMovimientos[Responsable],$B97)&"") | K97: =IF($B97="","",INDEX(tblMovimientos[Observaciones],$B97)&"")
B98: =IF(kxSKU="","",IFERROR(_xlfn.AGGREGATE(14,6,tblMovimientos[ID]/(tblMovimientos[SKU]=kxSKU),77),"")) | C98: =IF($B98="","",INDEX(tblMovimientos[Fecha],$B98)) | D98: =IF($B98="","",INDEX(tblMovimientos[Tipo],$B98)) | E98: =IF($B98="","",IF(INDEX(tblMovimientos[CantidadNeta],$B98)>0,INDEX(tblMovimientos[CantidadNeta],$B98),"")) | F98: =IF($B98="","",IF(INDEX(tblMovimientos[CantidadNeta],$B98)<0,-INDEX(tblMovimientos[CantidadNeta],$B98),"")) | G98: =IF($B98="","",INDEX(tblMovimientos[Saldo],$B98)) | H98: =IF($B98="","",INDEX(tblMovimientos[Documento],$B98)&"") | I98: =IF($B98="","",INDEX(tblMovimientos[Responsable],$B98)&"") | K98: =IF($B98="","",INDEX(tblMovimientos[Observaciones],$B98)&"")
B99: =IF(kxSKU="","",IFERROR(_xlfn.AGGREGATE(14,6,tblMovimientos[ID]/(tblMovimientos[SKU]=kxSKU),78),"")) | C99: =IF($B99="","",INDEX(tblMovimientos[Fecha],$B99)) | D99: =IF($B99="","",INDEX(tblMovimientos[Tipo],$B99)) | E99: =IF($B99="","",IF(INDEX(tblMovimientos[CantidadNeta],$B99)>0,INDEX(tblMovimientos[CantidadNeta],$B99),"")) | F99: =IF($B99="","",IF(INDEX(tblMovimientos[CantidadNeta],$B99)<0,-INDEX(tblMovimientos[CantidadNeta],$B99),"")) | G99: =IF($B99="","",INDEX(tblMovimientos[Saldo],$B99)) | H99: =IF($B99="","",INDEX(tblMovimientos[Documento],$B99)&"") | I99: =IF($B99="","",INDEX(tblMovimientos[Responsable],$B99)&"") | K99: =IF($B99="","",INDEX(tblMovimientos[Observaciones],$B99)&"")
B100: =IF(kxSKU="","",IFERROR(_xlfn.AGGREGATE(14,6,tblMovimientos[ID]/(tblMovimientos[SKU]=kxSKU),79),"")) | C100: =IF($B100="","",INDEX(tblMovimientos[Fecha],$B100)) | D100: =IF($B100="","",INDEX(tblMovimientos[Tipo],$B100)) | E100: =IF($B100="","",IF(INDEX(tblMovimientos[CantidadNeta],$B100)>0,INDEX(tblMovimientos[CantidadNeta],$B100),"")) | F100: =IF($B100="","",IF(INDEX(tblMovimientos[CantidadNeta],$B100)<0,-INDEX(tblMovimientos[CantidadNeta],$B100),"")) | G100: =IF($B100="","",INDEX(tblMovimientos[Saldo],$B100)) | H100: =IF($B100="","",INDEX(tblMovimientos[Documento],$B100)&"") | I100: =IF($B100="","",INDEX(tblMovimientos[Responsable],$B100)&"") | K100: =IF($B100="","",INDEX(tblMovimientos[Observaciones],$B100)&"")
B101: =IF(kxSKU="","",IFERROR(_xlfn.AGGREGATE(14,6,tblMovimientos[ID]/(tblMovimientos[SKU]=kxSKU),80),"")) | C101: =IF($B101="","",INDEX(tblMovimientos[Fecha],$B101)) | D101: =IF($B101="","",INDEX(tblMovimientos[Tipo],$B101)) | E101: =IF($B101="","",IF(INDEX(tblMovimientos[CantidadNeta],$B101)>0,INDEX(tblMovimientos[CantidadNeta],$B101),"")) | F101: =IF($B101="","",IF(INDEX(tblMovimientos[CantidadNeta],$B101)<0,-INDEX(tblMovimientos[CantidadNeta],$B101),"")) | G101: =IF($B101="","",INDEX(tblMovimientos[Saldo],$B101)) | H101: =IF($B101="","",INDEX(tblMovimientos[Documento],$B101)&"") | I101: =IF($B101="","",INDEX(tblMovimientos[Responsable],$B101)&"") | K101: =IF($B101="","",INDEX(tblMovimientos[Observaciones],$B101)&"")
B102: =IF(kxSKU="","",IFERROR(_xlfn.AGGREGATE(14,6,tblMovimientos[ID]/(tblMovimientos[SKU]=kxSKU),81),"")) | C102: =IF($B102="","",INDEX(tblMovimientos[Fecha],$B102)) | D102: =IF($B102="","",INDEX(tblMovimientos[Tipo],$B102)) | E102: =IF($B102="","",IF(INDEX(tblMovimientos[CantidadNeta],$B102)>0,INDEX(tblMovimientos[CantidadNeta],$B102),"")) | F102: =IF($B102="","",IF(INDEX(tblMovimientos[CantidadNeta],$B102)<0,-INDEX(tblMovimientos[CantidadNeta],$B102),"")) | G102: =IF($B102="","",INDEX(tblMovimientos[Saldo],$B102)) | H102: =IF($B102="","",INDEX(tblMovimientos[Documento],$B102)&"") | I102: =IF($B102="","",INDEX(tblMovimientos[Responsable],$B102)&"") | K102: =IF($B102="","",INDEX(tblMovimientos[Observaciones],$B102)&"")
B103: =IF(kxSKU="","",IFERROR(_xlfn.AGGREGATE(14,6,tblMovimientos[ID]/(tblMovimientos[SKU]=kxSKU),82),"")) | C103: =IF($B103="","",INDEX(tblMovimientos[Fecha],$B103)) | D103: =IF($B103="","",INDEX(tblMovimientos[Tipo],$B103)) | E103: =IF($B103="","",IF(INDEX(tblMovimientos[CantidadNeta],$B103)>0,INDEX(tblMovimientos[CantidadNeta],$B103),"")) | F103: =IF($B103="","",IF(INDEX(tblMovimientos[CantidadNeta],$B103)<0,-INDEX(tblMovimientos[CantidadNeta],$B103),"")) | G103: =IF($B103="","",INDEX(tblMovimientos[Saldo],$B103)) | H103: =IF($B103="","",INDEX(tblMovimientos[Documento],$B103)&"") | I103: =IF($B103="","",INDEX(tblMovimientos[Responsable],$B103)&"") | K103: =IF($B103="","",INDEX(tblMovimientos[Observaciones],$B103)&"")
B104: =IF(kxSKU="","",IFERROR(_xlfn.AGGREGATE(14,6,tblMovimientos[ID]/(tblMovimientos[SKU]=kxSKU),83),"")) | C104: =IF($B104="","",INDEX(tblMovimientos[Fecha],$B104)) | D104: =IF($B104="","",INDEX(tblMovimientos[Tipo],$B104)) | E104: =IF($B104="","",IF(INDEX(tblMovimientos[CantidadNeta],$B104)>0,INDEX(tblMovimientos[CantidadNeta],$B104),"")) | F104: =IF($B104="","",IF(INDEX(tblMovimientos[CantidadNeta],$B104)<0,-INDEX(tblMovimientos[CantidadNeta],$B104),"")) | G104: =IF($B104="","",INDEX(tblMovimientos[Saldo],$B104)) | H104: =IF($B104="","",INDEX(tblMovimientos[Documento],$B104)&"") | I104: =IF($B104="","",INDEX(tblMovimientos[Responsable],$B104)&"") | K104: =IF($B104="","",INDEX(tblMovimientos[Observaciones],$B104)&"")
B105: =IF(kxSKU="","",IFERROR(_xlfn.AGGREGATE(14,6,tblMovimientos[ID]/(tblMovimientos[SKU]=kxSKU),84),"")) | C105: =IF($B105="","",INDEX(tblMovimientos[Fecha],$B105)) | D105: =IF($B105="","",INDEX(tblMovimientos[Tipo],$B105)) | E105: =IF($B105="","",IF(INDEX(tblMovimientos[CantidadNeta],$B105)>0,INDEX(tblMovimientos[CantidadNeta],$B105),"")) | F105: =IF($B105="","",IF(INDEX(tblMovimientos[CantidadNeta],$B105)<0,-INDEX(tblMovimientos[CantidadNeta],$B105),"")) | G105: =IF($B105="","",INDEX(tblMovimientos[Saldo],$B105)) | H105: =IF($B105="","",INDEX(tblMovimientos[Documento],$B105)&"") | I105: =IF($B105="","",INDEX(tblMovimientos[Responsable],$B105)&"") | K105: =IF($B105="","",INDEX(tblMovimientos[Observaciones],$B105)&"")
B106: =IF(kxSKU="","",IFERROR(_xlfn.AGGREGATE(14,6,tblMovimientos[ID]/(tblMovimientos[SKU]=kxSKU),85),"")) | C106: =IF($B106="","",INDEX(tblMovimientos[Fecha],$B106)) | D106: =IF($B106="","",INDEX(tblMovimientos[Tipo],$B106)) | E106: =IF($B106="","",IF(INDEX(tblMovimientos[CantidadNeta],$B106)>0,INDEX(tblMovimientos[CantidadNeta],$B106),"")) | F106: =IF($B106="","",IF(INDEX(tblMovimientos[CantidadNeta],$B106)<0,-INDEX(tblMovimientos[CantidadNeta],$B106),"")) | G106: =IF($B106="","",INDEX(tblMovimientos[Saldo],$B106)) | H106: =IF($B106="","",INDEX(tblMovimientos[Documento],$B106)&"") | I106: =IF($B106="","",INDEX(tblMovimientos[Responsable],$B106)&"") | K106: =IF($B106="","",INDEX(tblMovimientos[Observaciones],$B106)&"")
B107: =IF(kxSKU="","",IFERROR(_xlfn.AGGREGATE(14,6,tblMovimientos[ID]/(tblMovimientos[SKU]=kxSKU),86),"")) | C107: =IF($B107="","",INDEX(tblMovimientos[Fecha],$B107)) | D107: =IF($B107="","",INDEX(tblMovimientos[Tipo],$B107)) | E107: =IF($B107="","",IF(INDEX(tblMovimientos[CantidadNeta],$B107)>0,INDEX(tblMovimientos[CantidadNeta],$B107),"")) | F107: =IF($B107="","",IF(INDEX(tblMovimientos[CantidadNeta],$B107)<0,-INDEX(tblMovimientos[CantidadNeta],$B107),"")) | G107: =IF($B107="","",INDEX(tblMovimientos[Saldo],$B107)) | H107: =IF($B107="","",INDEX(tblMovimientos[Documento],$B107)&"") | I107: =IF($B107="","",INDEX(tblMovimientos[Responsable],$B107)&"") | K107: =IF($B107="","",INDEX(tblMovimientos[Observaciones],$B107)&"")
B108: =IF(kxSKU="","",IFERROR(_xlfn.AGGREGATE(14,6,tblMovimientos[ID]/(tblMovimientos[SKU]=kxSKU),87),"")) | C108: =IF($B108="","",INDEX(tblMovimientos[Fecha],$B108)) | D108: =IF($B108="","",INDEX(tblMovimientos[Tipo],$B108)) | E108: =IF($B108="","",IF(INDEX(tblMovimientos[CantidadNeta],$B108)>0,INDEX(tblMovimientos[CantidadNeta],$B108),"")) | F108: =IF($B108="","",IF(INDEX(tblMovimientos[CantidadNeta],$B108)<0,-INDEX(tblMovimientos[CantidadNeta],$B108),"")) | G108: =IF($B108="","",INDEX(tblMovimientos[Saldo],$B108)) | H108: =IF($B108="","",INDEX(tblMovimientos[Documento],$B108)&"") | I108: =IF($B108="","",INDEX(tblMovimientos[Responsable],$B108)&"") | K108: =IF($B108="","",INDEX(tblMovimientos[Observaciones],$B108)&"")
...

Sheet 18_PEDIDO
B2: Pedido sugerido de compra
B3: Capa de lectura · Qué comprar, cuánto y a quién · Filtre por proveedor e imprima (Ctrl + P)
B7: =cfgEmpresa -> NOMBRE DE SU EMPRESA | J7: PEDIDO SUGERIDO
B8: ="NIT "&cfgNIT&" · "&cfgBodega -> NIT · Bodega principal | J8: =YEAR(TODAY())*10000+MONTH(TODAY())*100+DAY(TODAY()) -> 20260925
B9: Sugerido por M-INV a partir de las alertas de stock (reposición hasta el máximo). | J9: =TODAY() -> 46290
B10: Filtrar por proveedor: | D10: (Todos) | J10: =kpiPedidoTotal -> 0
B11: =txtPedidoContacto -> Todos los proveedores. Para enviar un pedido, elija el proveedor e imprima. | J11: =txtPedidoResumen -> 0 línea(s) · 0 proveedor(es)
B12: =txtPedidoEntrega | J12: Elaboró: ______________ Aprobó: ______________
B14: # | C14: Proveedor | D14: SKU | E14: Producto | F14: Unidad | G14: Stock | H14: Mínimo | I14: Máximo | J14: Prioridad | K14: A pedir | L14: Costo unit. | M14: Subtotal
B15: =IF('91_KPIS'!$T8="","",1) | C15: =IF($B15="","",IF(INDEX(tblStock[Proveedor],'91_KPIS'!$T8)="","(Sin proveedor)",INDEX(tblStock[Proveedor],'91_KPIS'!$T8))) | D15: =IF($B15="","",INDEX(tblStock[SKU],'91_KPIS'!$T8)) | E15: =IF($B15="","",INDEX(tblStock[Producto],'91_KPIS'!$T8)) | F15: =IF($B15="","",INDEX(tblStock[Unidad],'91_KPIS'!$T8)) | G15: =IF($B15="","",INDEX(tblStock[StockActual],'91_KPIS'!$T8)) | H15: =IF($B15="","",INDEX(tblStock[StockMin],'91_KPIS'!$T8)) | I15: =IF($B15="","",INDEX(tblStock[StockMax],'91_KPIS'!$T8)) | J15: =IF($B15="","",INDEX(tblStock[Estado],'91_KPIS'!$T8)) | K15: =IF($B15="","",MAX(0,IF($I15>0,$I15,2*$H15)-MAX(0,$G15))) | L15: =IF($B15="","",INDEX(tblStock[CostoUnitario],'91_KPIS'!$T8)) | M15: =IF($B15="","",$K15*$L15)
B16: =IF('91_KPIS'!$T9="","",2) | C16: =IF($B16="","",IF(INDEX(tblStock[Proveedor],'91_KPIS'!$T9)="","(Sin proveedor)",INDEX(tblStock[Proveedor],'91_KPIS'!$T9))) | D16: =IF($B16="","",INDEX(tblStock[SKU],'91_KPIS'!$T9)) | E16: =IF($B16="","",INDEX(tblStock[Producto],'91_KPIS'!$T9)) | F16: =IF($B16="","",INDEX(tblStock[Unidad],'91_KPIS'!$T9)) | G16: =IF($B16="","",INDEX(tblStock[StockActual],'91_KPIS'!$T9)) | H16: =IF($B16="","",INDEX(tblStock[StockMin],'91_KPIS'!$T9)) | I16: =IF($B16="","",INDEX(tblStock[StockMax],'91_KPIS'!$T9)) | J16: =IF($B16="","",INDEX(tblStock[Estado],'91_KPIS'!$T9)) | K16: =IF($B16="","",MAX(0,IF($I16>0,$I16,2*$H16)-MAX(0,$G16))) | L16: =IF($B16="","",INDEX(tblStock[CostoUnitario],'91_KPIS'!$T9)) | M16: =IF($B16="","",$K16*$L16)
B17: =IF('91_KPIS'!$T10="","",3) | C17: =IF($B17="","",IF(INDEX(tblStock[Proveedor],'91_KPIS'!$T10)="","(Sin proveedor)",INDEX(tblStock[Proveedor],'91_KPIS'!$T10))) | D17: =IF($B17="","",INDEX(tblStock[SKU],'91_KPIS'!$T10)) | E17: =IF($B17="","",INDEX(tblStock[Producto],'91_KPIS'!$T10)) | F17: =IF($B17="","",INDEX(tblStock[Unidad],'91_KPIS'!$T10)) | G17: =IF($B17="","",INDEX(tblStock[StockActual],'91_KPIS'!$T10)) | H17: =IF($B17="","",INDEX(tblStock[StockMin],'91_KPIS'!$T10)) | I17: =IF($B17="","",INDEX(tblStock[StockMax],'91_KPIS'!$T10)) | J17: =IF($B17="","",INDEX(tblStock[Estado],'91_KPIS'!$T10)) | K17: =IF($B17="","",MAX(0,IF($I17>0,$I17,2*$H17)-MAX(0,$G17))) | L17: =IF($B17="","",INDEX(tblStock[CostoUnitario],'91_KPIS'!$T10)) | M17: =IF($B17="","",$K17*$L17)
B18: =IF('91_KPIS'!$T11="","",4) | C18: =IF($B18="","",IF(INDEX(tblStock[Proveedor],'91_KPIS'!$T11)="","(Sin proveedor)",INDEX(tblStock[Proveedor],'91_KPIS'!$T11))) | D18: =IF($B18="","",INDEX(tblStock[SKU],'91_KPIS'!$T11)) | E18: =IF($B18="","",INDEX(tblStock[Producto],'91_KPIS'!$T11)) | F18: =IF($B18="","",INDEX(tblStock[Unidad],'91_KPIS'!$T11)) | G18: =IF($B18="","",INDEX(tblStock[StockActual],'91_KPIS'!$T11)) | H18: =IF($B18="","",INDEX(tblStock[StockMin],'91_KPIS'!$T11)) | I18: =IF($B18="","",INDEX(tblStock[StockMax],'91_KPIS'!$T11)) | J18: =IF($B18="","",INDEX(tblStock[Estado],'91_KPIS'!$T11)) | K18: =IF($B18="","",MAX(0,IF($I18>0,$I18,2*$H18)-MAX(0,$G18))) | L18: =IF($B18="","",INDEX(tblStock[CostoUnitario],'91_KPIS'!$T11)) | M18: =IF($B18="","",$K18*$L18)
B19: =IF('91_KPIS'!$T12="","",5) | C19: =IF($B19="","",IF(INDEX(tblStock[Proveedor],'91_KPIS'!$T12)="","(Sin proveedor)",INDEX(tblStock[Proveedor],'91_KPIS'!$T12))) | D19: =IF($B19="","",INDEX(tblStock[SKU],'91_KPIS'!$T12)) | E19: =IF($B19="","",INDEX(tblStock[Producto],'91_KPIS'!$T12)) | F19: =IF($B19="","",INDEX(tblStock[Unidad],'91_KPIS'!$T12)) | G19: =IF($B19="","",INDEX(tblStock[StockActual],'91_KPIS'!$T12)) | H19: =IF($B19="","",INDEX(tblStock[StockMin],'91_KPIS'!$T12)) | I19: =IF($B19="","",INDEX(tblStock[StockMax],'91_KPIS'!$T12)) | J19: =IF($B19="","",INDEX(tblStock[Estado],'91_KPIS'!$T12)) | K19: =IF($B19="","",MAX(0,IF($I19>0,$I19,2*$H19)-MAX(0,$G19))) | L19: =IF($B19="","",INDEX(tblStock[CostoUnitario],'91_KPIS'!$T12)) | M19: =IF($B19="","",$K19*$L19)
B20: =IF('91_KPIS'!$T13="","",6) | C20: =IF($B20="","",IF(INDEX(tblStock[Proveedor],'91_KPIS'!$T13)="","(Sin proveedor)",INDEX(tblStock[Proveedor],'91_KPIS'!$T13))) | D20: =IF($B20="","",INDEX(tblStock[SKU],'91_KPIS'!$T13)) | E20: =IF($B20="","",INDEX(tblStock[Producto],'91_KPIS'!$T13)) | F20: =IF($B20="","",INDEX(tblStock[Unidad],'91_KPIS'!$T13)) | G20: =IF($B20="","",INDEX(tblStock[StockActual],'91_KPIS'!$T13)) | H20: =IF($B20="","",INDEX(tblStock[StockMin],'91_KPIS'!$T13)) | I20: =IF($B20="","",INDEX(tblStock[StockMax],'91_KPIS'!$T13)) | J20: =IF($B20="","",INDEX(tblStock[Estado],'91_KPIS'!$T13)) | K20: =IF($B20="","",MAX(0,IF($I20>0,$I20,2*$H20)-MAX(0,$G20))) | L20: =IF($B20="","",INDEX(tblStock[CostoUnitario],'91_KPIS'!$T13)) | M20: =IF($B20="","",$K20*$L20)
B21: =IF('91_KPIS'!$T14="","",7) | C21: =IF($B21="","",IF(INDEX(tblStock[Proveedor],'91_KPIS'!$T14)="","(Sin proveedor)",INDEX(tblStock[Proveedor],'91_KPIS'!$T14))) | D21: =IF($B21="","",INDEX(tblStock[SKU],'91_KPIS'!$T14)) | E21: =IF($B21="","",INDEX(tblStock[Producto],'91_KPIS'!$T14)) | F21: =IF($B21="","",INDEX(tblStock[Unidad],'91_KPIS'!$T14)) | G21: =IF($B21="","",INDEX(tblStock[StockActual],'91_KPIS'!$T14)) | H21: =IF($B21="","",INDEX(tblStock[StockMin],'91_KPIS'!$T14)) | I21: =IF($B21="","",INDEX(tblStock[StockMax],'91_KPIS'!$T14)) | J21: =IF($B21="","",INDEX(tblStock[Estado],'91_KPIS'!$T14)) | K21: =IF($B21="","",MAX(0,IF($I21>0,$I21,2*$H21)-MAX(0,$G21))) | L21: =IF($B21="","",INDEX(tblStock[CostoUnitario],'91_KPIS'!$T14)) | M21: =IF($B21="","",$K21*$L21)
B22: =IF('91_KPIS'!$T15="","",8) | C22: =IF($B22="","",IF(INDEX(tblStock[Proveedor],'91_KPIS'!$T15)="","(Sin proveedor)",INDEX(tblStock[Proveedor],'91_KPIS'!$T15))) | D22: =IF($B22="","",INDEX(tblStock[SKU],'91_KPIS'!$T15)) | E22: =IF($B22="","",INDEX(tblStock[Producto],'91_KPIS'!$T15)) | F22: =IF($B22="","",INDEX(tblStock[Unidad],'91_KPIS'!$T15)) | G22: =IF($B22="","",INDEX(tblStock[StockActual],'91_KPIS'!$T15)) | H22: =IF($B22="","",INDEX(tblStock[StockMin],'91_KPIS'!$T15)) | I22: =IF($B22="","",INDEX(tblStock[StockMax],'91_KPIS'!$T15)) | J22: =IF($B22="","",INDEX(tblStock[Estado],'91_KPIS'!$T15)) | K22: =IF($B22="","",MAX(0,IF($I22>0,$I22,2*$H22)-MAX(0,$G22))) | L22: =IF($B22="","",INDEX(tblStock[CostoUnitario],'91_KPIS'!$T15)) | M22: =IF($B22="","",$K22*$L22)
B23: =IF('91_KPIS'!$T16="","",9) | C23: =IF($B23="","",IF(INDEX(tblStock[Proveedor],'91_KPIS'!$T16)="","(Sin proveedor)",INDEX(tblStock[Proveedor],'91_KPIS'!$T16))) | D23: =IF($B23="","",INDEX(tblStock[SKU],'91_KPIS'!$T16)) | E23: =IF($B23="","",INDEX(tblStock[Producto],'91_KPIS'!$T16)) | F23: =IF($B23="","",INDEX(tblStock[Unidad],'91_KPIS'!$T16)) | G23: =IF($B23="","",INDEX(tblStock[StockActual],'91_KPIS'!$T16)) | H23: =IF($B23="","",INDEX(tblStock[StockMin],'91_KPIS'!$T16)) | I23: =IF($B23="","",INDEX(tblStock[StockMax],'91_KPIS'!$T16)) | J23: =IF($B23="","",INDEX(tblStock[Estado],'91_KPIS'!$T16)) | K23: =IF($B23="","",MAX(0,IF($I23>0,$I23,2*$H23)-MAX(0,$G23))) | L23: =IF($B23="","",INDEX(tblStock[CostoUnitario],'91_KPIS'!$T16)) | M23: =IF($B23="","",$K23*$L23)
B24: =IF('91_KPIS'!$T17="","",10) | C24: =IF($B24="","",IF(INDEX(tblStock[Proveedor],'91_KPIS'!$T17)="","(Sin proveedor)",INDEX(tblStock[Proveedor],'91_KPIS'!$T17))) | D24: =IF($B24="","",INDEX(tblStock[SKU],'91_KPIS'!$T17)) | E24: =IF($B24="","",INDEX(tblStock[Producto],'91_KPIS'!$T17)) | F24: =IF($B24="","",INDEX(tblStock[Unidad],'91_KPIS'!$T17)) | G24: =IF($B24="","",INDEX(tblStock[StockActual],'91_KPIS'!$T17)) | H24: =IF($B24="","",INDEX(tblStock[StockMin],'91_KPIS'!$T17)) | I24: =IF($B24="","",INDEX(tblStock[StockMax],'91_KPIS'!$T17)) | J24: =IF($B24="","",INDEX(tblStock[Estado],'91_KPIS'!$T17)) | K24: =IF($B24="","",MAX(0,IF($I24>0,$I24,2*$H24)-MAX(0,$G24))) | L24: =IF($B24="","",INDEX(tblStock[CostoUnitario],'91_KPIS'!$T17)) | M24: =IF($B24="","",$K24*$L24)
B25: =IF('91_KPIS'!$T18="","",11) | C25: =IF($B25="","",IF(INDEX(tblStock[Proveedor],'91_KPIS'!$T18)="","(Sin proveedor)",INDEX(tblStock[Proveedor],'91_KPIS'!$T18))) | D25: =IF($B25="","",INDEX(tblStock[SKU],'91_KPIS'!$T18)) | E25: =IF($B25="","",INDEX(tblStock[Producto],'91_KPIS'!$T18)) | F25: =IF($B25="","",INDEX(tblStock[Unidad],'91_KPIS'!$T18)) | G25: =IF($B25="","",INDEX(tblStock[StockActual],'91_KPIS'!$T18)) | H25: =IF($B25="","",INDEX(tblStock[StockMin],'91_KPIS'!$T18)) | I25: =IF($B25="","",INDEX(tblStock[StockMax],'91_KPIS'!$T18)) | J25: =IF($B25="","",INDEX(tblStock[Estado],'91_KPIS'!$T18)) | K25: =IF($B25="","",MAX(0,IF($I25>0,$I25,2*$H25)-MAX(0,$G25))) | L25: =IF($B25="","",INDEX(tblStock[CostoUnitario],'91_KPIS'!$T18)) | M25: =IF($B25="","",$K25*$L25)
B26: =IF('91_KPIS'!$T19="","",12) | C26: =IF($B26="","",IF(INDEX(tblStock[Proveedor],'91_KPIS'!$T19)="","(Sin proveedor)",INDEX(tblStock[Proveedor],'91_KPIS'!$T19))) | D26: =IF($B26="","",INDEX(tblStock[SKU],'91_KPIS'!$T19)) | E26: =IF($B26="","",INDEX(tblStock[Producto],'91_KPIS'!$T19)) | F26: =IF($B26="","",INDEX(tblStock[Unidad],'91_KPIS'!$T19)) | G26: =IF($B26="","",INDEX(tblStock[StockActual],'91_KPIS'!$T19)) | H26: =IF($B26="","",INDEX(tblStock[StockMin],'91_KPIS'!$T19)) | I26: =IF($B26="","",INDEX(tblStock[StockMax],'91_KPIS'!$T19)) | J26: =IF($B26="","",INDEX(tblStock[Estado],'91_KPIS'!$T19)) | K26: =IF($B26="","",MAX(0,IF($I26>0,$I26,2*$H26)-MAX(0,$G26))) | L26: =IF($B26="","",INDEX(tblStock[CostoUnitario],'91_KPIS'!$T19)) | M26: =IF($B26="","",$K26*$L26)
B27: =IF('91_KPIS'!$T20="","",13) | C27: =IF($B27="","",IF(INDEX(tblStock[Proveedor],'91_KPIS'!$T20)="","(Sin proveedor)",INDEX(tblStock[Proveedor],'91_KPIS'!$T20))) | D27: =IF($B27="","",INDEX(tblStock[SKU],'91_KPIS'!$T20)) | E27: =IF($B27="","",INDEX(tblStock[Producto],'91_KPIS'!$T20)) | F27: =IF($B27="","",INDEX(tblStock[Unidad],'91_KPIS'!$T20)) | G27: =IF($B27="","",INDEX(tblStock[StockActual],'91_KPIS'!$T20)) | H27: =IF($B27="","",INDEX(tblStock[StockMin],'91_KPIS'!$T20)) | I27: =IF($B27="","",INDEX(tblStock[StockMax],'91_KPIS'!$T20)) | J27: =IF($B27="","",INDEX(tblStock[Estado],'91_KPIS'!$T20)) | K27: =IF($B27="","",MAX(0,IF($I27>0,$I27,2*$H27)-MAX(0,$G27))) | L27: =IF($B27="","",INDEX(tblStock[CostoUnitario],'91_KPIS'!$T20)) | M27: =IF($B27="","",$K27*$L27)
B28: =IF('91_KPIS'!$T21="","",14) | C28: =IF($B28="","",IF(INDEX(tblStock[Proveedor],'91_KPIS'!$T21)="","(Sin proveedor)",INDEX(tblStock[Proveedor],'91_KPIS'!$T21))) | D28: =IF($B28="","",INDEX(tblStock[SKU],'91_KPIS'!$T21)) | E28: =IF($B28="","",INDEX(tblStock[Producto],'91_KPIS'!$T21)) | F28: =IF($B28="","",INDEX(tblStock[Unidad],'91_KPIS'!$T21)) | G28: =IF($B28="","",INDEX(tblStock[StockActual],'91_KPIS'!$T21)) | H28: =IF($B28="","",INDEX(tblStock[StockMin],'91_KPIS'!$T21)) | I28: =IF($B28="","",INDEX(tblStock[StockMax],'91_KPIS'!$T21)) | J28: =IF($B28="","",INDEX(tblStock[Estado],'91_KPIS'!$T21)) | K28: =IF($B28="","",MAX(0,IF($I28>0,$I28,2*$H28)-MAX(0,$G28))) | L28: =IF($B28="","",INDEX(tblStock[CostoUnitario],'91_KPIS'!$T21)) | M28: =IF($B28="","",$K28*$L28)
B29: =IF('91_KPIS'!$T22="","",15) | C29: =IF($B29="","",IF(INDEX(tblStock[Proveedor],'91_KPIS'!$T22)="","(Sin proveedor)",INDEX(tblStock[Proveedor],'91_KPIS'!$T22))) | D29: =IF($B29="","",INDEX(tblStock[SKU],'91_KPIS'!$T22)) | E29: =IF($B29="","",INDEX(tblStock[Producto],'91_KPIS'!$T22)) | F29: =IF($B29="","",INDEX(tblStock[Unidad],'91_KPIS'!$T22)) | G29: =IF($B29="","",INDEX(tblStock[StockActual],'91_KPIS'!$T22)) | H29: =IF($B29="","",INDEX(tblStock[StockMin],'91_KPIS'!$T22)) | I29: =IF($B29="","",INDEX(tblStock[StockMax],'91_KPIS'!$T22)) | J29: =IF($B29="","",INDEX(tblStock[Estado],'91_KPIS'!$T22)) | K29: =IF($B29="","",MAX(0,IF($I29>0,$I29,2*$H29)-MAX(0,$G29))) | L29: =IF($B29="","",INDEX(tblStock[CostoUnitario],'91_KPIS'!$T22)) | M29: =IF($B29="","",$K29*$L29)
B30: =IF('91_KPIS'!$T23="","",16) | C30: =IF($B30="","",IF(INDEX(tblStock[Proveedor],'91_KPIS'!$T23)="","(Sin proveedor)",INDEX(tblStock[Proveedor],'91_KPIS'!$T23))) | D30: =IF($B30="","",INDEX(tblStock[SKU],'91_KPIS'!$T23)) | E30: =IF($B30="","",INDEX(tblStock[Producto],'91_KPIS'!$T23)) | F30: =IF($B30="","",INDEX(tblStock[Unidad],'91_KPIS'!$T23)) | G30: =IF($B30="","",INDEX(tblStock[StockActual],'91_KPIS'!$T23)) | H30: =IF($B30="","",INDEX(tblStock[StockMin],'91_KPIS'!$T23)) | I30: =IF($B30="","",INDEX(tblStock[StockMax],'91_KPIS'!$T23)) | J30: =IF($B30="","",INDEX(tblStock[Estado],'91_KPIS'!$T23)) | K30: =IF($B30="","",MAX(0,IF($I30>0,$I30,2*$H30)-MAX(0,$G30))) | L30: =IF($B30="","",INDEX(tblStock[CostoUnitario],'91_KPIS'!$T23)) | M30: =IF($B30="","",$K30*$L30)
B31: =IF('91_KPIS'!$T24="","",17) | C31: =IF($B31="","",IF(INDEX(tblStock[Proveedor],'91_KPIS'!$T24)="","(Sin proveedor)",INDEX(tblStock[Proveedor],'91_KPIS'!$T24))) | D31: =IF($B31="","",INDEX(tblStock[SKU],'91_KPIS'!$T24)) | E31: =IF($B31="","",INDEX(tblStock[Producto],'91_KPIS'!$T24)) | F31: =IF($B31="","",INDEX(tblStock[Unidad],'91_KPIS'!$T24)) | G31: =IF($B31="","",INDEX(tblStock[StockActual],'91_KPIS'!$T24)) | H31: =IF($B31="","",INDEX(tblStock[StockMin],'91_KPIS'!$T24)) | I31: =IF($B31="","",INDEX(tblStock[StockMax],'91_KPIS'!$T24)) | J31: =IF($B31="","",INDEX(tblStock[Estado],'91_KPIS'!$T24)) | K31: =IF($B31="","",MAX(0,IF($I31>0,$I31,2*$H31)-MAX(0,$G31))) | L31: =IF($B31="","",INDEX(tblStock[CostoUnitario],'91_KPIS'!$T24)) | M31: =IF($B31="","",$K31*$L31)
B32: =IF('91_KPIS'!$T25="","",18) | C32: =IF($B32="","",IF(INDEX(tblStock[Proveedor],'91_KPIS'!$T25)="","(Sin proveedor)",INDEX(tblStock[Proveedor],'91_KPIS'!$T25))) | D32: =IF($B32="","",INDEX(tblStock[SKU],'91_KPIS'!$T25)) | E32: =IF($B32="","",INDEX(tblStock[Producto],'91_KPIS'!$T25)) | F32: =IF($B32="","",INDEX(tblStock[Unidad],'91_KPIS'!$T25)) | G32: =IF($B32="","",INDEX(tblStock[StockActual],'91_KPIS'!$T25)) | H32: =IF($B32="","",INDEX(tblStock[StockMin],'91_KPIS'!$T25)) | I32: =IF($B32="","",INDEX(tblStock[StockMax],'91_KPIS'!$T25)) | J32: =IF($B32="","",INDEX(tblStock[Estado],'91_KPIS'!$T25)) | K32: =IF($B32="","",MAX(0,IF($I32>0,$I32,2*$H32)-MAX(0,$G32))) | L32: =IF($B32="","",INDEX(tblStock[CostoUnitario],'91_KPIS'!$T25)) | M32: =IF($B32="","",$K32*$L32)
